Workbook

Sheet 5.000 UTM - 2026
A1: N° | B1: Código | C1: Verif | D1: Nombre | E1: Comuna | F1: Provincia | G1: Ingreso Of. Partes | H1: Monto propuesto M$ | I1: Monto RecomendadoM$ | J1: Etapa | K1: Proceso | L1: Sector | M1: Observaciones | N1: Comité | O1: Oficios cargados a bip | P1: Objetivo del Pladeco | Q1: Lineamiento ERD | R1: Plan del Gobernador | S1: H | T1: M | U1: TOT | V1: Unidad Tecnica | W1: Formulador Proyecto | X1: ORD. Ingreso N° | Y1: Fecha Ord. | Z1: N° Exped. | AA1: Ingreso Of. Partes | AB1: Ingreso Of. Planificación | AC1: Fecha Derivado a Evaluador | AD1: Plazo evaluación | AE1: Derivado Unidad Técnica Evaluadora | AF1: Fecha Derivación | AG1: Ev. DIT | AH1: Reingreso Depto. Planif. | AI1: Fecha Evaluación | AJ1: observaciones Ord. Gore N° | AK1: Fecha Ord. | AL1: Fecha Ficha Evaluación | AM1: Informa | AN1: Ord.Resp. Obs. | AO1: Fecha Ord. | AP1: N° EXP. | AQ1: Ingreso Oficina | AR1: ORD. GORE Observaciones | AS1: Fecha Ord. | AT1: Ord. | AU1: Fecha ORD. | AV1: Fecha Recomendación (Evaluación) | AW1: Estado Proyecto | AX1: Dentro de 15 días | AY1: Iteraciones
A2: 1 | B2: 40076838 | C2: 0 | D2: Construcción Garitas Peatonales Purranque y Corte Alto | E2: Purranque | F2: =+IFERROR(VLOOKUP(E2,'Feriados y Comunas'!$C$1:$D$36,2,FALSE),"") -> OSORNO | G2: 45987 | H2: 222616 | I2: 222616 | J2: Ejecución | K2: 2026 | L2: Multisectorial | M2: Ok - Oficio 035 07-01- 26 | O2: ok | Q2: Se encuentra dentro de la ERD en el: Lineamiento: Bienestar Socio Territorial. Ítem: Espacios y Equipamiento Publico. Objetivo: Construir equipamientos públicos y espacios de carácter cívico en la región. Actividad: No Hay. | R2: Se enlaza con el Programa Regional del Gobernador: - Pilar 3. Inclusión Social y Mejoramiento de la Calidad de Vida. | S2: 6388 | T2: 7565 | U2: =SUM(S2:T2) -> 13953 | V2: Municipalidad Purranque | W2: Municipalidad Purranque | X2: 687 | Y2: 45994 | AA2: 45995 | AB2: 45995 | AC2: 45995 | AD2: =WORKDAY(AC2,15,'Feriados y Comunas'!A$2:A$26) -> 46020 | AE2: D Castro | AJ2: 3260 035 | AK2: 09-12-2025 07-01-2026 | AL2: 04-12-2025 30-12-2025 | AM2: OBSERVADO SIN OBS | AN2: 738 | AO2: 46020 | AQ2: 46021 | AV2: 46021 | AW2: Recomendado | AX2: 4 | AY2: 2
A3: 2 | B3: 40077324 | C3: 0 | D3: Mejoramiento Integral Espacio Público Sector Los Canelos, Hornopiren, Hualaihué. | E3: Hualaihué | F3: =+IFERROR(VLOOKUP(E3,'Feriados y Comunas'!$C$1:$D$36,2,FALSE),"") -> PALENA | G3: 46000 | H3: 328738 | I3: 328738 | J3: Ejecución | K3: 2026 | L3: Multisectorial | M3: Ok - Oficio 037 07-01-26 | O3: ok | Q3: Se encuentra dentro de la ERD en: Lineamiento: Bienestar Socio Territorial. Ítem: Espacios y Equipamiento Publico. Objetivo: Construir nuevas áreas verdes de uso publico como herramienta de esparcimiento e integración barrial en las ciudades de la región. Actividad: Programa regional de construcción y reposición de áreas verdes. | R3: Se enlaza con el Programa Regional del Gobernador en el Pilar: 1. Políticas Públicas en Materia de Seguridad Ciudadana Letra: i) Espacios Seguros: Mejorar la iluminación y la seguridad en parques, plazas y áreas públicas para garantizar espacios seguros para todos los habitantes. | S3: 89 | T3: 81 | U3: =SUM(S3:T3) -> 170 | V3: Municipalidad Hualiahue | W3: Municipalidad Hualiahue | X3: 1585 | Y3: 46000 | AA3: 46000 | AB3: 46000 | AC3: 46000 | AD3: =WORKDAY(AC3,15,'Feriados y Comunas'!A$2:A$26) -> 46022 | AE3: D Castro | AJ3: 3354 037 | AK3: 18-12-2025 07-01-2026 | AL3: 18-12-2025 30-12-2025 | AM3: OBSERVADO SIN OBS | AN3: - | AO3: - | AQ3: - | AV3: 46021 | AW3: Recomendado | AX3: 2 | AY3: 2
A4: 3 | B4: 40041153 | C4: 0 | D4: Mejoramiento Cementerio Municipal, Comuna de Queilen | E4: Queilén | F4: CHILOÉ | G4: 46000 | H4: 325000 | I4: 325000 | J4: Ejecución | K4: 2026 | L4: Multisectorial | M4: Ok - Oficio 251 05-02-26 | O4: ok | Q4: Se encuentra dentro de la ERD en: Lineamiento: Bienestar Socio Territorial. Ítem: Espacios y Equipamiento Publico. Objetivo: Construir nuevas áreas verdes de uso publico como herramienta de esparcimiento e integración barrial en las ciudades de la región. Actividad: Programa regional de construcción y reposición de áreas verdes. | R4: Se enlaza con el Programa Regional del Gobernador en el Pilar: 1. Políticas Públicas en Materia de Seguridad Ciudadana Letra: i) Espacios Seguros: Mejorar la iluminación y la seguridad en parques, plazas y áreas públicas para garantizar espacios seguros para todos los habitantes. | S4: 2798 | T4: 2745 | U4: =SUM(S4:T4) -> 5543 | V4: Municipalidad Queilen | W4: Municipalidad Queilen | X4: 1201 | Y4: 45996 | AA4: 45996 | AB4: 45996 | AC4: 46002 | AD4: =WORKDAY(AC4,15,'Feriados y Comunas'!A$2:A$26) -> 46024 | AE4: D Castro | AJ4: 251 | AK4: 46058 | AL4: 46007 | AM4: SIN OBS | AN4: - | AO4: - | AQ4: - | AV4: 46007 | AW4: Recomendado | AY4: 1
A5: 4 | B5: 40055485 | C5: 0 | D5: Mejoramiento Edificio Centro Atención Integral (CAI) | E5: San Pablo | F5: =+IFERROR(VLOOKUP(E5,'Feriados y Comunas'!$C$1:$D$36,2,FALSE),"") -> OSORNO | G5: 45917 | H5: 300000 | I5: 300000 | J5: Ejecución | K5: 2026 | L5: Salud | M5: ok - Oficio 297 10-02-2026 | N5: 46091 | O5: ok | Q5: Se encuentra dentro de la ERD en el - Lineamiento: Bienestar Socio Territorial. - Ítem: Salud. - Objetivo: Aumentar Cobertura de atención primaria en salud en la comunas de la región. - Actividad: | R5: Se enlaza con el programa del Gobernador Regional en el - Pilar: 3. Inclusión Social y Mejoramiento de la Calidad de Vida. - Letra: e) Acceso a Servicios de Salud: Ampliar y mejorar la red de servicios de salud, especialmente en zonas rurales, garantizando atención médica de calidad para todos. | S5: 5345 | T5: 5364 | U5: =SUM(S5:T5) -> 10709 | V5: Municipalidad San Pablo | W5: Municipalidad San Pablo | X5: 656 | Y5: 45915 | AA5: 45917 | AB5: 45917 | AC5: 45917 | AD5: =WORKDAY(AC5,15,'Feriados y Comunas'!A$2:A$26) -> 45940 | AE5: D Castro | AJ5: 2607 3259 ?? 297 | AK5: 08-10-2025 09-12-2025 ?? 10-02-2026 | AL5: 03-10-2025 27-11-2025 15-01-2025 06-02-2026 | AM5: OBSERVADO OBSERVADO OBSERVADO SIN OBS | AN5: 779 63 41 | AO5: 17-11-2025 31-12-2025 26-01-2026 | AQ5: 18-11-2025 05-01-2026 27-01-2026 | AR5: 2607 3259 ?? 297 | AS5: 08-10-2025 09-12-2025 ?? 10-02-2026 | AV5: 46059 | AW5: Recomendado | AX5: 10 | AY5: =IFERROR(__xludf.DUMMYFUNCTION("IFERROR(COUNTA(SPLIT(AK5, "" "")), 0)"),4.0) -> 4
A6: 5 | B6: 40073440 | C6: 0 | D6: Mejoramiento Acceso Poniente | E6: Futaleufú | F6: =+IFERROR(VLOOKUP(E6,'Feriados y Comunas'!$C$1:$D$36,2,FALSE),"") -> PALENA | G6: 45903 | H6: 230000 | I6: 230000 | J6: Ejecución | K6: 2026 | L6: Seguridad | M6: ok - Oficio 125 19-01-2026 | N6: 46091 | O6: ok | Q6: Se encuentra dentro de los lineamientos de la ERD en - Lineamiento: Conectividad y Movilidad Regional Sustentable. - Ítem: Movilidad Sostenible. - Obj.: Extender y Mejorar las aceras peatonales en localidades urbanas. - Actividad: Plan de inversión en infraestructura vialidad menor. | R6: Se enlaza con el Programa Regional del Gobernador en el - Pilar: 2. Desarrollo Económico Sostenible: una Alianza Público-Privada - Letra: c)Inversiones en Infraestructura: Mejorar la conectividad y la infraestructura regional para atraer inversiones y generar empleo. | S6: 1542 | T6: 1520 | U6: =SUM(S6:T6) -> 3062 | V6: Municipalidad Futaleufu | W6: Municipalidad Futaleufu | X6: 406 | Y6: 45902 | AA6: 45903 | AB6: 45903 | AC6: 45903 | AD6: =WORKDAY(AC6,15,'Feriados y Comunas'!A$2:A$26) -> 45926 | AE6: D Castro | AJ6: 2605 3075 125 | AK6: 08-10-2025 14-11-2025 19-01-2026 | AL6: 29-09-2025 10-11-2025 14-11-2025 | AM6: OBSERVADO OBSERVADO SIN OBS | AN6: 530 ??? | AO6: 29-10-2025 ??? | AQ6: 03-11-2025 ??? | AR6: 2605 3075 | AS6: 08-10-2025 14-11-2025 | AV6: 45975 | AW6: Recomendado | AX6: 19 | AY6: =IFERROR(__xludf.DUMMYFUNCTION("IFERROR(COUNTA(SPLIT(AK6, "" "")), 0)"),3.0) -> 3
A7: 6 | B7: 40071265 | C7: 0 | D7: Reposición Sede Social y Camarines Club Deportivo El Bosque | E7: Dalcahue | F7: CHILOÉ | G7: 46104 | H7: 337129 | I7: 337129 | J7: Ejecución | K7: 2026 | L7: Deportes | M7: ok - Oficio 1127 13-05-2026 | N7: 46178 | O7: ok | Q7: Bienestar socioterritorial: "Construir equipamientos públicos y espacios de carácter cívico en la región", fortaleciendo la infraestructura básica en zonas rurales.Fortalecimiento de la organización social: El proyecto responde a la necesidad de espacios para la "articulación entre organizaciones comunitarias rurales", contribuyendo al fortalecimiento del tejido social. | R7: La propuesta se articula con los siguientes pilares programáticos del programa de gobierno, presentados en el orden jerárquico establecido: 3. Inclusión Social y Calidad de Vida "Programas de Apoyo Social: Desarrollar iniciativas para apoyar a los sectores más vulnerables de nuestra comunidad". (Aplica al proveer infraestructura adecuada a organizaciones rurales que carecen de espacios dignos) . "Infraestructura Comunitaria: Fomentar la construcción y mejoramiento de sedes sociales y recintos comunitarios para fortalecer la vida barrial". 4. Participación Ciudadana y Gobernanza "Participación Ciudadana: Fomentar la participación activa de la comunidad en la toma de decisiones". (El proyecto se sustenta en un diagnóstico participativo con diversas agrupaciones locales, incluyendo el Club Deportivo y Juntas de Vecinos) . | S7: 145 | T7: 140 | U7: 285 | V7: MUNICIPALIDAD DE DALCAHUE | W7: MUNICIPALIDAD DE DALCAHUE | X7: 90 | Y7: 46101 | AA7: 46104 | AB7: 46105 | AC7: 46105 | AD7: =WORKDAY(AC7,15,'Feriados y Comunas'!A$2:A$26) -> 46126 | AE7: Dcastro | AJ7: 901 1127 | AK7: 21-042026 13-05-2026 | AL7: 20-04-2026 11-05-2026 | AM7: OBSERVADO SIN OBS | AN7: 143 | AO7: 46140 | AQ7: 46141 | AV7: 46153 | AW7: Recomendado | AY7: =IFERROR(__xludf.DUMMYFUNCTION("IFERROR(COUNTA(SPLIT(AK7, "" "")), 0)"),2.0) -> 2
A8: 7 | B8: 40073338 | C8: 0 | D8: Reposición Estacion Medico Rural Puchilco | E8: Puqueldón | F8: =+IFERROR(VLOOKUP(E8,'Feriados y Comunas'!$C$1:$D$36,2,FALSE),"") -> CHILOÉ | G8: 45813 | H8: 202086 | I8: 203117 | J8: Ejecución | K8: 2026 | L8: Salud | M8: ok - Oficio 327 17-02-2026 | N8: Pendiente | O8: ok | Q8: Se encuentra dentro de la ERD en el - Lineamiento: Bienestar Socio Territorial. - Ítem: Salud. - Objetivo: Aumentar Cobertura de atención primaria en salud en la comunas de la región. - Actividad: Convenio de Programación. | R8: Se enlaza con el programa del Gobernador Regional en el - Pilar: 3. Inclusión Social y Mejoramiento de la Calidad de Vida. - Letra: e) Acceso a Servicios de Salud: Ampliar y mejorar la red de servicios de salud, especialmente en zonas rurales, garantizando atención médica de calidad para todos. | S8: 184 | T8: 190 | U8: =SUM(S8:T8) -> 374 | V8: Municipalidad Puqueldon | W8: Municipalidad Puqueldon | X8: 397 | Y8: 45811 | AA8: 45813 | AB8: 45813 | AC8: 45813 | AD8: =WORKDAY(AC8,15,'Feriados y Comunas'!A$2:A$26) -> 45835 | AE8: Dcastro | AJ8: 1502 327 725 1606 | AK8: 30-06-2025 17-02-2026 08-04-2026 26-06-2026 | AL8: 13-06-2025 17-02-2026 07-04-2026 26-06-2026 | AM8: OBSERVADO OBSERVADO OBSERVADO SIN OBS | AN8: 68 120 377 | AO8: 10-02-2026 11-03-2026 11-06-2026 | AR8: 1502 | AS8: 45838 | AV8: 46199 | AW8: Recomendado | AX8: 6 | AY8: =IFERROR(__xludf.DUMMYFUNCTION("IFERROR(COUNTA(SPLIT(AK8, "" "")), 0)"),4.0) -> 4
A9: 8 | B9: 40070963 | C9: 0 | D9: Mejoramiento Sistema de Alcantarillado y Aguas Superficiales Pescaderia Feria Yumbel. | E9: Castro | F9: =+IFERROR(VLOOKUP(E9,'Feriados y Comunas'!$C$1:$D$36,2,FALSE),"") -> CHILOÉ | G9: 45922 | H9: 313141 | I9: 326592 | J9: Ejecución | K9: 2026 | L9: Turismo | M9: ok - Oficio 1861 22-07-2026 | N9: 46178 | O9: ok | Q9: La iniciativa es plenamente coherente con el lineamiento de "Bienestar socioterritorial", enfocado en la provisión de servicios públicos de calidad: Infraestructura Pública: Contribuye al objetivo de "Lograr que la comunidad cuente con infraestructura y equipamiento necesario para desenvolverse de buena manera, generando las condiciones para mejorar crecientemente la calidad de vida de los habitantes". | R9: La propuesta se articula con los siguientes pilares programáticos del programa de gobierno: Inclusión Social y Calidad de Vida "Programas de Apoyo Social: Desarrollar iniciativas para apoyar a los sectores más vulnerables de nuestra comunidad". (Aplica al apoyo directo a los locatarios de la feria y mejora de sus condiciones laborales). | S9: 1900 | T9: 2001 | U9: =SUM(S9:T9) -> 3901 | V9: Municipalidad Castro | W9: Municipalidad Castro | X9: 946 | Y9: 45909 | AA9: 45922 | AB9: 45922 | AC9: 45922 | AD9: =WORKDAY(AC9,15,'Feriados y Comunas'!A$2:A$26) -> 45943 | AE9: Dcastro | AJ9: 2822 3258 385 1069 1349 1861 | AK9: 27-10-2025 09-12-2025 02-03-2026 11-05-2026 03-06-2026 22-07-2026 | AL9: 27-10-2025 09-12-2026 02-03-2026 08-05-2026 03-06-2026 21-07-2026 | AM9: OBSERVADO OBSERVADO OBSERVADO OBSERVADO OBSERVADO SIN OBS | AN9: 1231 162 332 543 812 | AO9: 14-11-2025 05-02-2026 17-03-2026 15-05-2026 03-06-2026 | AQ9: 17-11-2025 17-02-2026 15-04-2026 15-05-2026 03-06-2026 | AR9: 2822 3258 385 | AS9: 27-10-2025 09-12-2025 02-03-2026 | AV9: 46224 | AW9: Recomendado | AX9: 23 | AY9: =IFERROR(__xludf.DUMMYFUNCTION("IFERROR(COUNTA(SPLIT(AK9, "" "")), 0)"),6.0) -> 6
A10: 9 | B10: 40075634 | C10: 0 | D10: Mejoramiento Plaza Villa Los Rios | E10: Fresia | F10: =+IFERROR(VLOOKUP(E10,'Feriados y Comunas'!$C$1:$D$36,2,FALSE),"") -> LLANQUIHUE | G10: 45930 | H10: 332400 | I10: 269828 | J10: Ejecución | K10: 2026 | L10: Multisectorial | M10: ok - Oficio 1694 02-07-2026 | N10: Pendiente | O10: ok | Q10: Se encuentra dentro de la ERD en: - Lineamiento: Bienestar Socio Territorial. - Ítem: Espacios y Equipamiento Publico. - Objetivo: Construir nuevas áreas verdes de uso publico como herramienta de esparcimiento e integración barrial en las ciudades de la región. - Actividad: Programa regional de construcción y reposición de áreas verdes. | R10: Se enlaza con el Programa Regional del Gobernador en el - Pilar: 1. Políticas Públicas en Materia de Seguridad Ciudadana - Letra: i) Espacios Seguros: Mejorar la iluminación y la seguridad en parques, plazas y áreas públicas para garantizar espacios seguros para todos los habitantes. | S10: 3830 | T10: 4039 | U10: =SUM(S10:T10) -> 7869 | V10: Municipalidad Fresia | W10: Municipalidad Fresia | X10: 786 | Y10: 45929 | AA10: 45930 | AB10: 45930 | AC10: 45930 | AD10: =WORKDAY(AC10,15,'Feriados y Comunas'!A$2:A$26) -> 45951 | AE10: Dcastro | AJ10: 2827 3076 1251 1694 | AK10: 27-10-2025 14-11-2025 25-05-2026 02-07-2026 | AL10: 23-10-2025 14-11-2025 22-05-2026 01-07-2026 | AM10: OBSERVADO OBSERVADO OBSERVADO SIN OBS | AN10: 888 288 377 | AO10: 6-11-2025 11-05-2026 11-06-2026 | AQ10: 6-11-2025 05-05-2026 16-06-2026 | AR10: 2827 3076 | AS10: 27-10-2025 14-11-2025 | AV10: 46204 | AW10: Recomendado | AX10: 17 | AY10: =IFERROR(__xludf.DUMMYFUNCTION("IFERROR(COUNTA(SPLIT(AK10, "" "")), 0)"),4.0) -> 4
A11: 10 | B11: 40073904 | C11: 0 | D11: Mejoramiento Espacio Público Sargento Candelaria Norte, Chonchi. | E11: Chonchi | F11: =+IFERROR(VLOOKUP(E11,'Feriados y Comunas'!$C$1:$D$36,2,FALSE),"") -> CHILOÉ | G11: 45975 | H11: 336000 | I11: 320000 | J11: Ejecución | K11: 2026 | L11: Multisectorial | M11: ok - Oficio 1911 22-07-2026 | N11: Pendiente | O11: ok | Q11: Se encuentra dentro de la ERD en: - Lineamiento: Bienestar Socio Territorial. - Ítem: Espacios y Equipamiento Publico. - Objetivo: Construir nuevas áreas verdes de uso publico como herramienta de esparcimiento e integración barrial en las ciudades de la región. - Actividad: Programa regional de construcción y reposición de áreas verdes. | R11: Se enlaza con el Programa Regional del Gobernador en el - Pilar: 1. Políticas Públicas en Materia de Seguridad Ciudadana - Letra: i) Espacios Seguros: Mejorar la iluminación y la seguridad en parques, plazas y áreas públicas para garantizar espacios seguros para todos los habitantes. | S11: 2865 | T11: 2854 | U11: =SUM(S11:T11) -> 5719 | V11: Municipalidad Chonchi | W11: Municipalidad Chonchi | X11: 1018 | Y11: 45975 | AC11: 45975 | AD11: =WORKDAY(AC11,15,'Feriados y Comunas'!A$2:A$26) -> 45996 | AE11: Dcastro | AJ11: 3355 1103 1491 1911 | AK11: 18-12-2025 12-05-2026 17-06-2026 22-07-2026 | AL11: 18-12-2025 11-05-2026 16-06-2026 21-07-2026 | AM11: OBSERVADO OBSERVADO OBSERVADO SIN OBS | AN11: 348 475 559 | AO11: 04-05-2026 12-06-2026 09-07-2026 | AQ11: 04-05-2026 15-06-2026 09-07-2026 | AR11: 3355 | AS11: 46009 | AV11: 46224 | AW11: Recomendado | AX11: 20 | AY11: =IFERROR(__xludf.DUMMYFUNCTION("IFERROR(COUNTA(SPLIT(AK11, "" "")), 0)"),4.0) -> 4
A12: 11 | B12: 40078509 | C12: 0 | D12: CONSTRUCCION INFRAESTRUCTURA RECREATIVA Y AREA VERDE SECTOR PILMAIQUEN, COMUNA DE PUYEHUE | E12: Puyehue | F12: =+IFERROR(VLOOKUP(E12,'Feriados y Comunas'!$C$1:$D$36,2,FALSE),"") -> OSORNO | G12: 46231 | H12: 163832 | I12: 193063 | J12: Ejecución | K12: 2026 | L12: Vivienda | M12: ok - Oficio 2613 01-09-2026 | N12: Pendiente | O12: ok | S12: 330 | T12: 340 | U12: 670 | V12: MUNICIPALIDAD DE PUYEHUE | W12: MUNICIPALIDAD DE PUYEHUE | X12: 880 | Y12: 46230 | AA12: 46231 | AB12: 46231 | AC12: 46231 | AD12: =WORKDAY(AC12,15,'Feriados y Comunas'!A$2:A$26) -> 46252 | AE12: HSolervicens DCastro HSolervicens DCastro Dcastro Dcastro | AJ12: 1996 2152 2291 2375 2485 2613 | AK12: 29-07-2026 05-08-2026 17-08-2026 19-08-2026 24-08-2026 01-09-2026 | AL12: 29-07-2026 05-08-2026 17-08-2026 19-08-2026 24-08-2026 28-08-2026 | AM12: OBSERVADO OBSERVADO OBSERVADO OBSERVADO OBSERVADO SIN OBS | AN12: 915 939 963 979 1000 | AO12: 4-08-2026 11-08-2026 18-08-2026 19-08-2026 25-08-2026 | AQ12: 5-08-2026 11-08-2026 18-08-2026 19-08-2026 26-08-2026 | AV12: 46262 | AW12: Recomendado | AY12: =IFERROR(__xludf.DUMMYFUNCTION("IFERROR(COUNTA(SPLIT(AK12, "" "")), 0)"),6.0) -> 6
A13: 12 | B13: 40073550 | C13: 0 | D13: Construcción Centro Comunitario el Jardin | E13: Fresia | F13: =+IFERROR(VLOOKUP(E13,'Feriados y Comunas'!$C$1:$D$36,2,FALSE),"") -> LLANQUIHUE | G13: 45923 | H13: 213266 | J13: Ejecución | K13: 2026 | L13: Multisectorial | M13: POSTULADO A FRIL. SE BAJA INICIATIVA EN MENOR A 5000 UTM 1. Revisar costo por metro cuadrado superior al promedio regional. 2. Ajustar Ppto. con Ficha IDI. 3. Anexar Certificación Secplan – DOM. 4. Incorporar Carta de No fraccionamiento Visada por Dpto. Jurídico. 5. Desarrollar análisis de alternativas. 6. Adjuntar documentación al BIP. GENERALES 1. Incorporar pronunciamiento, aprobación o visación de la Dirección de Vialidad del MOP. 2. Carta del alcalde de no fraccionamiento. PLANOS E INGENERÍA 1. Los planos de estructura deben incorporar la firma del profesional responsable, indicando nombre y profesión como mínimo. 2. Memoria de agua potable y aguas servidas deben incorporar firma a mano alzada o digital. ANEXOS 1. Incorporar lo señalado en 5.8. b) Ficha IDI 2. Incorporar lo señalado en 5.8. m) Certificado Compromiso de Absorción de Costos de operación y mantención. - Certificado de factibilidad eléctrica adjunto perdió validez. El plazo es muy acotado. TERRENO Y OTROS 1. Se solicita incorporar Resolución de Destinación o Contrato de Comodato vigente emitido por Bienes Nacionales. Certificado adjunto menciona que proyecto será presentado al fondo regional de iniciativa local. Corregir. | N13: 45953 | Q13: Se encuentra dentro de la ERD en el: Lineamiento: Bienestar Socio Territorial. Ítem: Espacios y Equipamiento Publico. Objetivo: Construir equipamientos públicos y espacios de carácter cívico en la región. Actividad: No Hay. | R13: Se enlaza con el Programa Regional del Gobernador: Pilar 3. Inclusión Social y Mejoramiento de la Calidad de Vida. Letra c) Programas de Apoyo Social: Desarrollar iniciativas para apoyar a los sectores más vulnerables de nuestra comunidad. | S13: 128 | T13: 110 | U13: =SUM(S13:T13) -> 238 | V13: Municipalidad Fresia | W13: Municipalidad Fresia | X13: 756 | Y13: 45915 | AA13: 45923 | AB13: 45923 | AC13: 45923 | AD13: =WORKDAY(AC13,15,'Feriados y Comunas'!A$2:A$26) -> 45944 | AE13: Dcastro | AJ13: 2828 3257 | AK13: 27-10-2025 09-12-2025 | AL13: 23/10/2025 09-12-2025 | AM13: OBSERVADO OBSERVADO | AN13: 899 | AO13: 45972 | AQ13: 45972 | AR13: 2828 | AS13: 45957 | AW13: Dado de baja | AX13: 22 | AY13: =IFERROR(__xludf.DUMMYFUNCTION("IFERROR(COUNTA(SPLIT(AK13, "" "")), 0)"),2.0) -> 2
A14: 13 | B14: 40073716 | C14: 0 | D14: Mejoramiento Multicanchas ST Michelle Bachelet | E14: Puerto Varas | F14: =+IFERROR(VLOOKUP(E14,'Feriados y Comunas'!$C$1:$D$36,2,FALSE),"") -> LLANQUIHUE | G14: 45960 | H14: 140909 | J14: Ejecución | K14: 2026 | L14: Deportes | M14: POSTULADO A FRIL. SE BAJA INICIATIVA EN MENOR A 5000 UTM 1. A nivel de alternativas describir con mayor detalle la intervención de la infraestructura. 2. Adjuntar Certificado de Informes previos. 3. Anexas Informe Técnico situación actual por profesional del área. 4. Incorporar factibilidad. 5. Adjuntar carta de no fraccionamiento firmado por el alcalde y visado por depto. jurídico. 6. Anexar Certificado de BNUP. 7. Incorporar KMZ. 8. Adjuntar documentación al BIP. GENERALES 1. Incluir carta de no fraccionamiento firmada por alcalde. ESTUDIO PREINVERSIONAL 2. Documento debe estar firmado por unidad formuladora y en formato PDF. TTR y,o EETT 3. Partida 2.5.3. señalada en EETT no se encuentra incluida en Carta Gantt PLANOS E INGENERÍA 4. Para el correcto y adecuado desarrollo de las actividades deportivas, el diseño de la multicancha deberá estar acorde a las disposiciones del Instituto Nacional de Deporte (IND), en cuanto a las dimensiones y requerimientos de las disciplinas consideradas en el proyecto. El diseño actual no cumple con las dimensiones mínimas. Se recomienda revisar “Manual de construcción y requisitos mínimos para parques, plazas, áreas verdes y áreas deportivas, MINVU, 2017”- 5. EL muro de escalada sobre la estructura de cierro de la multicancha debe ser estructuralmente validado. ANEXOS 6. Adjuntar b) Ficha IDI 7. Adjuntar h) Factibilidad eléctrica. | N14: 45975 | Q14: La iniciativa se orienta dentro de la ERD en el: - Lineamiento: Bienestar Socio Territorial. - Ítem: Espacios y Equipamiento Público - Objetivo: Aumentar el Nro. De espacios polideportivos en la región con criterios de genero e inclusividad. - Actividad: No hay. | R14: Se enlaza con el Programa Regional del Gobernador: - Pilar: 3. Inclusión Social y Mejoramiento de la Calidad de Vida. - Letra: c) Programas de Apoyo Social: Desarrollar iniciativas para apoyar a los sectores más vulnerables de nuestra comunidad. | S14: 1059 | T14: 1159 | U14: =SUM(S14:T14) -> 2218 | V14: Municipalidad Puerto Varas | W14: Municipalidad Puerto Varas | X14: 72 | Y14: 45960 | AA14: 45964 | AB14: 45964 | AC14: 45964 | AD14: =WORKDAY(AC14,15,'Feriados y Comunas'!A$2:A$26) -> 45985 | AE14: Dcastro | AJ14: 3077 | AL14: 45975 | AM14: OBSERVADO | AR14: 3077 | AS14: 45975 | AW14: Dado de baja | AX14: 10 | AY14: =IFERROR(__xludf.DUMMYFUNCTION("IFERROR(COUNTA(SPLIT(AK14, "" "")), 0)"),1.0) -> 1
A15: 14 | B15: 40066308 | C15: 0 | D15: Construcción Centro Comunitario ST Pureo | E15: Queilén | F15: =+IFERROR(VLOOKUP(E15,'Feriados y Comunas'!$C$1:$D$36,2,FALSE),"") -> CHILOÉ | G15: 45749 | H15: 212093 | J15: Ejecución | K15: 2026 | L15: Multisectorial | M15: 1. Ajustar la Demanda. 2. Incorporar estratificación social. 3. Anexar Ppto. AITO. 4. Adjuntar Mecánica de Suelos. 5. Incorporar Revisores independiente. 6. Anexar Modelo de Gestión. 7. Adjuntar documentación al BIP. 1. De acuerdo a lo solicitado por Departamento jurídico del Gobierno Regional, deberá presentar certificado de alcalde y validado por su Departamento jurídico que señale lo siguiente: “El proyecto no considera restricciones técnicas, legales ni administrativas para su posterior ejecución. Por otra parte, se declara que el proyecto en cuestión no corresponde al fraccionamiento de una iniciativa de mayor envergadura”. 2. Los procesos son anuales, por lo tanto, deberá actualizar información del perfil al presente año 2025. 3. Revisar el Perfil del proyecto no cuadra el presupuesto ingresado con el presentado. 4. Revisar punto 5.8 letra d) Informe Técnico de Emplazamiento: 5. Sin Archivo de georreferenciación. 6. Las Especificaciones Técnicas, incluye placa modelo FRIL, Letrero Modelo FRIL, el financiamiento aplica al FRIL. 7. Presupuesto: El presentado no cuadra con el perfil, recordar Tanto el Presupuesto como la Carta Gantt deben tener los mismos elementos que las EETT. 8. Respecto a Planimetría, debe revisar instructivo y considerar lo faltante. 9. Se presenta un certificado de declaración jurada de la propiedad el que corresponde al FRIL. 10. Respecto a certificaciones, en general debe considerar que estas deben contener: fecha, nombre del proyecto y código BIP, así también debe considerar lo siguiente: Revisar instructivo y presentar Certificado del DOM, tal como se solicita. Falta permiso de edificación, revisar instructivo. 11. Informe de Revisores Independientes de Arquitectura e Ingeniería. 12. Falta Plan de Mitigación durante la ejecución de las Obras. 13. Falta Carta Gantt del proyecto. 14. Falta Actualizar factibilidades. | N15: 45806 | Q15: Se encuentra dentro de la ERD en el: Lineamiento: Bienestar Socio Territorial. Ítem: Espacios y Equipamiento Publico. Objetivo: Construir equipamientos públicos y espacios de carácter cívico en la región. Actividad: No Hay. | R15: Se enlaza con el Programa Regional del Gobernador: - Pilar 3. Inclusión Social y Mejoramiento de la Calidad de Vida. - Letra c) Programas de Apoyo Social: Desarrollar iniciativas para apoyar a los sectores más vulnerables de nuestra comunidad. | S15: 175 | T15: 186 | U15: =SUM(S15:T15) -> 361 | V15: Municipalidad Queilen | W15: Municipalidad Queilen | X15: 207 | Y15: 45749 | AC15: 45750 | AD15: =WORKDAY(AC15,15,'Feriados y Comunas'!A$2:A$26) -> 45772 | AE15: D Castro | AJ15: 1165 | AK15: 45811 | AL15: 45806 | AM15: OBSERVADO | AR15: 1165 | AS15: 45811 | AW15: Observado | AX15: 37 | AY15: =IFERROR(__xludf.DUMMYFUNCTION("IFERROR(COUNTA(SPLIT(AK15, "" "")), 0)"),1.0) -> 1
A16: 15 | B16: 40066350 | C16: 0 | D16: Construcción Centro Comunitario Cheuquemo | E16: Río Negro | F16: =+IFERROR(VLOOKUP(E16,'Feriados y Comunas'!$C$1:$D$36,2,FALSE),"") -> OSORNO | G16: 45853 | H16: 164000 | J16: Ejecución | K16: 2026 | L16: Multisectorial | M16: 1. Actualizar certificados de la postulación FRIL 2. Incorporar anexos de acuerdo a instructivo. 3. Anexar Carta del alcalde de no fraccionamiento. 4. Adjuntar documentación al BIP. | N16: 18-07-25. | Q16: Se encuentra dentro de la ERD en el: Lineamiento: Bienestar Socio Territorial. Ítem: Espacios y Equipamiento Publico. Objetivo: Construir equipamientos públicos y espacios de carácter cívico en la región. Actividad: No Hay. | R16: Se enlaza con el Programa Regional del Gobernador: - Pilar 3. Inclusión Social y Mejoramiento de la Calidad de Vida. - Letra c) Programas de Apoyo Social: Desarrollar iniciativas para apoyar a los sectores más vulnerables de nuestra comunidad. | S16: 68 | T16: 80 | U16: =SUM(S16:T16) -> 148 | V16: Municipalidad Rio Negro | W16: Municipalidad Rio Negro | X16: 50 | Y16: 45852 | AA16: 45853 | AB16: 45853 | AC16: 45853 | AD16: =WORKDAY(AC16,15,'Feriados y Comunas'!A$2:A$26) -> 45875 | AJ16: 1669 | AK16: 45860 | AL16: 45856 | AM16: OBSERVADO | AR16: 1669 | AS16: 45860 | AW16: Observado | AX16: 2 | AY16: =IFERROR(__xludf.DUMMYFUNCTION("IFERROR(COUNTA(SPLIT(AK16, "" "")), 0)"),1.0) -> 1
A17: 16 | B17: 40066406 | C17: 0 | D17: Construcción Centro Comunitario Chan Chan | E17: Río Negro | F17: =+IFERROR(VLOOKUP(E17,'Feriados y Comunas'!$C$1:$D$36,2,FALSE),"") -> OSORNO | G17: 45853 | H17: 159000 | J17: Ejecución | K17: 2026 | L17: Multisectorial | M17: 1. Actualizar certificados de la postulación FRIL 2. Incorporar anexos de acuerdo a instructivo. 3. Anexar Carta del alcalde de no fraccionamiento. 4. Adjuntar documentación al BIP. | N17: 45856 | Q17: Se encuentra dentro de la ERD en el: Lineamiento: Bienestar Socio Territorial. Ítem: Espacios y Equipamiento Publico. Objetivo: Construir equipamientos públicos y espacios de carácter cívico en la región. Actividad: No Hay. | R17: Se enlaza con el Programa Regional del Gobernador: - Pilar 3. Inclusión Social y Mejoramiento de la Calidad de Vida. - Letra c) Programas de Apoyo Social: Desarrollar iniciativas para apoyar a los sectores más vulnerables de nuestra comunidad. | S17: 197 | T17: 204 | U17: =SUM(S17:T17) -> 401 | V17: Municipalidad Rio Negro | W17: Municipalidad Rio Negro | X17: 51 | Y17: 45853 | AA17: 45853 | AB17: 45853 | AC17: 45853 | AD17: =WORKDAY(AC17,15,'Feriados y Comunas'!A$2:A$26) -> 45875 | AJ17: 1670 | AK17: 45860 | AL17: 45856 | AM17: OBSERVADO | AR17: 1670 | AS17: 45860 | AW17: Observado | AX17: 2 | AY17: =IFERROR(__xludf.DUMMYFUNCTION("IFERROR(COUNTA(SPLIT(AK17, "" "")), 0)"),1.0) -> 1
A18: 17 | B18: 40074807 | C18: 0 | D18: Reposición Centro Comunitario Pob. Flor Naciente N°1 ST Changue | E18: Maullín | F18: =+IFERROR(VLOOKUP(E18,'Feriados y Comunas'!$C$1:$D$36,2,FALSE),"") -> LLANQUIHUE | G18: 45873 | H18: 160000 | J18: Ejecución | K18: 2026 | L18: Vivienda | M18: 1. Crear Ficha 2026. 2. Adjuntar Planta Emplazamiento. 3. Anexar Participación Ciudadana. 4. Incorporar Permiso de edificación. 5. Adjuntar Memoria. 6. Anexar Mecánica. 7. Incorporar Revisores independientes. 8. Adjuntar Cronograma. 9. Anexar Plan de Mitigación. 10. Incorporar Modelo de Gestión. 11. Adjuntar Informe Técnico Estado Actual. 12. Anexar IMIV si corresponde. 13. Incorporar Dominio Vigente. 14. Adjuntar Hipotecas y Gravámenes. 15. Anexar Informes Previos. 16. Incorporar Factibilidades. 17. Adjuntar Costos Operacionales. 18. Anexar Carta del alcalde de no fraccionamiento. 19. Incorporar análisis de alternativas y descripción detallada de la solución. 20. Los antecedentes no son suficientes para realizar análisis técnico. 21. Adjuntar documentación al BIP. | N18: 45877 | Q18: Se encuentra dentro de la ERD en el: Lineamiento: Bienestar Socio Territorial. Ítem: Espacios y Equipamiento Publico. Objetivo: Construir equipamientos públicos y espacios de carácter cívico en la región. Actividad: No Hay. | R18: Se enlaza con el Programa Regional del Gobernador: - Pilar 3. Inclusión Social y Mejoramiento de la Calidad de Vida. - Letra c) Programas de Apoyo Social: Desarrollar iniciativas para apoyar a los sectores más vulnerables de nuestra comunidad. | V18: Municipalidad Maullín | W18: Municipalidad Maullín | X18: 691 | Y18: 45869 | AA18: 45873 | AB18: 45873 | AC18: 45873 | AD18: =WORKDAY(AC18,15,'Feriados y Comunas'!A$2:A$26) -> 45895 | AJ18: 1968 | AK18: 45881 | AL18: 45877 | AM18: OBSERVADO | AR18: 1968 | AS18: 45881 | AW18: Observado | AX18: 4 | AY18: =IFERROR(__xludf.DUMMYFUNCTION("IFERROR(COUNTA(SPLIT(AK18, "" "")), 0)"),1.0) -> 1
A19: 18 | B19: 40073344 | C19: 0 | D19: Construcción Calle Fuente Bellavista | E19: Ancud | F19: =+IFERROR(VLOOKUP(E19,'Feriados y Comunas'!$C$1:$D$36,2,FALSE),"") -> CHILOÉ | G19: 45876 | H19: 215349 | J19: Ejecución | K19: 2026 | L19: Vivienda | M19: 1. Adjuntar Carta de no fraccionamiento alcalde. 2. Incorporar Certificado de Conexiones domiciliarias. 3. Adjuntar documentación al BIP. 1. Debe retirar del proyecto todo lo relacionado a fuente de financiamiento que no corresponde. Recordar que el financiamiento es FNDR del Gobierno Regional. 2. Al finalizar correcciones debe corregir la ficha IDI (actualmente tiene errores). Corregir beneficiarios directos que no coinciden con el perfil o la institución técnica, que debe ser el municipio.3. Respecto al perfil del proyecto, Identificar gráficamente (confinar con polígono) el Barrio Caicumeo, dentro de este polígono identificar la calle con pavimento de ripio a mejorar, así como también debe graficar todas las otras calles que cuentan con pavimento granular o ripio. 4. Respecto a certificaciones: a) Certificado de emplazamiento en bien de uso público, le falta el BIP b) Ver instructivo 2025 y presentar ANEXO 1 (para casos donde no hay permiso de edificación) c) Compromiso de absorción de costos de operación y mantención, le falta el BIP d) Respecto a participación ciudadana, revisar instructivo y presentar anexos propuestos, según corresponda e) Ver instructivo y presentar copia de certificado de título de los profesionales patrocinantes, responsables ante la ley que subscriben el proyecto. f) Presentar certificado firmada por alcalde más asesor jurídico, garantizando que no existen restricciones técnicas, legales ni administrativas para su posterior ejecución, y declarando que el proyecto en cuestión no corresponde al fraccionamiento de una iniciativa de mayor envergadura. (Es requerimiento del Departamento jurídico del Gobierno Regional) | N19: 45898 | Q19: Se encuentra dentro de la ERD en el: Lineamiento: Conectividad y Movilidad Regional Sustentable. Ítem: Movilidad Sostenible. Objetivo: Extender y Mejorar las aceras peatonales en localidades urbanas. Actividad: Plan de Mejoramiento de aceras de ata estándar con criterios de accesibilidad universal en ciudades intermedias de la región. | R19: Se enlaza con el Programa Regional del Gobernador: Pilar 1. Políticas Públicas en Materia de Seguridad Ciudadana. Letra i) Espacios Seguros: Mejorar la iluminación y la seguridad en parques, plazas y áreas públicas para garantizar espacios seguros para todos los habitantes. | S19: 288 | T19: 312 | U19: =SUM(S19:T19) -> 600 | V19: Municipalidad Ancud | W19: Municipalidad Ancud | X19: 1079 | Y19: 45874 | AA19: 45876 | AB19: 45876 | AC19: 45876 | AD19: =WORKDAY(AC19,15,'Feriados y Comunas'!A$2:A$26) -> 45898 | AJ19: 2276 | AK19: 45902 | AL19: 45898 | AM19: OBSERVADO | AR19: 2276 | AS19: 45902 | AW19: Observado | AX19: 15 | AY19: =IFERROR(__xludf.DUMMYFUNCTION("IFERROR(COUNTA(SPLIT(AK19, "" "")), 0)"),1.0) -> 1
A20: 19 | B20: 40070936 | C20: 0 | D20: Mejoramiento Escuela Rural San Javier | E20: Curaco de Vélez | F20: =+IFERROR(VLOOKUP(E20,'Feriados y Comunas'!$C$1:$D$36,2,FALSE),"") -> CHILOÉ | G20: 45883 | H20: 326436 | J20: Ejecución | K20: 2026 | L20: Educación | M20: 1. Adjuntar Carta de no fraccionamiento alcalde. 2. Certificado de Hipotecas y Gravámenes. 3. Se sugiere analizar Ppto. Hasta M$300. 4. Aclarar administración del establecimiento. 5. Adjuntar documentación al BIP.GENERALES 1. Aprobación de Dirección de Vialidad. 2. Estacionamiento universal debe incorporar acceso. 3. Oficio o certificado de “Visación Técnica del MINEDUC” o “Conformidad de Intervención” emitido por la SEREMI de Educación. 4. Adjuntar carta de no fraccionamiento. TTR y,o EETT 1. Hay partidas que son señaladas en el índice y no aparecen en el documento (desde página 64 a la 69). Incorporar partidas faltantes. Incorporar imagen esquemática de placa recordatoria. 2. Página 12 repetida. 3. Valor de presupuesto no es el mismo que el señalado en imagen del letrero de obras. PLANOS E INGENERÍA 1. En firmas de planos de arquitectura, figuran dos directores de SECPLAN. 2. Pl-A.01.2.12v1: Diseño estructural de la rampa no corresponde. Se señala capa vegetal de 0,30m como componente de la estructura del pavimento. Además, esta partida no se encuentra en EETT ni presupuesto. ANEXOS 1. Respecto al a 5.8. Antecedentes, j) Propiedad del terreno: Según el Certificado de Hipotecas y Gravámenes, el terreno donde se emplaza laEscuela Rural presenta una prohibición inscrita a fojas 212 a favor del Instituto Nacional de Deportes de Chile. Se solicita al municipio acreditar la naturaleza de dicha prohibición y, en caso de corresponder, adjuntar autorización expresa del IND que permita la ejecución del proyecto en el inmueble, a fin de verificar la disponibilidad jurídica del terreno. 2. Incorporar firma arquitecto en Carta Gantt. | N20: 45898 | Q20: Se encuentra dentro de la ERD en, - Lineamiento: Bienestar Socio Territorial. - Ítem: Educación. - Objetivo: Mejorar el desempeño de los establecimientos educacionales públicos y subvencionados de la Región . - Actividad: No hay. | R20: Se enlaza con el Programa Regional del Gobernador en el lineamiento - Pilar: 3. Inclusión Social y Mejoramiento de la Calidad de Vida. -Letra: i) Infraestructura Educativa: Renovar y construir nuevas instalaciones educativas para garantizar ambientes de aprendizaje adecuados. | S20: 20 | T20: 28 | U20: =SUM(S20:T20) -> 48 | V20: Municipalidad Curaco de Velez | W20: Municipalidad Curaco de Velez | X20: 329 | Y20: 45859 | AA20: 45883 | AB20: 45883 | AC20: 45883 | AD20: =WORKDAY(AC20,15,'Feriados y Comunas'!A$2:A$26) -> 45905 | AE20: Dcastro | AJ20: 2271 | AK20: 45902 | AL20: 45898 | AM20: OBSERVADO | AR20: 2271 | AS20: 45902 | AW20: Observado | AX20: 12 | AY20: =IFERROR(__xludf.DUMMYFUNCTION("IFERROR(COUNTA(SPLIT(AK20, "" "")), 0)"),1.0) -> 1
A21: 20 | B21: 40071284 | C21: 0 | D21: Mejoramiento Patinodromo, Parque Los Molinos | E21: Curaco de Vélez | F21: =+IFERROR(VLOOKUP(E21,'Feriados y Comunas'!$C$1:$D$36,2,FALSE),"") -> CHILOÉ | G21: 45901 | H21: 323060 | J21: Ejecución | K21: 2026 | L21: Deportes | M21: 1. Se sugiere postular proyecto integral de Mejoramiento Parque Los Molinos al FNDR tradicional. 2. Iniciativa actual corresponde a un fraccionamiento más cuando existe un FRIL asociado al mismo Rol. 3. Adjuntar documentación al BIP. | N21: 45926 | Q21: La iniciativa se orienta dentro de la ERD en el: - Lineamiento: Bienestar Socio Territorial. - Ítem: Espacios y Equipamiento Público - Objetivo: Aumentar el Nro. De espacios polideportivos en la región con criterios de genero e inclusividad. - Actividad: No hay. | R21: Se enlaza con el Programa Regional del Gobernador: - Pilar: 3. Inclusión Social y Mejoramiento de la Calidad de Vida. - Letra: c) Programas de Apoyo Social: Desarrollar iniciativas para apoyar a los sectores más vulnerables de nuestra comunidad. | S21: 180 | T21: 220 | U21: =SUM(S21:T21) -> 400 | V21: Municipalidad Curaco de Velez | W21: Municipalidad Curaco de Velez | X21: 328 | Y21: 45859 | AA21: 45901 | AB21: 45901 | AC21: 45901 | AD21: =WORKDAY(AC21,15,'Feriados y Comunas'!A$2:A$26) -> 45924 | AE21: Dcastro | AJ21: 2519 | AK21: 45930 | AL21: 45926 | AM21: OBSERVADO | AR21: 2519 | AS21: 45930 | AW21: Observado | AX21: 17 | AY21: =IFERROR(__xludf.DUMMYFUNCTION("IFERROR(COUNTA(SPLIT(AK21, "" "")), 0)"),1.0) -> 1
A22: 21 | B22: 40072776 | C22: 0 | D22: Conservación Veredas ST Almirante Latorre | E22: Calbuco | F22: =+IFERROR(VLOOKUP(E22,'Feriados y Comunas'!$C$1:$D$36,2,FALSE),"") -> LLANQUIHUE | G22: 45901 | H22: 303000 | J22: Ejecución | K22: 2026 | L22: seguridad | M22: GENERALES 1. Se debe adjuntar minuta de respuesta a observaciones respecto de la evaluación anterior (23-09-2025). Al responder nuevas observaciones, se debe incluir minuta de respuestas. 2. Se recomienda revisar accesibilidad universal, puesto que: a) Radios de giro inferior a normativa en múltiples lugares. b) No se cumple el ancho mínimo de ruta en múltiples lugares. 3. Discordancia en valor total del proyecto entre valor señalado en BIP, Presupuesto y Ficha IDI. 4. Respecto al estudio de mecánica de suelos: Se señala en el ítem 1.2 Alcances del mismo, que no aplica para el presente proyecto. 5. Respecto a archivos cargados en el BIP: Eliminar archivos que no son definitivos o están disgregados, respecto a presupuesto y EETT. Se debe adjuntar solo un archivo de presupuesto y un archivo de EETT. 6. Se recomienda que el proyecto sea abordado con una perspectiva de desarrollo urbano más integral y estratégica. Actualmente, la iniciativa se limita a la conservación de veredas; sin embargo, considerando la relevancia de la vía, que cumple una función troncal en la distribución de los flujos vehiculares y peatonales de la comuna, y la disponibilidad de un ancho de 5 metros entre línea oficial y solera en ambos costados de la calzada, resultaría pertinente proyectar una intervención más integral del espacio urbano. Asimismo, al continuar el desarrollo de esta iniciativa bajo el presente mecanismo de financiamiento, se deben tener en cuenta las restricciones establecidas en el Instructivo 5.000 UTM respecto de la postulación de futuros proyectos complementarios o asociados que interactúen directa o indirectamente con el actual proyecto. PLANOS E INGENERÍA 1. Se debe cumplir con lo señalado en OGUC en Artículo 2.2.8. punto 1., en los lugares donde sea necesario. Por ejemplo, sobre el muro de contención. ANEXOS 1. Certificado DOM BNUP debe señalar el tipo de vía según Art. 2.3.2. OGUC. 2. Incluir memoria de accesibilidad. 3. Incluir plan de mitigación. | N22: 45933 | Q22: Se encuentra dentro de los lineamientos de la ERD en - Lineamiento: Conectividad y Movilidad Regional Sustentable. - Ítem: Movilidad Sostenible. - Obj.: Extender y Mejorar las aceras peatonales en localidades urbanas. - Actividad: Plan de Mejoramiento de aceras de alto estándar con criterios de accesibilidad universal en ciudades intermedias de la región. | R22: Se enlaza con el Programa Regional del Gobernador: - Pilar: 1. Políticas Públicas en Materia de Seguridad Ciudadana. - Letra: i) Espacios Seguros: Mejorar la iluminación y la seguridad en parques, plazas y áreas públicas para garantizar espacios seguros para todos los habitantes. | S22: 1537 | T22: 1742 | U22: =SUM(S22:T22) -> 3279 | V22: Municipalidad Calbuco | W22: Municipalidad Calbuco | X22: 562 | Y22: 45897 | AA22: 45901 | AB22: 45901 | AC22: 45901 | AD22: =WORKDAY(AC22,15,'Feriados y Comunas'!A$2:A$26) -> 45924 | AE22: Dcastro | AJ22: 2408 2896 | AK22: 23-09-2025 03-11-2025 | AL22: 23-09-2025 30-10-2025 | AM22: OBSERVADO OBSERVADO | AN22: 764 | AO22: 45930 | AQ22: 45932 | AR22: 2408 2896 | AS22: 23-09-2025 03-11-2025 | AW22: Observado | AX22: 17 | AY22: =IFERROR(__xludf.DUMMYFUNCTION("IFERROR(COUNTA(SPLIT(AK22, "" "")), 0)"),2.0) -> 2
A23: 22 | B23: 40072916 | C23: 0 | D23: Mejoramiento Calles Padre Nicanor y Sor Teresa | E23: Puerto Varas | F23: =+IFERROR(VLOOKUP(E23,'Feriados y Comunas'!$C$1:$D$36,2,FALSE),"") -> LLANQUIHUE | G23: 45903 | H23: 201000 | J23: Ejecución | K23: 2026 | L23: Multisectorial | M23: Generales 1. Mecánica de suelos adjunta está incompleta. Debe incorporar memoria del informe. Informe de laboratorio adjunto no señala ensayo de infiltración necesario para la solución de aguas drenaje. 2. Memoria de cálculo debe señalar de donde se obtienen los valores asumidos para el diseño del drenaje. | N23: 45975 | Q23: Se encuentra dentro de los lineamientos de la ERD en - Lineamiento: Conectividad y Movilidad Regional Sustentable. - Ítem: Movilidad Sostenible. - Obj.: Extender y Mejorar las aceras peatonales en localidades urbanas. - Actividad: Plan de inversión en infraestructura vialidad menor. | R23: Se enlaza con el Programa Regional del Gobernador en el - Pilar: 2. Desarrollo Económico Sostenible: una Alianza Público-Privada - Letra: c)Inversiones en Infraestructura: Mejorar la conectividad y la infraestructura regional para atraer inversiones y generar empleo. | S23: 254 | T23: 332 | U23: =SUM(S23:T23) -> 586 | V23: Municipalidad Puerto Varas | X23: 1144 | Y23: 45898 | AA23: 45903 | AB23: 45903 | AC23: 45903 | AD23: =WORKDAY(AC23,15,'Feriados y Comunas'!A$2:A$26) -> 45926 | AE23: Dcastro | AJ23: 2518 2907 3086 | AK23: 30-09-2025 03-11-2025 14-11-2025 | AL23: 26-09-2025 30-11-2025 14-11-2025 | AM23: OBSERVADO OBSERVADO OBSERVADO | AN23: 65 | AO23: 45953 | AQ23: 45953 | AR23: 2518 2907 3086 | AS23: 30-09-2025 03-11-2025 14-11-2025 | AW23: Observado | AX23: 15 | AY23: =IFERROR(__xludf.DUMMYFUNCTION("IFERROR(COUNTA(SPLIT(AK23, "" "")), 0)"),3.0) -> 3
A24: 23 | B24: 40075003 | C24: 0 | D24: Mejoramiento Plaza Villa El Trebol | E24: Fresia | F24: =+IFERROR(VLOOKUP(E24,'Feriados y Comunas'!$C$1:$D$36,2,FALSE),"") -> LLANQUIHUE | G24: 45904 | H24: 180000 | J24: Ejecución | K24: 2026 | L24: Multisectorial | M24: 1. Adjuntar documentación de acuerdo a los instructivos del Gobierno Regional. 2. Adjuntar documentación al BIP. 1. El proyecto no cuenta con archivos cargados en la plataforma | N24: Pendiente | Q24: Se encuentra dentro de la ERD en: - Lineamiento: Bienestar Socio Territorial. - Ítem: Espacios y Equipamiento Publico. - Objetivo: Construir nuevas áreas verdes de uso publico como herramienta de esparcimiento e integración barrial en las ciudades de la región. - Actividad: Programa regional de construcción y reposición de áreas verdes. | R24: Se enlaza con el Programa Regional del Gobernador en el - Pilar: 1. Políticas Públicas en Materia de Seguridad Ciudadana - Letra: i) Espacios Seguros: Mejorar la iluminación y la seguridad en parques, plazas y áreas públicas para garantizar espacios seguros para todos los habitantes. | S24: 3504 | T24: 3824 | U24: =SUM(S24:T24) -> 7328 | V24: Municipalidad Fresia | W24: Municipalidad Fresia | X24: 728 | Y24: 45904 | AA24: 45904 | AB24: 45904 | AC24: 45904 | AD24: =WORKDAY(AC24,15,'Feriados y Comunas'!A$2:A$26) -> 45929 | AE24: Dcastro | AJ24: 2608 2362 | AK24: 08-10-2025 19-08-2026 | AL24: 03-10-2025 18-08-2026 | AM24: OBSERVADO OBSERVADO | AN24: 503 | AO24: 46225 | AQ24: 46239 | AR24: 2608 | AS24: 45938 | AW24: Observado | AX24: 14 | AY24: =IFERROR(__xludf.DUMMYFUNCTION("IFERROR(COUNTA(SPLIT(AK24, "" "")), 0)"),2.0) -> 2
A25: 24 | B25: 40072891 | C25: 0 | D25: Mejoramiento Multicanchas ST Borde Lago | E25: Puerto Varas | F25: =+IFERROR(VLOOKUP(E25,'Feriados y Comunas'!$C$1:$D$36,2,FALSE),"") -> LLANQUIHUE | G25: 45911 | H25: 300000 | J25: Ejecución | K25: 2026 | L25: Multisectorial | M25: 1. A nivel de alternativas describir con mayor detalle la intervención de la infraestructura. 2. Adjuntar Certificado de Informes previos. 3. Anexas Informe Técnico situación actual por profesional del área. 4. Incorporar factibilidad. 5. Adjuntar carta de no fraccionamiento firmado por el alcalde y visado por depto. jurídico. 6. Anexar Certificado de BNUP. 7. Adjuntar documentación al BIP. GENERALES 1. Incluir carta de no fraccionamiento firmada por alcalde. 2. Justificación de la IDI no corresponde al actual proyecto. ESTUDIO PREINVERSIONAL 1. Documento debe estar firmado por unidad formuladora y en formato PDF. TTR y,o EETT 1. Partida 2.5.3. señalada en EETT no se encuentra incluida en Carta Gantt PLANOS E INGENERÍA 1. Para el correcto y adecuado desarrollo de las actividades deportivas, el diseño de la multicancha deberá estar acorde a las disposiciones del Instituto Nacional de Deporte (IND), en cuanto a las dimensiones y requerimientos de las disciplinas consideradas en el proyecto. El diseño actual no cumple con las dimensiones mínimas. Se recomienda revisar “Manual de construcción y requisitos mínimos para parques, plazas, áreas verdes y áreas deportivas, MINVU, 2017” 2. EL muro de escalada sobre la estructura de cierro de la multicancha debe ser estructuralmente validado. ANEXOS 1. Adjuntar b) Ficha IDI 2. Adjuntar h) Factibilidad eléctrica. 3. Adjuntar j) Propiedad del terreno. 4. Adjuntar m) Certificado compromiso de absorción de costos de operación y mantención. El nombre del proyecto señalado en el archivo adjunto no corresponde al actual proyecto. | N25: 45975 | Q25: La iniciativa se orienta dentro de la ERD en el: - Lineamiento: Bienestar Socio Territorial. - Ítem: Espacios y Equipamiento Público - Objetivo: Aumentar el Nro. De espacios polideportivos en la región con criterios de genero e inclusividad. - Actividad: No hay. | R25: Se enlaza con el Programa Regional del Gobernador: - Pilar: 3. Inclusión Social y Mejoramiento de la Calidad de Vida. - Letra: c) Programas de Apoyo Social: Desarrollar iniciativas para apoyar a los sectores más vulnerables de nuestra comunidad. | S25: 885 | T25: 562 | U25: =SUM(S25:T25) -> 1447 | V25: Municipalidad Puerto Varas | W25: Municipalidad Puerto Varas | X25: 1197 | Y25: 45909 | AA25: 45912 | AB25: 45912 | AC25: 45912 | AD25: =WORKDAY(AC25,15,'Feriados y Comunas'!A$2:A$26) -> 45937 | AE25: Dcastro | AJ25: 2609 3079 | AK25: 08-10-2025 14-11-2025 | AL25: 03-10-2025 14-11-2025 | AM25: OBSERVADO OBSERVADO | AN25: 71 | AO25: 45960 | AQ25: 45964 | AR25: 2609 3079 | AS25: 08-10-2025 14-11-2025 | AW25: Observado | AX25: 13 | AY25: =IFERROR(__xludf.DUMMYFUNCTION("IFERROR(COUNTA(SPLIT(AK25, "" "")), 0)"),2.0) -> 2
A26: 25 | B26: 40031582 | C26: 0 | D26: Construcción Casa Cuesta Arriba | E26: Puerto Varas | F26: =+IFERROR(VLOOKUP(E26,'Feriados y Comunas'!$C$1:$D$36,2,FALSE),"") -> LLANQUIHUE | G26: 45911 | H26: 220000 | J26: Ejecución | K26: 2026 | L26: Multisectorial | M26: 1. Debe existir concordancia de ítems entre EETT, Presupuesto y Carta Gantt. 2. Adjuntar anexo q) Proyectos de especialidades, según lo allí indicado; incorporar mecánica de suelo | N26: 45960 | Q26: Se encuentra dentro de la ERD en el: Lineamiento: Bienestar Socio Territorial. Ítem: Espacios y Equipamiento Publico. Objetivo: Construir equipamientos públicos y espacios de carácter cívico en la región. Actividad: No Hay | R26: Se enlaza con el Programa Regional del Gobernador: Pilar 3. Inclusión Social y Mejoramiento de la Calidad de Vida. Letra c) Programas de Apoyo Social: Desarrollar iniciativas para apoyar a los sectores más vulnerables de nuestra comunidad. | S26: 42 | T26: 63 | U26: =SUM(S26:T26) -> 105 | V26: Municipalidad Puerto Varas | W26: Municipalidad Puerto Varas | X26: 1198 | Y26: 45909 | AA26: 45912 | AB26: 45912 | AC26: 45912 | AD26: =WORKDAY(AC26,15,'Feriados y Comunas'!A$2:A$26) -> 45937 | AE26: Dcastro | AJ26: 2610 2931 | AK26: 08-10-2025 04-11-2025 | AL26: 03-10-2025 30-10-2025 | AM26: OBSERVADO OBSERVADO | AN26: 66 | AO26: 45954 | AQ26: 45958 | AR26: 2610 2931 | AS26: 08-10-2025 04-11-2025 | AW26: Observado | AX26: 13 | AY26: =IFERROR(__xludf.DUMMYFUNCTION("IFERROR(COUNTA(SPLIT(AK26, "" "")), 0)"),2.0) -> 2
A27: 26 | B27: 40072914 | C27: 0 | D27: Mejoramiento Plaza Pob. Digna Campesina de Nueva Braunau | E27: Puerto Varas | F27: =+IFERROR(VLOOKUP(E27,'Feriados y Comunas'!$C$1:$D$36,2,FALSE),"") -> LLANQUIHUE | G27: 45911 | H27: 300000 | J27: Ejecución | K27: 2026 | L27: Multisectorial | M27: Adjuntar EETT firmados por UT. 2. Anexar Ppto. Desglosado. 3. Incorporar APUS 4. Adjuntar Permiso de obra menor. 5. Anexar Memoria. 6. Incorporar Mecánica si corresponde. 7. Adjuntar Cronograma. 8. Anexar Factibilidades. 9. Incorporar Carta de no fraccionamiento, visada por Depto. juridico. 10. Se solicita especificar y caracterizar el área de influencia, cantidad de áreas verdes, multicanchas, etc. 11. Especificar la población objetivo. Ajustar esta con la población total de la localidad. 12. Desarrollar y especificar análisis de alternativas. 13. Adjuntar documentación al BIP. GENERALES Proyecto incompleto: No presenta presupuesto y especificaciones técnicas. | N27: 45933 | Q27: Se encuentra dentro de la ERD en: - Lineamiento: Bienestar Socio Territorial. - Ítem: Espacios y Equipamiento Publico. - Objetivo: Construir nuevas áreas verdes de uso publico como herramienta de esparcimiento e integración barrial en las ciudades de la región. - Actividad: Programa regional de construcción y reposición de áreas verdes. | R27: Se enlaza con el Programa Regional del Gobernador en el - Pilar: 1. Políticas Públicas en Materia de Seguridad Ciudadana - Letra: i) Espacios Seguros: Mejorar la iluminación y la seguridad en parques, plazas y áreas públicas para garantizar espacios seguros para todos los habitantes. | S27: 248 | T27: 324 | U27: =SUM(S27:T27) -> 572 | V27: Municipalidad Puerto Varas | W27: Municipalidad Puerto Varas | X27: 1195 | Y27: 45909 | AA27: 45912 | AB27: 45912 | AC27: 45912 | AD27: =WORKDAY(AC27,15,'Feriados y Comunas'!A$2:A$26) -> 45937 | AJ27: 2611 | AK27: 45938 | AL27: 45933 | AM27: OBSERVADO | AR27: 2611 | AS27: 45938 | AW27: Observado | AX27: 13 | AY27: =IFERROR(__xludf.DUMMYFUNCTION("IFERROR(COUNTA(SPLIT(AK27, "" "")), 0)"),1.0) -> 1
A28: 27 | B28: 40072880 | C28: 0 | D28: Mejoramiento Multicanchas ST Monte Alegre | E28: Puerto Varas | F28: =+IFERROR(VLOOKUP(E28,'Feriados y Comunas'!$C$1:$D$36,2,FALSE),"") -> LLANQUIHUE | G28: 45911 | H28: 300000 | J28: Ejecución | K28: 2026 | L28: Multisectorial | M28: 1. Crear Ficha 2026. 2. Iniciativa debe ser separada, ya que correspondería a un fraccionamiento al presentar otras 2 en la misma área de influencia. 3. La demanda no se ajusta para ambas infraestructuras. 4. Desarrollar el análisis de alternativas, especificar y describir la alternativa seleccionada. 5. Inconsistencia entre justificación ficha IDI y perfil. 6. Adjuntar documentación al BIP. | N28: 45933 | Q28: La iniciativa se orienta dentro de la ERD en el: - Lineamiento: Bienestar Socio Territorial. - Ítem: Espacios y Equipamiento Público - Objetivo: Aumentar el Nro. De espacios polideportivos en la región con criterios de genero e inclusividad. - Actividad: No hay. | R28: Se enlaza con el Programa Regional del Gobernador: - Pilar: 3. Inclusión Social y Mejoramiento de la Calidad de Vida. - Letra: c) Programas de Apoyo Social: Desarrollar iniciativas para apoyar a los sectores más vulnerables de nuestra comunidad. | S28: 645 | T28: 387 | U28: =SUM(S28:T28) -> 1032 | V28: Municipalidad Puerto Varas | W28: Municipalidad Puerto Varas | X28: 1196 | Y28: 45909 | AA28: 45912 | AB28: 45912 | AC28: 45912 | AD28: =WORKDAY(AC28,15,'Feriados y Comunas'!A$2:A$26) -> 45937 | AE28: Dcastro | AJ28: 2612 | AK28: 45938 | AL28: 45933 | AM28: OBSERVADO | AR28: 2612 | AS28: 45938 | AW28: Observado | AX28: 13 | AY28: =IFERROR(__xludf.DUMMYFUNCTION("IFERROR(COUNTA(SPLIT(AK28, "" "")), 0)"),1.0) -> 1
A29: 28 | B29: 40071625 | C29: 0 | D29: Mejoramiento Camarines y Servicios Higienicos Estadio Municipal | E29: San Pablo | F29: =+IFERROR(VLOOKUP(E29,'Feriados y Comunas'!$C$1:$D$36,2,FALSE),"") -> OSORNO | G29: 45917 | H29: 312894 | J29: Ejecución | K29: 2026 | L29: Deportes | M29: 1. Faltan antecedentes mínimos para un análisis completo. 2. Adicionalmente el proyecto corresponde a un fraccionamiento, ya que solo el proyecto mejora solo una parte del recinto, y no un mejoramiento integral. 3. Adjuntar documentación al BIP. | N29: 45953 | Q29: La iniciativa se orienta dentro de la ERD en el: - Lineamiento: Bienestar Socio Territorial. - Ítem: Espacios y Equipamiento Público - Objetivo: Aumentar el Nro. De espacios polideportivos en la región con criterios de genero e inclusividad. - Actividad: No hay. | R29: Se enlaza con el Programa Regional del Gobernador: - Pilar: 3. Inclusión Social y Mejoramiento de la Calidad de Vida. - Letra: c) Programas de Apoyo Social: Desarrollar iniciativas para apoyar a los sectores más vulnerables de nuestra comunidad. | S29: 154 | T29: 205 | U29: =SUM(S29:T29) -> 359 | V29: Municipalidad San Pablo | W29: Municipalidad San Pablo | X29: 657 | Y29: 45915 | AA29: 45917 | AB29: 45917 | AC29: 45917 | AD29: =WORKDAY(AC29,15,'Feriados y Comunas'!A$2:A$26) -> 45940 | AJ29: 2825 | AK29: 45957 | AL29: 45953 | AM29: OBSERVADO | AR29: 2825 | AS29: 45957 | AW29: Observado | AX29: 24 | AY29: =IFERROR(__xludf.DUMMYFUNCTION("IFERROR(COUNTA(SPLIT(AK29, "" "")), 0)"),1.0) -> 1
A30: 29 | B30: 40075706 | C30: 0 | D30: Construcción Centro Comunitario Multiproposito Trumao | E30: San Pablo | F30: =+IFERROR(VLOOKUP(E30,'Feriados y Comunas'!$C$1:$D$36,2,FALSE),"") -> OSORNO | G30: 45917 | H30: 295000 | J30: Ejecución | K30: 2026 | L30: Salud | M30: 1. Crear Ficha 2026, Corregir m2. 2. Ppto. No concuerda con ficha IDI. 3. Adjuntar Participación ciudadana anexo 2. 4. Anexar Permiso. 5. Incorporar Memoria. 6. Adjuntar Mecánica. 7. Anexar Cronograma. 8. Incorporar Modelo de Gestión. 9. Adjuntar Certificado de Hipotecas y Gravámenes. 10. Anexar Costos Operacionales Firmado por el Consejo. 11. Incorporar Certificado Secplan – DOM. 12. Adjuntar Carta de no Fraccionamiento visado por Depto. Jurídico. 13. Anexar Informes Previos. 14. Incorporar Plan de Mitigación. 15. Adjuntar documentación al BIP. EVALUACIÓN TÉCNICA - PRESUPUESTO 1. No está presupuestada la demolición de la edificación existente. 2. Se debe señalar bajo cada firma de documento y plano de los proyectos de especialidades, a lo menos el nombre y profesión del proyectista. 3. Valor total de presupuesto no coincide con Ficha IDI en BIP. TTR y,o EETT 1. Incorporar imagen final Letrero de Obras, ajustada al manual de normas gráficas GORE 2025 2. Incorporar imagen final Placa Recordatoria, ajustada al manual de normas gráficas GORE 2025. PLANOS E INGENERÍA 1. Pl-eléctrico: En Baño 1 y Baño 2 se debe incorporar dispositivo de iluminación. 2. Incorporar plano de demoliciones. ANEXOS 1. Incorporar lo señalado en 5.8. b) Ficha IDI 2. Incorporar lo señalado en 5.8. h) Factibilidad sanitaria 3. Incorporar lo señalado en 5.8. j) Propiedades del terreno: Certificado de hipotecas y gravámenes. 4. Incorporar lo señalado en 5.8. k) Certificado del DOM 5. Incorporar lo señalado en 5.8. l) Permiso de edificación 6. Incorporar lo señalado en 5.8. n) Participación ciudadana 7. Incorporar lo señalado en 5.8. q) Proyectos de Especialidades, tales como Ingeniería, Estudios Hidráulicos, Mecánica de Suelo, etc. 8. Incorporar lo señalado en 5.8. r) Copia de certificado de título. 9. Incorporar lo señalado en 5.8. u) Plan de mitigación durante la ejecución de las obras. Esto, respecto a la programación que dé continuidad a la asistencia médica que se presta en una de las edificaciones. | N30: 45953 | Q30: Se encuentra dentro de la ERD en el - Lineamiento: Bienestar Socio Territorial. - Ítem: Salud. - Objetivo: Aumentar Cobertura de atención primaria en salud en la comunas de la región. - Actividad: | R30: Se enlaza con el programa del Gobernador Regional en el - Pilar: 3. Inclusión Social y Mejoramiento de la Calidad de Vida. - Letra: e) Acceso a Servicios de Salud: Ampliar y mejorar la red de servicios de salud, especialmente en zonas rurales, garantizando atención médica de calidad para todos. | S30: 120 | T30: 158 | U30: =SUM(S30:T30) -> 278 | V30: Municipalidad San Pablo | W30: Municipalidad San Pablo | X30: 655 | Y30: 45910 | AA30: 45917 | AB30: 45917 | AC30: 45917 | AD30: =WORKDAY(AC30,15,'Feriados y Comunas'!A$2:A$26) -> 45940 | AE30: Dcastro | AJ30: 2824 | AK30: 45957 | AL30: 45953 | AM30: OBSERVADO | AR30: 2824 | AS30: 45957 | AW30: Observado | AX30: 24 | AY30: =IFERROR(__xludf.DUMMYFUNCTION("IFERROR(COUNTA(SPLIT(AK30, "" "")), 0)"),1.0) -> 1
A31: 30 | B31: 40076630 | C31: 0 | D31: Reposición Bateria Sanitaria del Monumento Natural Lahuen Ñadi | E31: Puerto Montt | F31: =+IFERROR(VLOOKUP(E31,'Feriados y Comunas'!$C$1:$D$36,2,FALSE),"") -> LLANQUIHUE | G31: 45958 | H31: 100740 | J31: Ejecución | K31: 2026 | L31: Recursos Naturales | M31: GENERALES 1. Es necesario mayor desarrollo del proyecto en general. 2. En informe técnico de emplazamiento es importante incluir imágenes de la situación actual de la edificación a reponer. 3. Todos los documentos y planos elaborados por el profesional competente, también deben ser firmados por la unidad técnica. 4. Monto solicitado en BIP no concuerda con lo señalado en presupuesto. EVALUACIÓN TÉCNICA - PRESUPUESTO 1. Incorporar Carta Gantt 2. No hay concordancia total entre presupuesto y especificaciones técnicas. Los ítems de presupuesto deben estar todos identificados en especificaciones técnicas, por ejemplo: ítems 9.2, 9.3 y 10. Además, no se pueden asignar presupuestos a partidas generales, como las señaladas en ítem 9. INSTALACIONES, estos deben ser desglosados. TTR y,o EETT Se recomienda revisar con detención el instructivo, ítem 5.8. letra f), y cumplir con todo lo allí señalado. 1. El itemizado de las partidas y subpartidas deben ser coherentes y coincidentes entre especificaciones técnicas y presupuesto. 2. Para cada partida que corresponda, debe incluir al final de la especificación, el N° de lámina de planimetría donde se encuentra lo especificado. 3. Se debe incluir la provisión del letrero de obra y Placa Conmemorativa, ambos con el diseño oficial vigente del año presupuestario. PLANOS E INGENERÍA 1. Planos de arquitectura deben incorporar más detalles de los elementos que lo componen, como: fundaciones, muros estructurales, tabiques, hojalatería, y todo lo que se señala en especificaciones técnicas que será indicado en planos. 2. Incorporar: 1. Plano de situación actual 2. Plano de demolición 3. Planta de accesibilidad universal 4. Plano de fundaciones. ANEXOS Incorpora antecedentes señalados en 5.8. del instructivo: b) Ficha IDI d) Informe técnico de emplazamiento. h) Factibilidad sanitaria y eléctrica. 1. Proyecto de agua potable y sanitario debe ser visado por autoridad sanitaria. 2. Se debe incorporar factibilidad eléctrica y factibilidad de dotación (Aprobación de derechos de aprovechamiento de agua). j) Propiedad del terreno 1. Certificado de hipotecas y gravámenes. l) Permiso de edificación o) Certificado de recepción municipal p) Proyecto de instalaciones domiciliarias 5. Plano proyecto eléctrico. 6. Planos proyecto agua potable y aguas servidas. r) Copia certificado de título s) Aprobaciones sectoriales 1. Según Ley 19.300 Articulo 10, Letra p), deben presentar la resolución del Servicio de Evaluación Ambiental (SEA) que indique que el proyecto no debe ingresar obligatoriamente al SEIA, o bien, la Resolución de Calificación Ambiental (RCA) favorable si es que entró al sistema. u) Plan de mitigación durante la ejecución de las obras. | N31: 46178 | Q31: Se encuentra dentro de la ERD en el: Lineamiento: Bienestar Socio Territorial. Ítem: Espacios y Equipamiento Publico. Objetivo: Construir equipamientos públicos y espacios de carácter cívico en la región. Actividad: No Hay. | R31: Se enlaza con el Programa Regional del Gobernador: - Pilar 3. Inclusión Social y Mejoramiento de la Calidad de Vida. - Letra c) Programas de Apoyo Social: Desarrollar iniciativas para apoyar a los sectores más vulnerables de nuestra comunidad. | S31: 5677 | T31: 6984 | U31: =SUM(S31:T31) -> 12661 | V31: Conaf | W31: Conaf | X31: 227 | Y31: 45957 | AA31: 45958 | AB31: 45958 | AC31: 45958 | AD31: =WORKDAY(AC31,15,'Feriados y Comunas'!A$2:A$26) -> 45980 | AE31: Dcastro | AJ31: 3074 308 1219 | AK31: 14-11-2025 11-02-2026 20-05-2026 | AL31: 04-11-2025 09-02-2026 20-05-2026 | AM31: OBSERVADO OBSERVADO OBSERVADO | AN31: 27 64 | AO31: 30-01-2026 11-04-20269 | AQ31: 02-02-2026 11-04-2026 | AR31: 3074 308 | AS31: 14-11-2025 11-02-2026 | AW31: Observado | AX31: 12 | AY31: =IFERROR(__xludf.DUMMYFUNCTION("IFERROR(COUNTA(SPLIT(AK31, "" "")), 0)"),3.0) -> 3
A32: 31 | B32: 40073420 | C32: 0 | D32: Mejoramiento Multicancha Claudio Matte Futaleufú | E32: Futaleufú | F32: =+IFERROR(VLOOKUP(E32,'Feriados y Comunas'!$C$1:$D$36,2,FALSE),"") -> PALENA | G32: 45987 | H32: 300000 | J32: Ejecución | K32: 2026 | L32: Deportes | M32: GENERALES 1. Nombre de proyecto indicado en BIP no coincide con el nombre indicado en todos los documentos del proyecto. 2. Proyecto debe estar aprobado por SERVIU. 3. Adjuntar certificado de no fraccionamiento firmado por Alcalde y visado por unidad jurídica. ESTUDIO PREINVERSIONAL 1. Incorporar imágenes de la situación actual de la estructura que evidencien su deterioro. 2. Antecedentes generales de la comuna son insuficientes: Se requiere definir claramente los antecedentes geográficos, área de estudio, características demográficas, infraestructura similar disponible en la comuna y su estado. EVALUACIÓN TÉCNICA - PRESUPUESTO 1. Errores de numeración en múltiples ítems. 2. Ítem 12.2.2, 12.2.6 no coincide con EETT. Verificar concordancia entre EETT y presupuesto. TTR y,o EETT 1. EETT de arquitectura e ingeniería deben estar solo en 1 documento. 2. Falta firma de ingeniero civil y eléctrico. PLANOS E INGENERÍA 1. Respecto de la planta de accesibilidad universal: La franja de circulación segura del estacionamiento debe proteger al peatón de la circulación vehicular de la calzada. Se debe proponer una nueva configuración. 2. Respecto a memoria de cálculo de proyecto de estructuras: Es necesario más información. Se debe cumplir con lo establecido en NCh 3417: Estructuras — Requisitos para proyectos de cálculo estructural. Ítem 5.1., principalmente indicar esquema de cargas y señalar principales resultados del análisis estructural. ANEXOS Incluir los siguientes antecedentes señalados en el ítem 5.8 del instructivo: b) Ficha IDI h) Factibilidad eléctrica k) Certificado DOM (Coordinación SECPLAN/DOM) o) Certificado de recepción municipal u) Plan de mitigación OFICIOS 1. Se debe cargar el oficio 659 24/12/2025 a BIP. TERRENO Y OTROS 1. Se requiere pronunciamiento de Instituto nacional del deporte de Chile para aclarar la naturaleza de la prohibición indicada en el certificado de hipotecas y gravámenes, prohibiciones, bien familiar y litigios. | N32: 46091 | Q32: La iniciativa se orienta dentro de la ERD en el: - Lineamiento: Bienestar Socio Territorial. - Ítem: Espacios y Equipamiento Público - Objetivo: Aumentar el Nro. De espacios polideportivos en la región con criterios de genero e inclusividad. - Actividad: No hay. | R32: Se enlaza con el Programa Regional del Gobernador: - Pilar: 3. Inclusión Social y Mejoramiento de la Calidad de Vida. - Letra: c) Programas de Apoyo Social: Desarrollar iniciativas para apoyar a los sectores más vulnerables de nuestra comunidad. | S32: 1300 | T32: 1300 | U32: =SUM(S32:T32) -> 2600 | V32: Municipalidad Futaleufu | W32: Municipalidad Futaleufu | X32: 562 | Y32: 45973 | AC32: 45987 | AD32: =WORKDAY(AC32,15,'Feriados y Comunas'!A$2:A$26) -> 46009 | AE32: Dcastro | AJ32: 3262 303 | AK32: 09-12-2025 11-02-2026 | AL32: 25-11-2025 10-02-2026 | AM32: OBSERVADO OBSERVADO | AN32: 659 | AO32: 46015 | AQ32: 46021 | AR32: 3262 303 | AS32: 09-12-2025 11-02-2026 | AW32: Observado | AX32: 9 | AY32: =IFERROR(__xludf.DUMMYFUNCTION("IFERROR(COUNTA(SPLIT(AK32, "" "")), 0)"),2.0) -> 2
A33: 32 | B33: 40065337 | C33: 0 | D33: Reposición Salón Multiuso Adulto Mayor, Los Muermos. | E33: Los Muermos | F33: LLANQUIHUE | G33: 46070 | H33: 336460 | J33: Ejecución | K33: 2026 | L33: Multisectorial | M33: Se informa Observaciones. GENERALES 1. Se observa que el presupuesto total del proyecto se encuentra en una brecha muy estrecha respecto al límite máximo financiable de la línea <5.000 UTM. A fin de cautelar la continuidad administrativa y evitar contingencias procedimentales, se recomienda ajustar el presupuesto para mantener un margen de seguridad de al menos $10.000.000 respecto al tope máximo de financiamiento. Lo anterior tiene como objetivo prevenir que, ante eventuales aumentos de obras o imprevistos propios de la ejecución, el proyecto supere el umbral normativo que obligaría a tramitar una reevaluación técnica ante el Ministerio de Desarrollo Social (MIDESO). Mantener esta holgura financiera permitirá al municipio gestionar variaciones menores sin comprometer la admisibilidad ni los plazos de ejecución de la obra. 2. Incorporar Plan de Gestión. 3. Incorporar Carta de no fraccionamiento firmada por Alcalde y visada por unidad jurídica. ESTUDIO PREINVERSIONAL 1. Incluir firma de profesional formulador. EVALUACIÓN TÉCNICA - PRESUPUESTO 1. El ítem 3.16 Equipamiento, presenta una inconsistencia ya que se encuentra cargado en el ítem de Obras Civiles. Se solicita realizar la separación contable de este presupuesto y clasificarlo correctamente bajo la categoría de Equipamiento, conforme a los clasificadores presupuestarios vigentes. Corregir este cambio también en ficha IDI. 2. El ítem 5.2 Placa de identificación de obra debe ajustarse al diseño oficial vigente del año presupuestario. PLANOS E INGENERÍA Plano de arquitectura: 1. A02 - Indicar ancho estacionamiento accesible 2. A02, A07 – No se indica acceso peatonal al predio. Se debe incluir portón de acceso independiente a portón de estacionamiento vehicular, y asegurar una ruta accesible hasta portón peatonal. Memoria de cálculo: 1. Memoria de cálculo eléctrica debe incluir firma de profesional. ANEXOS b) Ficha IDI: Adjuntar. j) Propiedad del terreno: Adjuntar Certificado de dominio vigente y Certificado de hipotecas y gravámenes. l) Permiso de edificación: Adjuntar certificado de informaciones previas. q) Proyectos de Especialidades, tales como Ingeniería, Estudios Hidráulicos, Mecánica de Suelo, etc: Debe adjuntar estudio de mecánica de suelos que valide el diseño estructural. r) Copia de certificado de título: Adjuntar certificado SEC formato digital y certificado de título proyectista eléctrico. u) Plan de mitigación: No queda claro de qué manera se van a reorganizar las actividades comunitarias programadas en el recinto a intervenir. | N33: Pendiente | Q33: Se encuentra dentro de la ERD en el: Lineamiento: Bienestar Socio Territorial. Ítem: Espacios y Equipamiento Publico. Objetivo: Construir equipamientos públicos y espacios de carácter cívico en la región. Actividad: No Hay. | R33: Se enlaza con el Programa Regional del Gobernador: Pilar 3. Inclusión Social y Mejoramiento de la Calidad de Vida. Letra c) Programas de Apoyo Social: Desarrollar iniciativas para apoyar a los sectores más vulnerables de nuestra comunidad. | S33: 110 | T33: 442 | U33: =SUM(S33:T33) -> 552 | V33: Municipalidad de Los Muermos | W33: Municipalidad de Los Muermos | X33: 268 | Y33: 46065 | AA33: 46070 | AB33: 46083 | AC33: 46083 | AD33: =WORKDAY(AC33,15,'Feriados y Comunas'!A$2:A$26) -> 46104 | AE33: Dcastro | AJ33: 432 1404 | AK33: 04-03-2026 10-06-2026 | AL33: 04-03-2026 09-06-2026 | AM33: OBSERVADO OBSERVADO | AN33: 569 | AO33: 46149 | AQ33: 46177 | AW33: Observado | AX33: 2 | AY33: =IFERROR(__xludf.DUMMYFUNCTION("IFERROR(COUNTA(SPLIT(AK33, "" "")), 0)"),2.0) -> 2
A34: 33 | B34: 40067355 | C34: 0 | D34: CONSTRUCCIÓN SEDE SOCIAL VILLA NUEVA PRIMAVERA, OSORNO | E34: Osorno | F34: =+IFERROR(VLOOKUP(E34,'Feriados y Comunas'!$C$1:$D$36,2,FALSE),"") -> OSORNO | G34: 46114 | H34: 173554 | J34: Ejecución | K34: 2026 | L34: Vivienda | M34: GENERALES 1. Se solicita adjuntar una minuta de respuesta a las observaciones formuladas. Este documento debe indicar expresamente la manera mediante la cual se subsanó cada una de las observaciones técnicas y, en caso de que la corrección haya derivado en otras modificaciones al proyecto original, se deben señalar también todos los cambios, a fin de permitir una revisión integral de la coherencia del proyecto. 2. El proyecto, al considerar la pavimentación de calzada y vereda en un tramo de 14 metros, incurre en un fraccionamiento de iniciativa de inversión pública, ya que dichas obras de infraestructura vial corresponden a proyectos de urbanización ajenos a la edificación de la sede social y que no dan solución integral a esta problemática del sector. Adicionalmente, al proyectarse sobre un predio no afecto a utilidad pública, se requeriría tramitar expropiaciones o cesiones formales. Según indica el instructivo en Capitulo IV, 4.1, 4, b) “Los proyectos que requieran realizar gestiones previas para hacer uso del terreno donde se localiza el proyecto, sin restricciones para los fines que se persiguen, tales como fusiones o anexiones de terrenos, expropiaciones, alzamiento de gravámenes y/o prohibiciones, autorizaciones para uso de predios rurales con usos ajenos a la agricultura y que deban proceder conforme al artículo 55 del Decreto N°458, que aprueba la Ley General de Urbanismo y Construcciones (LGUC)” No podrán acogerse al instructivo, y por lo tanto no son admisibles. Como alternativa de solución, para asegurar la viabilidad de la iniciativa y dar cumplimiento a la normativa de accesibilidad universal, se solicita eliminar el componente de pavimentación en vía pública y readecuar el diseño interior del predio. Esto debe permitir la incorporación de un estacionamiento accesible, asegurando la conectividad entre el espacio público y el acceso principal de la sede social sin requerir intervenciones externas a la propiedad, cumpliendo con lo establecido en artículo 4.1.7 de la OGUC. 3. Adjuntar carta de no fraccionamiento firmada por el alcalde y visada por unidad jurídica. 4. Se recomienda incorporar algún equipamiento necesario para el funcionamiento de la sede social, como: sillas, telón proyector, proyector, horno, refrigerador. EVALUACIÓN TÉCNICA - PRESUPUESTO 1. Debe incluir firma de todos los profesionales que participan del diseño y SECPLAN. 2. Incluir placa conmemorativa. 3. Partida “6.2 Protección ventanas” debe cubicarse por unidad o metros. 4. Partida “3.5.3. Ventanas” debe cubicarse por unidad. TTR y,o EETT 1. Para cada partida que corresponda, debe incluir al final de la especificación, el N° de lámina de planimetría donde se encuentra lo especificado. 2. Respeto de partida “4.2.1.5. Red Húmeda”, diseño debe quedar resuelto en el proyecto. 3. Debe incluir firma de todos los profesionales que participan del diseño y SECPLAN (EETT y Carta Gantt). 4. Incluir imágenes de referencia para los elementos del ítem “4.3 Artefactos Sanitarios”. PLANOS E INGENERÍA 1. Todos los planos deben incluir firma SECPLAN. Plano de arquitectura: 1. Verificar cumplimiento de normas de accesibilidad universal respecto a pendientes máximas de rampas de acceso, para el caso en el que se excede el 8% de pendiente. 2. Adjuntar planta de accesibilidad universal. 3. Incluir render del proyecto. 4. Debe señalar ubicación y largo de dren de aguas lluvias (sede social). 5. En la lámina 3/3, se requiere incorporar un mayor nivel de detalle en las secciones constructivas, especificando claramente la composición de tabiques y techumbre (revestimientos, aislación térmica con espesor y densidad, barreras de humedad, niveles, etc). 6. Debe indicar en una vista en elevación la ubicación de “Placa nombre sede”. 7. Incluir detalle de jardinera, según se indica en partida “6.4 Jardinera”. Plano de agua potable y sanitario: 1. No se define la red interior, ni los aparatos que la componen. Incluir también red húmeda y sistema termosolar. 2. Factibilidad de agua potable señala que el arranque no deberá ser mayor a 20 metros, sin embargo, en planos de proyecto de agua potable, se indica arranque de 22 metros de longitud. Plano de electricidad: 1. Debe incorporar artefacto termoeléctrico. 2. Indicar ubicación empalme. ANEXOS b) Ficha IDI: Adjuntar. j) Propiedad del terreno: Adjuntar certificado de hipoteca, gravámenes y prohibiciones. k) Certificado del DOM: Adjuntar certificado que acredite que el DOM y la SECPLAN están en conocimiento de los detalles del proyecto. l) Permiso de edificación: Adjuntar certificado de informaciones previas. s) Aprobaciones sectoriales: Adjuntar certificado de aprobación SERVIU. p) Proyecto de instalaciones domiciliarias: - Adjuntar memoria de cálculo proyecto sanitario. - Adjuntar memoria de cálculo proyecto agua potable. - Adjuntar memoria de cálculo proyecto eléctrico. q) Proyecto de especialidades: - Adjuntar memoria de cálculo estructural firmada por ingeniero civil. - Adjuntar mecánica de suelo con informe de laboratorio. r) Copia certificado de título: - Adjuntar patente municipal ingeniero civil. - Adjuntar certificado de título, patente municipal y certificado SEC profesional eléctrico. | N34: 46178 | Q34: La iniciativa es plenamente coherente con los lineamientos de "Bienestar socioterritorial" y "Cohesión e identidad sociocultural": Equipamiento Público: Se alinea con el lineamiento de construir equipamientos públicos y espacios de carácter cívico en la región. Infraestructura Comunitaria: Responde al objetivo de lograr que la comunidad cuente con la infraestructura necesaria para su desarrollo, generando condiciones para mejorar la calidad de vida de sus habitantes. Integración y Cohesión: Fomenta la creación de sedes sociales destinadas a la articulación de organizaciones de distinta índole, incluyendo agrupaciones de personas mayores. | R34: 3. Inclusión Social y Calidad de Vida Iniciativas de Apoyo Social: La construcción de esta sede permite apoyar directamente a los sectores más vulnerables de la población y a los adultos mayores, quienes actualmente no cuentan con un espacio propio. Desarrollo de Barrios: Fomenta la creación e instalación de sedes sociales y recintos comunitarios para fortalecer la vida barrial. 4. Participación Ciudadana y Gobernanza Participación Ciudadana: El proyecto se sustenta en la necesidad de generar espacios de diálogo, encuentro y participación activa de la comunidad en la toma de decisiones. Gestión y Descentralización: Al regularizar y ejecutar la obra, se da solución a una demanda postergada de la ciudadanía. | S34: 132 | T34: 172 | U34: 304 | V34: MUNICIPALIDAD DE OSORNO | W34: MUNICIPALIDAD DE OSORNO | X34: 7103 | Y34: 46111 | AA34: 46114 | AB34: 46115 | AC34: 46115 | AD34: =WORKDAY(AC34,15,'Feriados y Comunas'!A$2:A$26) -> 46136 | AE34: Dcastro | AJ34: 951 | AK34: 46136 | AL34: 46134 | AM34: OBSERVADO | AW34: Observado | AY34: =IFERROR(__xludf.DUMMYFUNCTION("IFERROR(COUNTA(SPLIT(AK34, "" "")), 0)"),1.0) -> 1
A35: 34 | B35: 40076942 | C35: 0 | D35: MEJORAMIENTO ESPACIO PUBLICO NAVEGANDO EL FUTURO xxvi | E35: Puerto Montt | F35: =+IFERROR(VLOOKUP(E35,'Feriados y Comunas'!$C$1:$D$36,2,FALSE),"") -> LLANQUIHUE | G35: 46122 | H35: 347646 | J35: Ejecución | K35: 2026 | L35: Multisectorial | M35: GENERALES 1. Se solicita adjuntar una minuta de respuesta a las observaciones formuladas. Debe indicar expresamente la manera mediante la cual se subsanó cada una de las observaciones técnicas y, en caso de que la corrección haya derivado en otras modificaciones al proyecto original, se deben señalar también todos los cambios, a fin de permitir una revisión integral de la coherencia del proyecto. ESTUDIO PREINVERSIONAL 1. Adjuntar formato PDF y firmado por profesional formulador. 2. Se requiere justificar la brecha en función del estándar de servicio, seguridad y accesibilidad universal y no solo de la cantidad de población. Asimismo, se debe precisar el déficit real de metros cuadrados (m2) de espacio público útil y justificar técnicamente por qué la oferta actual no suple las necesidades de los habitantes del sector. 3. Corregir y justificar la distribución de los beneficiarios por sexo (hombres y mujeres). Considerando la información del Censo 2017 contenida en el propio perfil (pág. 20), la proporción de la población es de 51,88% mujeres y 48,12% hombres. Corregir también en Ficha IDI. 4. Indicar cuantos son los metros cuadrados efectivos de intervención, ya que en no concuerda con lo indicado en Ficha IDI. EVALUACIÓN TÉCNICA - PRESUPUESTO 1. Hay 2 versiones del presupuesto. Dejar solo 1 para poder revisar el que corresponde. TTR y,o EETT 1. Formato de Carta Gantt dificulta su lectura. Cambiar a un formato más amigable. 2. Duración del proyecto indicado en Carta Gantt, no concuerda con lo señalado en Ficha IDI. PLANOS E INGENERÍA 1. Calidad de imagen de planos no permite su análisis. Adjuntar en formato DWG y mejorar resolución de planos. 2. Memoria de accesibilidad debe ser firmada por Arquitecto. ANEXOS a) Adjuntar oficio conductor de ingreso proyecto menor a 5000 UTM. k) Certificado DOM: - Adjuntar certificado Coordinación SECPLAN/DOM: Certificado que acredite que DOM y SECPLAN están en total conocimiento de los detalles del proyecto. n) Participación ciudadana: - Adjuntar listado de asistencia con registro fotográfico de la participación ciudadana con fecha y hora. j) Propiedad del terreno: - El certificado de registro de hipotecas y gravámenes presenta una inscripción por Servidumbre de tránsito. Es necesario más antecedentes respecto a esto: Adjuntar Plano y Registro de Servidumbre de Tránsito. - Por otro lado, en los mapas del SII se indica la existencia de un rol 12343- 46 dentro del polígono de intervención, del cual no se incorporan antecedentes en el proyecto. Se solicitan antecedentes para aclarar la situación. r) Copia de Certificado de título: - Adjuntar certificado de título profesional eléctrico. - Adjuntar patente al día de Arquitecto Sebastián Parada. s) Aprobaciones sectoriales: Adjuntar aprobación SERVIU. | N35: Pendiente | Q35: La iniciativa es plenamente coherente con los lineamientos de: 1. Bienestar socioterritorial Espacios y Equipamiento Público: "Construir nuevas áreas verdes de uso público como herramienta de esparcimiento e integración barrial en las ciudades de la región". "Aumentar el número de espacios polideportivos en la región, con criterios de género e inclusividad". 2. Cohesión e identidad sociocultural Integración Social: "Incentivar políticas y programas que favorezcan la inclusión social de personas en situación de discapacidad en la región". | R35: La propuesta se articula con los siguientes pilares programáticos del programa de gobierno: 1. Seguridad Pública i) Espacios Seguros: “Mejorar la iluminación y la seguridad en parques, plazas y áreas públicas para garantizar espacios seguros para todos los habitantes" m) Actividades Recreativas y Deportivas: “Fomentar actividades recreativas, culturales y deportivas para jóvenes, creando espacios de integración y desarrollo positivo" 3. Inclusión Social y Calidad de Vida k) Desarrollo Urbano Sostenible: “Promover políticas de desarrollo urbano que integren espacios verdes y respeten el entorno natural". | S35: 906 | T35: 906 | U35: 1812 | V35: MUNICIPALIDAD DE PUERTO MONTT | W35: MUNICIPALIDAD DE PUERTO MONTT | X35: S-319 | Y35: 46121 | AA35: 46122 | AB35: 46122 | AC35: 46122 | AD35: =WORKDAY(AC35,15,'Feriados y Comunas'!A$2:A$26) -> 46143 | AE35: Dcastro Dcastro | AJ35: 1042 2689 | AK35: 06-05-2026 09-09-2026 | AL35: 05-05-2026 09-09-2026 | AM35: OBSERVADO OBSERVADO | AN35: S-611 | AO35: 46217 | AQ35: 46218 | AW35: Observado | AY35: =IFERROR(__xludf.DUMMYFUNCTION("IFERROR(COUNTA(SPLIT(AK35, "" "")), 0)"),2.0) -> 2
A36: 35 | B36: 40078975 | C36: 0 | D36: HABILITACION SISTEMA DE MONITOREO Y RECONOCIMIENTO VEHICULAR CHILOE | E36: Prov. Chiloé | F36: =+IFERROR(VLOOKUP(E36,'Feriados y Comunas'!$C$1:$D$36,2,FALSE),"") -> CHILOÉ | G36: 46147 | H36: 280878 | J36: Ejecución | K36: 2026 | L36: Seguridad | M36: GENERALES 1. Se solicita adjuntar una minuta de respuesta a las observaciones formuladas. Este documento debe indicar expresamente la manera mediante la cual se subsanó cada una de las observaciones técnicas y, en caso de que la corrección haya derivado en otras modificaciones al proyecto original, se deben señalar también todos los cambios, a fin de permitir una revisión integral de la coherencia del proyecto. 2. Nombre del proyecto se debe corregir a “CONSTRUCCIÓN SISTEMA DE MONITOREO Y RECONOCIMIENTO VEHICULAR PROVINCIA DE CHILOE” o similar. Todos los documentos del proyecto deben actualizar nombre. 3. Adjuntar carta de no fraccionamiento firmada por el jefe de servicio. ESTUDIO PREINVERSIONAL 1. Perfil de proyecto debe incorporar firma de profesional formulador. 2. Se debe eliminar archivos adjuntos que están fuera del alcance del presente documento y que se deben presentar adjuntos como archivos individuales. Específicamente el Presupuesto y Carta Gantt. EVALUACIÓN TÉCNICA - PRESUPUESTO 1. En general, se debe reordenar el itemizado del presupuesto, ya que no sigue una metodología tradicional. El ordenamiento actual dificulta el seguimiento e interpretación al cruzar información con los EETT. Itemizado debe ser correlativo y desglosado correctamente. 2. Todos los precios indicados deben estar en Pesos Chilenos ($). Eliminar referencias a UF. 3. Se solicita reestructurar el presupuesto general del proyecto separando estrictamente las partidas en tablas diferenciadas según su clasificador presupuestario: por un lado, se deben agrupar los ítems de equipos (hardware, software, licencias y enlaces de comunicación) y, por otro, aislar de forma independiente los costos de obras civiles e infraestructura física (tales como la provisión e instalación de postes, canalizaciones, fundaciones, etc). 4. No puede haber partidas globales, estas deben ser desglosadas en subpartidas, cubicadas y presupuestadas correctamente. Además, detalladas en EETT. 5. Adjuntar el Presupuesto General y la Carta Gantt de forma independiente, generando un archivo individual para cada uno de estos antecedentes. Ambos deben venir en formato PDF y Excel. 6. Respecto a partida 1.5.3 indicada en EETT, se deben desglosar todas las subpartidas y presupuestar. 7. Carta Gantt debe abordar solo el plazo de ejecución del proyecto. No incluir el proceso administrativo previo y posterior. TTR y,o EETT 1. Se debe eliminar referencias a otros documentos adjuntos fuera del alcance del presente documento. Específicamente todo lo indicado en Anexos. 2. El itemizado de las partidas a ejecutar debe ser correlativo con Presupuesto y Carta Gantt. Debe haber concordancia absoluta. 3. Ítem 1.11 debe ser eliminado. Esto se sustituye por el punto de "Responsabilidades del contratista" para especialidades, que debe ser indicado en GENERALIDADES de las EETT. 4. EETT deben venir firmada por unidad formuladora y unidad técnica (profesionales que diseñan). 5. Incluir partida Letrero de Obras, y Placa conmemorativa. 6. Partida 1.5.4 debe desglosar subpartidas de obras civiles. Actualmente no se indican ni cubican: excavaciones y retiros, hormigón, canastillo o enfierradura, Poste octagonal, y otros. Por otro lado, se solicita que la necesidad de realizar un estudio de mecánica de suelos sea resuelta y sancionada por el profesional calculista del proyecto en esta etapa de diseño. Este deberá evaluar técnicamente la pertinencia del estudio para el diseño estructural propuesto que actualmente ya cuenta con un análisis estructural, asumiendo la responsabilidad sobre la suficiencia de los antecedentes del terreno utilizados en el cálculo. 7. Respecto a partida 1.1, 1.2, 1.3 y 1.4: el costo de la contratación del servicio debe quedar a cargo del respectivo municipio y indicado en el Certificado Compromiso de Absorción de Costos de operación y mantención. La habilitación, configuración y puesta en marcha a cargo del contratista. PLANOS E INGENERÍA 1. Planos eléctricos deben indicar poste, acometida aérea. 2. Planos deben estar firmados por profesional responsable, unidad formuladora y unidad técnica. 3. Se debe incorporar detalle de fundación proyectada indicando dimensiones en elevación. 4. Unificar unidades de medida en planta de fundación. ANEXOS b) Ficha IDI: Debe adjuntar como antecedente. d) Informe técnico de emplazamiento: Adjuntar un breve informe que se enfoque en indicar la ubicación exacta en la que se emplazaran los postes, acompañado de fotografías del lugar. e) Adjuntar archivo de georreferenciación (.kmz), de los puntos donde se proyectan los postes. h) Factibilidad eléctrica: Debe adjuntar certificados de factibilidad técnica de los organismos competentes, para los puntos de conexión proyectados. m) Certificado Compromiso de Absorción de Costos de operación y mantención: Debe ser certificado por el concejo municipal de ambos municipios beneficiados directamente. Debe indicar además el desglose de los costos asociados y proyectarlos durante la vida útil del proyecto. r) Copia certificado de título: Corresponde adjuntar para los profesionales responsables de diseño. s) Aprobaciones Sectoriales: Tras el análisis del emplazamiento del proyecto, se constata que aparentemente los puntos de instalación de los postes se encuentran en fajas de camino bajo tuición de la Dirección de Vialidad. Por lo tanto, se solicita adjuntar el pronunciamiento formal o la autorización de dicho organismo que valide la intervención en la red vial nacional. | N36: Pendiente | Q36: La iniciativa es plenamente coherente con los lineamientos de: Gobernanza regional y local: Objetivo Transversal / Temas Ejes: Promover la utilización de herramientas y plataformas tecnológicas de punta para optimizar la toma de decisiones, la planificación y la gestión integrada de la seguridad pública e institucionalidad regional. | R36: La propuesta se articula con los siguientes pilares programáticos del programa de gobierno: 1. Seguridad Pública: h) Videovigilancia Inteligente: proponer la instalación de sistemas de videovigilancia inteligente en puntos estratégicos, integrados con un centro de monitoreo regional para una respuesta rápida y eficaz. | V36: DIT | W36: UOCT | X36: 13420 | Y36: 46142 | AA36: 46147 | AB36: 46147 | AC36: 46148 | AD36: =WORKDAY(AC36,15,'Feriados y Comunas'!A$2:A$26) -> 46169 | AE36: Dcastro | AJ36: 1402 | AK36: 46183 | AL36: 46157 | AM36: OBSERVADO | AW36: Observado | AY36: =IFERROR(__xludf.DUMMYFUNCTION("IFERROR(COUNTA(SPLIT(AK36, "" "")), 0)"),1.0) -> 1
A37: 36 | B37: 40075435 | C37: 0 | D37: REPOSICION TALLER LABORAL COMUNITARIO, COMUNA DE COCHAMÓ | E37: Cochamó | F37: =+IFERROR(VLOOKUP(E37,'Feriados y Comunas'!$C$1:$D$36,2,FALSE),"") -> LLANQUIHUE | G37: 46177 | H37: 324664 | J37: Ejecución | K37: 2026 | L37: Vivienda | M37: 1. Ajuntar Perfil Firmado. 2. Anexar EETT con Firma de la UT. 3. Incorporar Ppto. OC. Firmado. 4. Adjuntar Ppto. Equipos, Equipamiento y AITO, si corresponde. 5. Incorporar Memorias explicativas de especialidades firmadas. 6. Adjuntar Carta de No Fraccionamiento. 7. Anexar Mecánica de suelos. 8. Incorporar Planos Firmados por profesional responsable. 9. Anexar Revisores Independientes. 10. Adjuntar Plan de Mitigación. 11. Incorporar Modelo de Gestión. 12. Anexar Informe Técnico Infraestructura Actual. 13. Adjuntar Certificado Hipotecas y gravámenes. 14. Incorporar C. I. P. 15. Adjuntar documentación al BIP. 16. La información solicitada resulta indispensable para llevar a cabo el análisis técnico exhaustivo del proyecto. | N37: Pendiente | V37: MUNICIPALIDAD DE COCHAMÓ | W37: MUNICIPALIDAD DE COCHAMÓ | X37: 402 | Y37: 46177 | AA37: 46177 | AB37: 46177 | AC37: 46177 | AD37: =WORKDAY(AC37,15,'Feriados y Comunas'!A$2:A$26) -> 46198 | AE37: Dcastro | AJ37: 1504 2063 | AK37: 17-06-2026 03-08-2026 | AL37: 16-06-2026 31-07-2026 | AM37: OBSERVADO OBSERVADO | AN37: 579 | AO37: 46231 | AQ37: 46232 | AW37: Observado | AY37: =IFERROR(__xludf.DUMMYFUNCTION("IFERROR(COUNTA(SPLIT(AK37, "" "")), 0)"),1.0) -> 1
A38: 37 | B38: 40064838 | C38: 0 | D38: REPOSICION CENTRO COMUNITARIO Y DELEGACION MUNICIPAL ISLA APIAO, COMUNA QUINCHAO | E38: Quinchao | F38: =+IFERROR(VLOOKUP(E38,'Feriados y Comunas'!$C$1:$D$36,2,FALSE),"") -> CHILOÉ | G38: 46177 | H38: 327411 | J38: Ejecución | K38: 2026 | L38: Vivienda | M38: GENERALES 1. Se solicita adjuntar una minuta de respuesta a las observaciones formuladas. Este documento debe indicar expresamente la manera mediante la cual se subsanó cada una de las observaciones técnicas y, en caso de que la corrección haya derivado en otras modificaciones al proyecto original, se deben señalar también todos los cambios, a fin de permitir una revisión integral de la coherencia del proyecto. 2. Adjuntar carta de no fraccionamiento firmada por alcalde y visada por unidad jurídica. 3. Es necesario replantear el diseño arquitectónico del proyecto, debido a que no se justifica técnicamente la desagregación de la iniciativa en dos infraestructuras independientes que duplican recintos de servicios (cada una con cocina, baño y comedor). Esta decisión de diseño fragmenta el Programa de Recintos propuesto y genera un perjuicio directo sobre la superficie del Salón Multipropósito. El salón multiuso constituye el espacio de mayor relevancia, representatividad y demanda social dentro de la infraestructura comunitaria de la Isla Apiao. Por otro lado, el plano ARQ12 grafica de manera explícita un achurado rojo sobre el sector de dormitorios, estar/comedor y cocina de la delegación bajo la leyenda: "ÁREA SIN ACCESO O ATENCIÓN A PÚBLICO. NO AFECTA A DS50". Esta exclusión es normativamente inadmisible. La Ley N°20.422 y las modificaciones del Decreto Supremo N°50/2015 incorporadas en la OGUC imponen que toda edificación de uso público o equipamiento debe garantizar el concepto de "Accesibilidad Universal" y "Diseño Universal" desde su origen en todo su entorno. Si bien el público general no ingresa habitualmente a las habitaciones, un funcionario, consultor o tallerista con discapacidad o movilidad reducida posee el derecho legal de pernoctar y circular en igualdad de condiciones de autonomía y seguridad. ESTUDIO PREINVERSIONAL 1. Se requiere un mayor grado de profundidad en el estudio Pre-inversional. Ajustarse a lo indicado en “Metodología General para la Formulación y Evaluación de Proyectos de Inversión Pública – SNI”. 2. Se debe incorporar registro de horarios de traslados diarios para uso público (durante los 7 días de la semana) entre Islas Quinchao y Apiao. 3. Cuantificación de la Demanda de Pernoctación: Presentar una Planta Funcionaria y Calendario Anual de Comisiones de Servicio. No basta con decir que se "ofrecen talleres"; se debe registrar el número de funcionarios municipales (asistentes sociales, veterinarios, inspectores de obras, médicos de rondas, etc.) y talleristas externos que efectivamente viajan al año, justificando técnicamente por qué la carga de trabajo requiere estadías de más de un día. 4. Certificación de Inexistencia de Oferta Privada: Incorporar un certificado formal de la Dirección de Turismo (DITUR) municipal o de la Oficina de Partes que declare el catastro de hospedajes formales en Isla Apiao, demostrando cuantitativamente que la oferta local privada es insuficiente, transformando la pernoctación municipal en una necesidad de fuerza mayor para la continuidad del servicio público. PLANOS E INGENIERÍA 1. Incorporar plano de situación actual de la infraestructura existente. 2. En lámina ARQ01, se debe indicar niveles de las plantas respecto al suelo. 3. Es necesario replantear el diseño arquitectónico, debido a que no se justifica separar el proyecto en 2 infraestructuras, cada una con cocina, baño, comedor. Esto en perjucio del espacio del salón multiuso, espacio de mayor relevancia dentro de la infraestructura. ANEXOS d) Informe técnico de emplazamiento: - Se necesita completar informe con más antecedentes respeto a rampa DOP, servidumbres de paso y ruta enrolada. - Se debe completar informe con un diagnóstico del estado actual de la estructura. j) Propiedad del terreno: - Adjuntar certificado de hipotecas y gravámenes. - Adjuntar antecedentes servidumbre de paso indicada en inscripción de dominio. - Adjuntar antecedentes comodato indicado en inscripción de dominio. o) Certificado de recepción municipal. p) Proyecto de instalaciones domiciliarias: - Adjuntar memoria proyecto eléctrico. - Adjuntar planos de proyecto de agua potable, certificado de factibilidad de dotación de comité de agua potable y aprobación de proyecto por autoridad sanitaria. q) Proyecto de especialidades: - Adjuntar estudio de mecánica de suelo con informe de laboratorio. r) Certificado de título: - Adjuntar Certificado SEC eléctrico. - Adjuntar patente municipal profesional patrocinador del proyecto. | N38: Pendiente | V38: MUNICIPALIDAD DE QUINCHAO | W38: MUNICIPALIDAD DE QUINCHAO | X38: 270 | Y38: 46177 | AA38: 46177 | AB38: 46177 | AC38: 46177 | AD38: =WORKDAY(AC38,15,'Feriados y Comunas'!A$2:A$26) -> 46198 | AE38: Dcastro | AJ38: 1466 | AK38: 46189 | AL38: 46188 | AM38: OBSERVADO | AW38: Observado | AY38: =IFERROR(__xludf.DUMMYFUNCTION("IFERROR(COUNTA(SPLIT(AK38, "" "")), 0)"),1.0) -> 1
A39: 38 | B39: 50002094 | C39: 0 | D39: CONSTRUCCION Espacio público recreativo Maratón, Puerto Montt | E39: Puerto Montt | F39: =+IFERROR(VLOOKUP(E39,'Feriados y Comunas'!$C$1:$D$36,2,FALSE),"") -> LLANQUIHUE | G39: 46196 | H39: 347000 | J39: Ejecución | K39: 2026 | L39: Multisectorial | M39: Archivos disponibles en BIP no son suficientes para poder iniciar la revisión. Verificar y adjuntar antecedentes del proyecto. | N39: Pendiente | V39: MUNICIPALIDAD DE PUERTO MONTT | W39: MUNICIPALIDAD DE PUERTO MONTT | X39: 492 | Y39: 46195 | AA39: 46196 | AB39: 46196 | AC39: 46196 | AD39: =WORKDAY(AC39,15,'Feriados y Comunas'!A$2:A$26) -> 46217 | AE39: Dcastro | AJ39: 1602 | AK39: 46199 | AL39: 46198 | AM39: OBSERVADO | AW39: Observado | AY39: =IFERROR(__xludf.DUMMYFUNCTION("IFERROR(COUNTA(SPLIT(AK39, "" "")), 0)"),1.0) -> 1
A40: 39 | B40: 50002090 | C40: 0 | D40: MEJORAMIENTO Espacio PÃºblico Rotonda La Paloma, Puerto Montt | E40: Puerto Montt | F40: =+IFERROR(VLOOKUP(E40,'Feriados y Comunas'!$C$1:$D$36,2,FALSE),"") -> LLANQUIHUE | G40: 46196 | H40: 347000 | J40: Ejecución | K40: 2026 | L40: Multisectorial | M40: CAMBIA CODIGO BIP 1. Archivos disponibles en BIP no son suficientes para poder iniciar la revisión. Verificar y adjuntar antecedentes del proyecto. 2. Corregir nombre de proyecto en BIP. | N40: Pendiente | V40: MUNICIPALIDAD DE PUERTO MONTT | W40: MUNICIPALIDAD DE PUERTO MONTT | X40: 491 | Y40: 46195 | AA40: 46196 | AB40: 46196 | AC40: 46196 | AD40: =WORKDAY(AC40,15,'Feriados y Comunas'!A$2:A$26) -> 46217 | AE40: Dcastro | AJ40: 1601 | AK40: 46199 | AL40: 46198 | AM40: OBSERVADO | AW40: Dado de baja | AY40: =IFERROR(__xludf.DUMMYFUNCTION("IFERROR(COUNTA(SPLIT(AK40, "" "")), 0)"),1.0) -> 1
A41: 40 | B41: 40079338 | C41: 0 | D41: CONSTRUCCION ACCESO Y MEJORAMIENTO SEGURIDAD VIAL POSTA QUETALCO, COMUNA DE DALCAHUE | E41: Dalcahue | F41: =+IFERROR(VLOOKUP(E41,'Feriados y Comunas'!$C$1:$D$36,2,FALSE),"") -> CHILOÉ | G41: 46189 | H41: 205940 | J41: Ejecución | K41: 2026 | L41: Salud | M41: GENERALES 1. Adjuntar minuta de respuesta a las observaciones formuladas. PLANOS E INGENIERÍA 1. Faltan firmas en planos. 2. Se debe asegurar accesibilidad universal desde los paraderos hasta la edificación pública. Adjuntar plano de accesibilidad. ANEXOS d) Informe técnico de emplazamiento: - Incluir en informe plano con deslindes de ambos predios. j) Propiedad del terreno: 177-90: Adjuntar Certificado de hipotecas, prohibiciones y gravámenes. k) Certificado coordinación SECPLAN/DOM. r) Certificado de título: Adjuntar certificado SEC profesional eléctrico. s) Certificado de no fraccionamiento: Debe venir firmado por alcalde y visado por unidad jurídica. | N41: Pendiente | S41: 456 | T41: 435 | U41: 891 | V41: MUNICIPALIDAD DE DALCAHUE | W41: MUNICIPALIDAD DE DALCAHUE | X41: 199 | Y41: 46189 | AA41: 46189 | AB41: 46189 | AC41: 46189 | AD41: =WORKDAY(AC41,15,'Feriados y Comunas'!A$2:A$26) -> 46210 | AE41: Dcastro Dcastro | AJ41: 1706 2589 | AK41: 03-07-2026 31-08-2026 | AL41: 03-07-2026 28-08-2026 | AM41: OBSERVADO OBSERVADO | AN41: 272 | AO41: 46206 | AQ41: 46238 | AW41: Observado | AY41: =IFERROR(__xludf.DUMMYFUNCTION("IFERROR(COUNTA(SPLIT(AK41, "" "")), 0)"),2.0) -> 2
A42: 41 | B42: 40080880 | C42: 0 | D42: CONSDTRUCCIÓN ESPACIO COMUNITARIO QUINCHO LA PICADA | E42: Puerto Octay | F42: =+IFERROR(VLOOKUP(E42,'Feriados y Comunas'!$C$1:$D$36,2,FALSE),"") -> OSORNO | G42: 46232 | H42: 348755 | J42: Ejecución | K42: 2026 | L42: Multisectorial | M42: 1. Ajustar ficha IDI y presupuesto, ya que está por sobre el monto permitido (Valor UTM al 31-12-25). 2. Corregir Descriptor IDI como iniciativa menor a 5000UTM. 3. Adjuntar Presupuesto Aito. Si corresponde. 4. Anexar Presupuesto Equipos y Equipamiento, si corresponde. 5. Incorporar Mecánica de Suelos. 6. Anexar Revisores Independientes. 7. Incorporar Modelo de Gestión. 8. Anexar Factibilidad Eléctrica. 9. Incorporar Planimetría Completa. 10. Adjuntar documentación al BIP. 11. La información solicitada resulta indispensable para llevar a cabo el análisis técnico exhaustivo del proyecto. | N42: Pendiente | S42: 300 | T42: 310 | U42: 610 | V42: MUNICIPALIDAD DE PUERTO OCTAY | W42: MUNICIPALIDAD DE PUERTO OCTAY | X42: 407 | Y42: 46226 | AA42: 46232 | AB42: 46232 | AC42: 46232 | AD42: =WORKDAY(AC42,15,'Feriados y Comunas'!A$2:A$26) -> 46253 | AE42: HSolervicens | AJ42: 2060 | AK42: 46234 | AL42: 46234 | AM42: OBSERVADO | AW42: Observado | AY42: =IFERROR(__xludf.DUMMYFUNCTION("IFERROR(COUNTA(SPLIT(AK42, "" "")), 0)"),1.0) -> 1
A43: 42 | B43: 40078828 | C43: 0 | D43: HABILITACION PLAZA DE ADIESTRAMIENTO PARA MASCOTAS EN EL PARQUE FRANCKE | E43: Osorno | F43: =+IFERROR(VLOOKUP(E43,'Feriados y Comunas'!$C$1:$D$36,2,FALSE),"") -> OSORNO | G43: 46184 | H43: 347900 | J43: Ejecución | K43: 2026 | L43: Multisectorial | N43: Pendiente | V43: MUNICIPALIDAD DE OSORNO | W43: MUNICIPALIDAD DE OSORNO | X43: 2026015391 | Y43: 46184 | AA43: 46184 | AB43: 46184 | AC43: 46184 | AD43: =WORKDAY(AC43,15,'Feriados y Comunas'!A$2:A$26) -> 46205 | AE43: Dcastro Dcastro | AJ43: 2115 2796 | AK43: 04-08-2026 14-09-2026 | AL43: 04-08-2026 14-09-2026 | AM43: OBSERVADO OBSERVADO | AN43: 22.686 | AO43: 46248 | AQ43: 46248 | AW43: Observado | AY43: =IFERROR(__xludf.DUMMYFUNCTION("IFERROR(COUNTA(SPLIT(AK43, "" "")), 0)"),2.0) -> 2
A44: 43 | B44: 40079646 | C44: 0 | D44: CONSTRUCCION MÓDULO DE ESTIMULACIÓN MULTISENSORIAL, SECTOR CONTAO, COMUNA DE HUALAIHUÉ | E44: Hualaihué | F44: =+IFERROR(VLOOKUP(E44,'Feriados y Comunas'!$C$1:$D$36,2,FALSE),"") -> PALENA | G44: 46208 | H44: 330000 | J44: Ejecución | K44: 2026 | L44: Salud | N44: Pendiente | V44: MUNICIPALIDAD DE HUALAIHUE | W44: MUNICIPALIDAD DE HUALAIHUE | X44: 670 | Y44: 46225 | AA44: 46239 | AB44: 46239 | AC44: 46239 | AD44: =WORKDAY(AC44,15,'Feriados y Comunas'!A$2:A$26) -> 46260 | AE44: Dcastro | AJ44: 2484 | AK44: 46258 | AL44: 46255 | AM44: OBSERVADO | AW44: Observado | AY44: =IFERROR(__xludf.DUMMYFUNCTION("IFERROR(COUNTA(SPLIT(AK44, "" "")), 0)"),1.0) -> 1
A45: 44 | B45: 40071282 | C45: 0 | D45: CONSTRUCCION GALPÓN GASTRONOMICO PARQUE TEGUEL, COMUNA DE DALCAHUE | E45: Dalcahue | F45: =+IFERROR(VLOOKUP(E45,'Feriados y Comunas'!$C$1:$D$36,2,FALSE),"") -> CHILOÉ | G45: 46224 | H45: 318789 | J45: Ejecución | K45: 2026 | L45: Turismo | N45: Pendiente | V45: MUNICIPALIDAD DE DALCAHUE | W45: MUNICIPALIDAD DE DALCAHUE | X45: 251 | Y45: 46224 | AA45: 46224 | AB45: 46224 | AC45: 46224 | AD45: =WORKDAY(AC45,15,'Feriados y Comunas'!A$2:A$26) -> 46245 | AE45: Dcastro | AJ45: 2540 | AK45: 46260 | AL45: 46260 | AM45: OBSERVADO | AW45: Observado | AY45: =IFERROR(__xludf.DUMMYFUNCTION("IFERROR(COUNTA(SPLIT(AK45, "" "")), 0)"),1.0) -> 1
A46: 45 | B46: 40076941 | C46: 0 | D46: HABILITACION ESPACIO PÚBLICO, POBLACIÓN LOS COLONOS DE ALERCE II | E46: Puerto Montt | F46: =+IFERROR(VLOOKUP(E46,'Feriados y Comunas'!$C$1:$D$36,2,FALSE),"") -> LLANQUIHUE | G46: 46240 | H46: 195010 | J46: Ejecución | K46: 2026 | L46: Multisectorial | N46: Pendiente | V46: MUNICIPALIDAD DE PUERTO MONTT | W46: MUNICIPALIDAD DE PUERTO MONTT | X46: S-0648 | Y46: 46239 | AA46: 46239 | AB46: 46239 | AC46: 46239 | AD46: =WORKDAY(AC46,15,'Feriados y Comunas'!A$2:A$26) -> 46260 | AE46: Dcastro | AJ46: 2495 | AK46: 46259 | AL46: 46258 | AM46: OBSERVADO | AW46: Observado | AY46: =IFERROR(__xludf.DUMMYFUNCTION("IFERROR(COUNTA(SPLIT(AK46, "" "")), 0)"),1.0) -> 1
A47: 46 | B47: 40077591 | C47: 0 | D47: MEJORAMIENTO CALZADA ALMIRANTE LATORRE | E47: Calbuco | F47: =+IFERROR(VLOOKUP(E47,'Feriados y Comunas'!$C$1:$D$36,2,FALSE),"") -> LLANQUIHUE | G47: 46241 | H47: 251829 | J47: Ejecución | K47: 2026 | L47: Transporte | N47: Pendiente | V47: MUNICIPALIDAD DE CALBUCO | W47: MUNICIPALIDAD DE CALBUCO | X47: 687 | Y47: 46241 | AA47: 46241 | AB47: 46241 | AC47: 46241 | AD47: =WORKDAY(AC47,15,'Feriados y Comunas'!A$2:A$26) -> 46262 | AE47: Dcastro | AJ47: 2690 | AK47: 46274 | AL47: 46273 | AM47: OBSERVADO | AW47: Observado | AY47: =IFERROR(__xludf.DUMMYFUNCTION("IFERROR(COUNTA(SPLIT(AK47, "" "")), 0)"),1.0) -> 1
A48: 47 | B48: 40081415 | C48: 0 | D48: MEJORAMIENTO ESPACIO PUBLICO ROTONDA LA PALOMA, PUERTO MONTT | E48: Puerto Montt | F48: =+IFERROR(VLOOKUP(E48,'Feriados y Comunas'!$C$1:$D$36,2,FALSE),"") -> LLANQUIHUE | G48: 46216 | H48: 345266 | J48: Ejecución | K48: 2026 | L48: Multisectorial | N48: Pendiente | V48: MUNICIPALIDAD DE PUERTO MONTT | W48: MUNICIPALIDAD DE PUERTO MONTT | X48: 602 | Y48: 46216 | AA48: 46216 | AB48: 46216 | AC48: 46216 | AD48: =WORKDAY(AC48,15,'Feriados y Comunas'!A$2:A$26) -> 46237 | AE48: Dcastro | AJ48: 2861 | AK48: 46286 | AL48: 46280 | AM48: OBSERVADO | AW48: Observado | AY48: =IFERROR(__xludf.DUMMYFUNCTION("IFERROR(COUNTA(SPLIT(AK48, "" "")), 0)"),1.0) -> 1
A49: 48 | B49: 40082188 | C49: 0 | D49: MEJORAMIENTO GIMNASIO MUNICIPAL DE CASTRO | E49: Castro | F49: =+IFERROR(VLOOKUP(E49,'Feriados y Comunas'!$C$1:$D$36,2,FALSE),"") -> CHILOÉ | G49: 46253 | H49: 332364 | J49: Ejecución | K49: 2026 | L49: Deportes | N49: Pendiente | V49: Municipalidad Castro | W49: Municipalidad Castro | X49: 1012 | Y49: 46252 | AA49: 46253 | AB49: 46253 | AC49: 46253 | AD49: =WORKDAY(AC49,15,'Feriados y Comunas'!A$2:A$26) -> 46274 | AE49: Dcastro | AJ49: 2827 | AK49: 46281 | AL49: 46279 | AM49: OBSERVADO | AW49: Observado | AY49: =IFERROR(__xludf.DUMMYFUNCTION("IFERROR(COUNTA(SPLIT(AK49, "" "")), 0)"),1.0) -> 1
A50: 49 | B50: 40079024 | C50: 0 | D50: CONSTRUCCION SEDE SOCIAL LOMAS DE BELLAVISTA, OSORNO | E50: Osorno | F50: =+IFERROR(VLOOKUP(E50,'Feriados y Comunas'!$C$1:$D$36,2,FALSE),"") -> OSORNO | G50: 46253 | H50: 223338 | J50: Ejecución | K50: 2026 | L50: Vivienda | N50: Pendiente | V50: MUNICIPALIDAD DE OSORNO | W50: MUNICIPALIDAD DE OSORNO | X50: 23151 | Y50: 46252 | AA50: 46253 | AB50: 46253 | AC50: 46253 | AD50: =WORKDAY(AC50,15,'Feriados y Comunas'!A$2:A$26) -> 46274 | AE50: Dcastro | AJ50: 2877 | AK50: 46287 | AL50: 46287 | AM50: OBSERVADO | AW50: Observado | AY50: =IFERROR(__xludf.DUMMYFUNCTION("IFERROR(COUNTA(SPLIT(AK50, "" "")), 0)"),1.0) -> 1
A51: 50 | B51: 40079109 | C51: 0 | D51: CONSTRUCCION CASA DE REUNIONES Y SABERES KUIFI PUÑEN, OSORNO | E51: Osorno | F51: =+IFERROR(VLOOKUP(E51,'Feriados y Comunas'!$C$1:$D$36,2,FALSE),"") -> OSORNO | G51: 46253 | H51: 210887 | J51: Ejecución | K51: 2026 | L51: Vivienda | N51: Pendiente | V51: MUNICIPALIDAD DE OSORNO | W51: MUNICIPALIDAD DE OSORNO | X51: 23153 | Y51: 46252 | AA51: 46253 | AB51: 46253 | AC51: 46253 | AD51: =WORKDAY(AC51,15,'Feriados y Comunas'!A$2:A$26) -> 46274 | AE51: Dcastro | AJ51: 2883 | AK51: 46288 | AL51: 46287 | AM51: OBSERVADO | AW51: Observado | AY51: =IFERROR(__xludf.DUMMYFUNCTION("IFERROR(COUNTA(SPLIT(AK51, "" "")), 0)"),1.0) -> 1
F52: =+IFERROR(VLOOKUP(E52,'Feriados y Comunas'!$C$1:$D$36,2,FALSE),"")
H53: =SUM(H5:H52) -> 12536026 | I53: =SUM(I5:I52) -> 2179729 | N53: =COUNTIF(N2:N52, "Pendiente") -> 23 | AO53: Observado | AW53: =COUNTIF(AW2:AW52, "Observado") -> 36
AO54: Recomendado | AW54: =COUNTIF(AW2:AW52, "Recomendado") -> 11
AO55: Dado de baja | AW55: =COUNTIF(AW2:AW52, "Dado de baja") -> 3

Sheet Feriados y Comunas
A1: Feriados | C1: Comuna | D1: PROVINCIA
A2: 45292 | C2: Puerto Montt | D2: LLANQUIHUE
A3: 45380 | C3: Puerto Varas | D3: LLANQUIHUE
A4: 45413 | C4: Cochamó | D4: LLANQUIHUE
A5: 45433 | C5: Calbuco | D5: LLANQUIHUE
A6: 45463 | C6: Maullín | D6: LLANQUIHUE
A7: 45489 | C7: Los Muermos | D7: LLANQUIHUE
A8: 45519 | C8: Fresia | D8: LLANQUIHUE
A9: 45553 | C9: Llanquihue | D9: LLANQUIHUE
A10: 45554 | C10: Frutillar | D10: LLANQUIHUE
A11: 45579 | C11: Prov. Llanquihue | D11: LLANQUIHUE
A12: 45596 | C12: Ancud | D12: CHILOÉ
A13: 45597 | C13: Castro | D13: CHILOÉ
... A26: 46016 | C26: Puerto Octay | D26: OSORNO
C27: Purranque | D27: OSORNO
C28: Río Negro | D28: OSORNO
C29: San Juan de la Costa | D29: OSORNO
C30: Prov. Osorno | D30: OSORNO
C31: Palena | D31: PALENA
C32: Chaitén | D32: PALENA
C33: Hualaihué | D33: PALENA
C34: Futaleufú | D34: PALENA
C35: Prov. Palena | D35: PALENA
C36: Regional | D36: REGIONAL

Sheet Ingresos
B2: N° | C2: Estado | D2: BIP | E2: Proyecto | F2: Comuna | G2: Oficio | H2: Recepción of. partes | I2: ARI | J2: Plazo Máx | K2: Estado plazo | L2: Estado Revisión | M2: Resultado
B3: 1 | C3: Nuevo | D3: 40079024 | E3: Construcción sede social Lomas de Bellavista | F3: Osorno | G3: 46252 | H3: 46253 | I3: Si | J3: =WORKDAY(H3, 21, 'Feriados y Comunas'!$A$2:$A$26) -> 46282 | K3: =IF(TODAY() > J3, "Atrasado", "Ok") -> Atrasado | L3: Ok | M3: Observado | O3: Plazos | P3: Días
B4: 2 | C4: Nuevo | D4: 40079109 | E4: Construcción casa de reuniones y saberes Kuifi Puñen | F4: Osorno | G4: 46252 | H4: 46253 | I4: Si | J4: =WORKDAY(H4, 21, 'Feriados y Comunas'!$A$2:$A$26) -> 46282 | K4: =IF(TODAY() > J4, "Atrasado", "Ok") -> Atrasado | L4: Ok | M4: Observado | O4: Verificación de Pertinencia y Admisibilidad | P4: 11
B5: 3 | C5: Nuevo | D5: 40082408 | E5: Construccion área esparcimiento Polloico | F5: Osorno | G5: 46258 | H5: 46258 | I5: No | J5: =WORKDAY(H5, 21, 'Feriados y Comunas'!$A$2:$A$26) -> 46287 | K5: =IF(TODAY() > J5, "Atrasado", "Ok") -> Atrasado | L5: Sin prioridad | M5: Pendiente | O5: Análisis y Evaluación Técnica (DIT) | P5: 10
B6: 4 | C6: 2da Ev | D6: 40081417 | E6: Constrrucción espacio público recreativo Maratón | F6: Puerto Montt | G6: 46261 | H6: 46261 | I6: Si | J6: =WORKDAY(H6, 21, 'Feriados y Comunas'!$A$2:$A$26) -> 46290 | K6: =IF(TODAY() > J6, "Atrasado", "Ok") -> Ok | L6: Ok | M6: Observado | O6: Reevaluación de la Iniciativa | P6: 10
B7: 5 | C7: 4ta Ev | D7: 40072916 | E7: Mejoramiento calle Padre Nicanor y Sor Teresa | F7: Puerto Varas | G7: 46261 | H7: 46261 | I7: Si | J7: =WORKDAY(H7, 21, 'Feriados y Comunas'!$A$2:$A$26) -> 46290 | K7: =IF(TODAY() > J7, "Atrasado", "Ok") -> Ok | L7: En revisión | M7: Pendiente
B8: 6 | C8: Nuevo | D8: 40081118 | E8: Reposición centro comunitario San Javier | F8: Curaco de Vélez | G8: 46265 | H8: 46265 | I8: Si | J8: =WORKDAY(H8, 21, 'Feriados y Comunas'!$A$2:$A$26) -> 46294 | K8: =IF(TODAY() > J8, "Atrasado", "Ok") -> Ok | L8: Pendiente | M8: Pendiente
B9: 7 | C9: Nuevo | D9: 40079931 | E9: Construcción pavimentacion cuestas Tolquien-Chullec | F9: Curaco de Vélez | G9: 46253 | H9: 46267 | I9: Si | J9: =WORKDAY(H9, 21, 'Feriados y Comunas'!$A$2:$A$26) -> 46296 | K9: =IF(TODAY() > J9, "Atrasado", "Ok") -> Ok | L9: Pendiente | M9: Pendiente
B10: 8 | C10: Nuevo | D10: 40081119 | E10: Reposición centro comuinitario productivo Huyar alto | F10: Curaco de Vélez | G10: 46265 | H10: 46267 | I10: Si | J10: =WORKDAY(H10, 21, 'Feriados y Comunas'!$A$2:$A$26) -> 46296 | K10: =IF(TODAY() > J10, "Atrasado", "Ok") -> Ok | L10: Pendiente | M10: Pendiente
B11: 9 | C11: Nuevo | D11: 40079935 | E11: Construcción pavimentaicón cuestas camino antiguo | F11: Curaco de Vélez | G11: 46253 | H11: 46269 | I11: Si | J11: =WORKDAY(H11, 21, 'Feriados y Comunas'!$A$2:$A$26) -> 46300 | K11: =IF(TODAY() > J11, "Atrasado", "Ok") -> Ok | L11: Pendiente | M11: Pendiente
B12: 10 | C12: 3era Ev | D12: 40079338 | E12: Construcción acceso y mejoramiento seguridad vial Posta Quetalco | F12: Dalcahue | G12: 46272 | H12: 46273 | I12: Si | J12: =WORKDAY(H12, 21, 'Feriados y Comunas'!$A$2:$A$26) -> 46302 | K12: =IF(TODAY() > J12, "Atrasado", "Ok") -> Ok | L12: Pendiente | M12: Pendiente
B13: 11 | C13: Nuevo | D13: 40071279 | E13: Construcción cuartel de bomberos 5ta compañia, cuerpo de Bomberos | F13: Dalcahue | G13: 46272 | H13: 46273 | I13: Si | J13: =WORKDAY(H13, 21, 'Feriados y Comunas'!$A$2:$A$26) -> 46302 | K13: =IF(TODAY() > J13, "Atrasado", "Ok") -> Ok | L13: Pendiente | M13: Pendiente
B14: 12 | C14: Reevaluación | D14: 40069991 | E14: Construcción módulos de antención primera de la red de salud comunal | F14: Frutillar | G14: 46273 | H14: 46273 | I14: - | J14: =WORKDAY(H14, 10, 'Feriados y Comunas'!$A$2:$A$26) -> 46287 | K14: =IF(TODAY() > J14, "Atrasado", "Ok") -> Atrasado | L14: Ok | M14: Observado
B15: 13 | C15: 2da Ev | D15: 40071282 | E15: Construcción galón gastronomico Parque Tenguel | F15: Dalcahue | G15: 46274 | H15: 46274 | I15: Si | J15: =WORKDAY(H15, 21, 'Feriados y Comunas'!$A$2:$A$26) -> 46303 | K15: =IF(TODAY() > J15, "Atrasado", "Ok") -> Ok | L15: Pendiente | M15: Pendiente
B16: 14 | C16: Nuevo | D16: No indica | E16: Pavimentación y aguas lluvia calle San Joaquin | F16: San Pablo | G16: 46269 | H16: 46276 | I16: No | J16: =WORKDAY(H16, 21, 'Feriados y Comunas'!$A$2:$A$26) -> 46307 | K16: =IF(TODAY() > J16, "Atrasado", "Ok") -> Ok | L16: Sin prioridad | M16: Pendiente
B17: 15 | C17: Nuevo | D17: No indica | E17: Construcción pórticos de acceso turísticos | F17: Hualaihué | G17: 46225 | H17: 46276 | I17: No | J17: =WORKDAY(H17, 21, 'Feriados y Comunas'!$A$2:$A$26) -> 46307 | K17: =IF(TODAY() > J17, "Atrasado", "Ok") -> Ok | L17: Sin prioridad | M17: Pendiente
B18: 16 | C18: 2da Ev | D18: 40075435 | E18: Reposición taller laboral | F18: Cochamó | G18: 46276 | H18: 46279 | I18: Si | J18: =WORKDAY(H18, 21, 'Feriados y Comunas'!$A$2:$A$26) -> 46308 | K18: =IF(TODAY() > J18, "Atrasado", "Ok") -> Ok | L18: Pendiente | M18: Pendiente
B19: 17 | C19: Nuevo | D19: 40079568 | E19: Construcción señalética indicativa y turística | F19: Cochamó | G19: 46276 | H19: 46279 | I19: Si | J19: =WORKDAY(H19, 21, 'Feriados y Comunas'!$A$2:$A$26) -> 46308 | K19: =IF(TODAY() > J19, "Atrasado", "Ok") -> Ok | L19: Pendiente | M19: Pendiente
B20: 18 | C20: Nuevo | D20: 40079128 | E20: Construcción sede social Villa Portal Osorno II | F20: Osorno | G20: 46276 | H20: 46279 | I20: Si | J20: =WORKDAY(H20, 21, 'Feriados y Comunas'!$A$2:$A$26) -> 46308 | K20: =IF(TODAY() > J20, "Atrasado", "Ok") -> Ok | L20: Pendiente | M20: Pendiente
B21: 19 | C21: Nuevo | E21: Habilitación pozo profundo San Pablo | F21: San Pablo | G21: 46281 | H21: 46281 | I21: Si | J21: =WORKDAY(H21, 21, 'Feriados y Comunas'!$A$2:$A$26) -> 46310 | K21: =IF(TODAY() > J21, "Atrasado", "Ok") -> Ok | L21: Pendiente | M21: Pendiente
B22: 20 | C22: Nuevo | D22: 40075706 | E22: Construcción centro comunitario multipropósito Trumao | F22: San Pablo | G22: 46281 | H22: 46281 | I22: Si | J22: =WORKDAY(H22, 21, 'Feriados y Comunas'!$A$2:$A$26) -> 46310 | K22: =IF(TODAY() > J22, "Atrasado", "Ok") -> Ok | L22: Pendiente | M22: Pendiente
B23: 21 | C23: Nuevo | D23: 40079222 | E23: Construcción centro comunitario Rahue II | F23: Osorno | G23: 46279 | H23: 46286 | I23: Si | J23: =WORKDAY(H23, 21, 'Feriados y Comunas'!$A$2:$A$26) -> 46315 | K23: =IF(TODAY() > J23, "Atrasado", "Ok") -> Ok | L23: Pendiente | M23: Pendiente
B24: 22 | C24: Nuevo | D24: 40080823 | E24: Mejoramiento plaza villa Bicentenario | F24: Fresia | G24: 46286 | H24: 46287 | I24: No | J24: =WORKDAY(H24, 21, 'Feriados y Comunas'!$A$2:$A$26) -> 46316 | K24: =IF(TODAY() > J24, "Atrasado", "Ok") -> Ok | L24: Pendiente | M24: Pendiente
B25: 23 | C25: 3er Ev | D25: 40075003 | E25: Mejoramiento plaza villa El Trebol | F25: Fresia | G25: 46288 | H25: 46288 | I25: Si | J25: =WORKDAY(H25, 21, 'Feriados y Comunas'!$A$2:$A$26) -> 46317 | K25: =IF(TODAY() > J25, "Atrasado", "Ok") -> Ok | L25: Pendiente | M25: Pendiente
B26: 23 | C26: Reevaluación | D26: 40075634 | E26: Mejoamiento plaza Vila Los Ríos | F26: Fresia | G26: 46289 | H26: 46289 | I26: Si | J26: =WORKDAY(H26, 10, 'Feriados y Comunas'!$A$2:$A$26) -> 46303 | K26: =IF(TODAY() > J26, "Atrasado", "Ok") -> Ok | L26: Pendiente | M26: Pendiente
C29: =COUNTIF(Ingresos[Estado],"Nuevo") -> 16 | D29: Nuevo | K29: Pendiente | L29: =COUNTIF(Ingresos[Estado Revisión], "Pendiente") -> 16
C30: =COUNTIF(Ingresos[Estado],"Ev") -> 0 | D30: n evaluación | K30: Ok | L30: =COUNTIF(Ingresos[Estado Revisión], "Ok") -> 4
C31: =COUNTIF(Ingresos[Estado],"Reevaluación") -> 2 | D31: Reevaluación | K31: Sin prioridad | L31: =COUNTIF(Ingresos[Estado Revisión], "Sin prioridad") -> 3
L32: =SUM(L29:L31) -> 23
