Workbook

Sheet Programas 2026
B1: Código | D1: Nombre | E1: Comuna | F1: Provincia | G1: Ingreso Of. Partes | H1: Monto M$ | I1: Etapa | J1: Proceso | K1: Sector | L1: Observaciones | M1: Objetivo del Pladeco | N1: Lineamiento ERD | O1: Plan del Gobernador | P1: H | Q1: M | R1: TOT | T1: Unidad Tecnica | U1: Formulador Proyecto | V1: ORD. Ingreso N° | W1: Fecha Ord. | X1: N° Exped. | Y1: Ingreso Of. Partes | Z1: Ingreso Of. Planificación | AA1: Fecha Derivado a Evaluador | AB1: Plazo evaluación | AD1: Derivado Unidad Técnica Evaluadora | AE1: Fecha Derivación | AF1: Reingreso Depto. Planif. | AG1: Fecha Evaluación | AI1: observaciones Ord. Gore N° | AJ1: Fecha Ord. | AK1: Fecha Ficha Evaluación | AL1: Informa | AM1: Ord.Resp. Obs. | AN1: Fecha Ord. | AO1: N° EXP. | AP1: Ingreso Oficina | AR1: ORD. GORE Observaciones | AS1: Fecha Ord. | AT1: Ord. Informa Pertinencia | AU1: Fecha ORD. | AV1: Estado Proyecto SEGÚN Haroldt | AW1: Dentro de 15 días
A2: 1 | B2: 40073088 | C2: 0 | D2: Transferencia Uso Eficiente de la Calefacción Residencial, Macro Zona Norte | E2: Regional | F2: Regional | G2: 45796 | H2: 2502275 | I2: Ejecución | J2: 2026 | K2: Recursos Naturales | L2: OK - Oficio 262 06-02-2026 | N2: Se encuentra dentro de la ERD en: Lineamiento: Bienestar Socio territorial Ítem: Medio Ambiente y Eficiencia energética. Obj.: Mejorar la calidad del aire por medio de la reducción de emisiones de los sistemas de calefacción, especialmente en las áreas urbanas. Actividad: No hay. | O2: Se enlaza con el programa del Gobernador Regional en el - Pilar 4. Protección del Medio Ambiente. - Letra ab) Energías Renovables: Fomentar el uso de energías limpias y renovables para reducir nuestra huella de carbono. | P2: 281119 | Q2: 291424 | R2: =SUM(P2:Q2) -> 572543 | T2: Medio Ambiente | U2: Medio Ambiente | V2: 3179 | W2: 45793 | AA2: 45796 | AB2: =WORKDAY(AA2,15,'Feriados y Comunas'!A$2:A$39) -> 45818 | AI2: 1302 3044 | AJ2: 17-06-2025 13-11-2025 | AK2: 13-06-2025 07-11-2025 | AL2: OBSERVADO | AM2: 5033 143 | AN2: 07-08-2025 09-01-2026 | AP2: 10-10-2025 16-01-2026 | AR2: 1302 3044 | AS2: 17-06-2025 13-11-2025 | AT2: 262 | AU2: 46059 | AV2: RECOMENDADO | AW2: 19 | AY2: 2 | AZ2: =NETWORKDAYS(G2,AU2) -> 190
A3: =1+A2 -> 2 | B3: 40073648 | C3: 0 | D3: Prevencion y Detección Temprana del Cancer | E3: Puerto Montt | F3: Prov. Llanquihue | G3: 45848 | H3: 400000 | I3: Ejecución | J3: 2025 | K3: Salud | L3: OK - Oficio 540 18-03-2026 (Derivado a DIDESOH) | N3: Se encuentra dentro de los lineamientos de la ERD en: Bienestar Socio territorial Ítem: Salud. Obj.: Ampliar la cobertura de atención primaria en salud en las comunas de la región. Aumentar oferta de especialistas en CESFAM. Actividad: No hay. | O3: Se enlaza con el programa del Gobernador Regional en el - Pilar: 3. Inclusión Social y Mejoramiento de la Calidad de Vida. - Letra: e) Acceso a Servicios de Salud: Ampliar y mejorar la red de servicios de salud, especialmente en zonas rurales, garantizando atención médica de calidad para todos. | P3: 17600 | Q3: 6800 | R3: =SUM(P3:Q3) -> 24400 | T3: Municipalidad Puerto Montt | U3: Municipalidad Puerto Montt | V3: 1546 | W3: 45848 | AA3: 45848 | AB3: =WORKDAY(AA3,15,'Feriados y Comunas'!A$2:A$39) -> 45870 | AI3: 1964 3073 | AJ3: 12-08-2025 14-11-2025 | AK3: 08-08-2025 14-11-2025 | AL3: OBSERVADO | AM3: 2372 128 | AN3: 16-10-2025 11-02-2026 | AP3: 16-10-2025 13-02-2026 | AT3: 540 | AU3: 46099 | AV3: OBSERVADO | AW3: 21 | AY3: 2 | AZ3: =NETWORKDAYS(G3,AU3) -> 180
A4: =1+A3 -> 3 | B4: 40071275 | C4: 0 | D4: Transferencia Fortalecimiento de la Internacionalización de PYMES Region de Los Lagos | E4: Regional | F4: Regional | G4: 45764 | H4: 248500 | I4: Ejecución | J4: 2026 | K4: Multisectorial | L4: OK - Oficio 966 27-04-2026 | N4: Se encuentra dentro de los lineamientos de la ERD en: Competitividad Regional Sustentable. Ítem: Diversificación de la Matriz Productiva con Enfoque Sustentable. Obj.: Potenciar la tecnificación del sector ganadero y de lácteos para diversificar y consolidar sus productos con valor agregado en mercados externos. Actividad: Programa de tecnificación dirigido a la sector ganadero y lácteos con enfoque de exportación. Capital Humano Calificado. Ítem: Acceso a capacitación en emprendimiento y áreas prioritarias. Obj: Mejorar la oferta de capacitación para mejorar y fomentar el emprendimiento local. Actividad: No Hay. | O4: Se enlaza con el programa del Gobernador Regional en el - Pilar 2. Desarrollo Económico Sostenible: una Alianza Público-Privada. - Letra b) Potenciar los desarrollos locales: incentivar la creatividad de los pequeños y medianos emprendedores mediante programas para escalar sus iniciativas | P4: 40 | Q4: 30 | R4: =SUM(P4:Q4) -> 70 | T4: Prochile | U4: Prochile | V4: 0 | W4: 45764 | AA4: 45765 | AB4: =WORKDAY(AA4,15,'Feriados y Comunas'!A$2:A$39) -> 45789 | AI4: 894 2323 3042 | AJ4: 13-05-2025 08-09-2025 13-11-2025 | AK4: 09-05-2025 05-09-2025 07-11-2025 | AL4: OBSERVADO | AM4: 3 4 206 | AN4: 14-08-2025 24-09-2025 27-03-2026 | AP4: 14-08-2025 24-09-2025 31-03-2026 | AR4: 894 2323 3042 | AS4: 13-05-2025 08-09-2025 13-11-2025 | AT4: 966 | AU4: 46139 | AV4: RECOMENDADO | AW4: 15 | AX4: OK | AY4: 3 | AZ4: =NETWORKDAYS(G4,AU4) -> 268
A5: =1+A4 -> 4 | B5: 40065461 | C5: 0 | D5: Transferencia Apoyo Salud Integral e Inclusión Social de Personas del Espectro Autista | E5: Prov. Osorno | F5: Prov. Osorno | G5: 45929 | H5: 1231664 | I5: Ejecución | J5: 2026 | K5: Salud | L5: OK - Oficio 1014 04-05-2026 | N5: Se encuentra dentro de los lineamientos de la ERD en: Bienestar Socio territorial Ítem: Salud. Obj.: Ampliar la cobertura de atención primaria en salud en las comunas de la región. Aumentar oferta de especialistas en CESFAM. Actividad: No hay. | O5: Se enlaza con el programa del Gobernador Regional en el Priorización de Inversiones Sectoriales y del FNDR para Nuevos Desafíos, Acción: Proyectos que aporten a la equidad territorial. | P5: 286 | Q5: 286 | R5: =SUM(P5:Q5) -> 572 | T5: Servicio Salud Osorno | U5: Servicio Salud Osorno | V5: 2945 | W5: 45912 | Y5: 45929 | Z5: 45929 | AA5: 45929 | AB5: =WORKDAY(AA5,15,'Feriados y Comunas'!A$2:A$39) -> 45950 | AI5: 2287 2992 2985 259 | AJ5: 25-09-2024 11-12-2024 07-11-2025 05-02-2026 | AK5: 26-09-2024 29-11-2024 07-11-2025 05-02-2026 | AL5: OBSERVADO | AM5: 2945 4200 1304 | AN5: 12-09-2025 28-11-2025 30-04-2026 | AP5: 29-09-2025 22-01-2026 30-04-2026 | AR5: 2287 2992 2985 259 | AS5: 25-09-2024 11-12-2024 07-11-2025 05-02-2026 | AT5: 1014 | AU5: 46146 | AV5: RECOMENDADO | AW5: 29 | AY5: 3 | AZ5: =NETWORKDAYS(G5,AU5) -> 156
A6: =1+A5 -> 5 | B6: 40079011 | C6: 0 | D6: Prevencion del Delito en los barrios: Fortalecimiento del vinculo Comunidad y Carabinertos de Chile. | E6: Regional | F6: Regional | G6: 46156 | H6: 196410 | I6: Ejecución | J6: 2026 | K6: Seguridad | L6: OK - Oficio 1474 16-06-2026 | N6: Se encuentra dentro de los lineamientos de la ERD en: Bienestar Socio territorial. Ítem: Espacio Publico y Equipamiento. Obj: Reducir el número de delitos de mayor connotación social en la Región. Actividad: No Hay. | O6: Se enlaza con el programa del Gobernador Regional en el - Pilar 1. Políticas Públicas en Materia de Seguridad Ciudadana. - Letra b) Prevención del Delito: Implementar programas de prevención en colaboración con las comunidades locales, escuelas y organizaciones sociales. | P6: 378 | Q6: 392 | R6: =SUM(P6:Q6) -> 770 | T6: Carabineros de Chile | U6: Municipalidad Puerto Montt | V6: 422 | W6: 46156 | AA6: 46156 | AB6: =WORKDAY(AA6,15,'Feriados y Comunas'!A$2:A$39) -> 46178 | AI6: 1254 | AJ6: 46168 | AK6: 46159 | AL6: OBSERVADO | AM6: 467 | AN6: 46170 | AP6: 46170 | AT6: 1474 | AU6: 46189 | AV6: RECOMENDADO | AW6: 3 | AX6: OK | AY6: 2 | AZ6: =NETWORKDAYS(G6,AU6) -> 24
A7: =1+A6 -> 6 | B7: 40075722 | C7: 0 | D7: Protección y Atención Integral al Desarrollo Infanto Adolecente TEA. | E7: Prov. Chiloé | F7: Prov. Chiloé | G7: 46114 | H7: 2048796 | I7: Ejecución | J7: 2026 | K7: Salud | L7: OK - Oficio 1568 24-06-2026 | N7: Se encuentra dentro de los lineamientos de la ERD: Bienestar Socio territorial Ítem: Salud. Obj.: Ampliar la cobertura de atención primaria en salud en las comunas de la región. Aumentar oferta de especialistas en CESFAM. Actividad: No hay. | O7: Se enlaza con el programa del Gobernador Regional: Pilar 3. Inclusión Social y Mejoramiento de la Calidad de Vidas. Letra e) Acceso a Servicios de Salud: Ampliar y mejorar la red de servicios de salud, especialmente en zonas rurales, garantizando atención médica de calidad para todos. | P7: 750 | Q7: 750 | R7: =SUM(P7:Q7) -> 1500 | T7: Servicio Salud Chiloe | U7: Servicio Salud Chiloe | V7: 661 | W7: 46114 | AA7: 46114 | AB7: =WORKDAY(AA7,15,'Feriados y Comunas'!A$2:A$39) -> 46136 | AI7: 2982 294 808 | AJ7: 07-11-2025 09-02-2026 15-04-2026 | AK7: 07-11-2025 06-02-2026 15-04-2026 | AL7: OBSERVADO | AM7: 1974 125 661 | AN7: 12-09-2025 16-01-2026 02-04-2026 | AP7: 16-06-2025 16-01-2026 02-04-2026 | AR7: 2982 294 808 | AS7: 07-11-2025 09-02-2026 15-04-2026 | AT7: 1568 | AU7: 46197 | AV7: RECOMENDADO | AW7: 10 | AY7: 1 | AZ7: =NETWORKDAYS(G7,AU7) -> 60
A8: =1+A7 -> 7 | B8: 40032300 | C8: 0 | D8: Capacitación Fomento Productivo, Asesoria Tecnica y Comercial al Turismo Natural y Cultural en Zonas de Rezago (ZDR) | E8: Regional | F8: Regional | G8: 46122 | H8: 556200 | I8: Ejecución | J8: 2026 | K8: Turismo | L8: Obs. Comité 17-04-26. 1. De acuerdo al instructivo de pertinencia de programas establecidos en la Res. Ex. 2645 del 28-06-25, los programas deben presentar Oficio Conductor, Perfil, Presupuesto detallado y Términos Técnicos de Referencia, los cuales deben estar en el Banco Integrado de Proyectos. Con el objeto de realizar un análisis de pertinencia y técnico de la iniciativa. Por lo tanto, se solicita: ● Incorporar perfil. ● Adjuntar Términos Técnicos de Referencia. ● Anexar Presupuesto Desglosado. ● Oficio Conductor. ● Adjuntar la documentación al BIP. 2. Adjuntar la Documentación al BIP. | N8: Se encuentra dentro de los lineamientos de la ERD en: Competitividad Regional Sustentable. Ítem: Desarrollo Turístico Sustentable. Obj.: Ampliar la cobertura de la oferta de servicios turísticos locales con base en los atributos naturales y culturales de la región. Actividad: Programa de fortalecimiento de idiomas para el turismo. Se enlaza con la política de Turismo e Imagen Región en: Eje Desarrollo y mejora competitividad de los destinos turísticos y sustentabilidad. Programa: Formalización y competitividad de la Oferta de servicios Turísticos sustentables. Iniciativa: Intervención para el desarrollo del turismo rural como fuente prioritaria de ingresos en territorios rurales. Plan de Zonas Rezagada de Territorio Insulares. - SI | O8: Se enlaza con el programa del Gobernador Regional en el - Pilar 2. Desarrollo Económico Sostenible: una Alianza Público-Privada. - Letra b) Potenciar los desarrollos locales: incentivar la creatividad de los pequeños y medianos emprendedores mediante programas para escalar sus iniciativas | P8: 150 | Q8: 150 | R8: =SUM(P8:Q8) -> 300 | T8: Indap | U8: Indap | V8: 1221 | W8: 46122 | Y8: 46122 | Z8: 46122 | AA8: 46122 | AB8: =WORKDAY(AA8,15,'Feriados y Comunas'!A$2:A$39) -> 46146 | AI8: 2855 896 841 | AJ8: 20-11-2024 13-05-2025 16-04-2026 | AK8: 15-11-2024 09-05-2025 17-04-2026 | AL8: OBSERVADO | AM8: 4190 418 1221 | AN8: 23-10-2024 27-01-2025 10-04-2026 | AO8: 112244/2024 113356/2025 | AP8: 24-10-2024 29-01-2025 10-04-2026 | AR8: 2855 896 841 | AS8: 20-11-2024 13-05-2025 16-04-2026 | AV8: OBSERVADO | AW8: 7 | AX8: OK | AY8: 2 | AZ8: =NETWORKDAYS(G8,AU8) -> -32945
A9: =1+A8 -> 8 | B9: 40071114 | C9: 0 | D9: Saneamiento Regularización Asentamientos de Chonchi | E9: Chonchi | F9: Prov. Chiloé | G9: 46188 | H9: 198976 | I9: Ejecución | J9: 2027 | K9: vivienda | L9: Obs. Comité 14-05-25. 1. El presente programa no se encuentra amparado en las glosas definidas para los Gobiernos Regionales ni especificados los programas a financiar. “La oferta programática de cada Gobierno Regional deberá respetar el principio de coherencia de las políticas públicas nacionales, coordinación, unidad de acción, eficiencia y eficacia, evitando la duplicidad o interferencia de funciones con otros órganos de la administración del estado”. Como en este caso es Bienes Nacionales. 2. Explorar financiamiento por medio de acciones concurrentes. | N9: Se encuentra dentro de los lineamientos de la ERD en: Bienestar Socio territorial. (Solo a nivel de definición) Ítem: No hay. Obj.: No hay. Actividad: No hay. | O9: Se enlaza con el programa del Gobernador Regional en el - Pilar 3. Inclusión Social y Mejoramiento de la Calidad de Vida. - Letra c) Programas de Apoyo Social: Desarrollar Iniciativas para apoyar a los sectores mas vulnerables de nuestra comunidad. | P9: 434 | Q9: 416 | R9: 850 | T9: Municipalidad Chonchi | U9: Municipalidad Chonchi | V9: 478 | W9: 46185 | AA9: 46188 | AB9: =WORKDAY(AA9,15,'Feriados y Comunas'!A$2:A$39) -> 46210 | AI9: 1019 | AJ9: 45800 | AK9: 45791 | AL9: OBSERVADO | AR9: 1019 | AS9: 45800 | AV9: OBSERVADO | AY9: 1 | AZ9: =NETWORKDAYS(G9,AU9) -> -32991
A10: =1+A9 -> 9 | B10: 40073176 | C10: 0 | D10: Protección Humedales Urbanos de la Región de Los Lagos | E10: Regional | F10: Regional | G10: 45796 | H10: 310600 | I10: Ejecución | J10: 2026 | K10: Recursos Naturales | L10: Obs. Comité 06-02-26.1. Del Diagnóstico: - Falta fuente de información al señalar limitaciones operativas del MMA. 2. Del Diagnóstico de la necesidad: - No se indica el año de referencia para los 21 humedales reconocidos. - No se informa cuántos humedales están judicializados. - Falta componente educativo explícito para colegios y ciudadanía. 3. De la Población beneficiaria: - Se debe aclarar si se trabajará sólo con colegios con certificación ambiental. - Inconsistencia entre beneficiarios directos e indirectos en distintos apartados. 4. Estrategia de intervención – Componentes 1 y 2: - Dudas sobre si talleres se limitan a los humedales piloto. - Ambigüedad sobre si todos los componentes se aplican solo a humedales piloto. 5. Indicadores y vinculación: - No se aclara si los 20 talleres son en total o por comuna. - Confusión en el concepto de plan piloto y si estos conversarán en futuro con los Planes de Gestión Integral (PGI) que mandatada por la Ley de Humedales Urbanos.). 6. De la Asamblea Climática: 7. No se especifican los humedales a intervenir: - El programa no identifica cuáles humedales serán abordados. Aunque se mencionan 35 en análisis, no hay una selección clara ni priorización definida. 8. Falta desagregación por humedal: - No se detallan actividades específicas ni criterios de priorización por humedal. Esto limita la trazabilidad territorial. 9. Limitado alcance de intervención directa: - Solo al menos 2 humedales serán parte de planes piloto, lo que limita el impacto directo del programa 10. Adjuntar la Documentación al BIP. | N10: Se encuentra dentro de los lineamientos de la ERD en: Ordenamiento territorial sustentable y resiliente. Ítem: Protección del patrimonio natural. Obj.: Promover el reconocimiento de los humedales urbanos por parte de los municipios Ley Nº21.202 sobre Humedales Urbanos. Política de Sostenibilidad Hídrica de la Región de Los Lagos (2021) - Seguridad hídrica para los ecosistemas. - Estrategia de acceso al agua para la prevención de eventos extremos: “Evaluar el rol hidráulico de los humedales urbanos. Actividad: Programa de tecnificación dirigido a la sector ganadero y lácteos con enfoque de exportación. | O10: Se enlaza con el programa del Gobernador Regional en el - Pilar 4. Protección del Medio Ambiente. - Letra a) Conservación de Recursos Naturales: Promover prácticas sostenibles y la conservación de nuestros ecosistemas. | P10: 2628 | Q10: 2724 | R10: =SUM(P10:Q10) -> 5352 | T10: Medio Ambiente | U10: Medio Ambiente | V10: 3178 | W10: 45793 | AA10: 45796 | AB10: =WORKDAY(AA10,15,'Feriados y Comunas'!A$2:A$39) -> 45818 | AI10: 1301 260 | AJ10: 17-06-2025 05-02-2026 | AK10: 13-06-2025 05-02-2026 | AL10: OBSERVADO | AP10: 46030 | AR10: 1301 260 | AS10: 17-06-2025 05-02-2026 | AV10: OBSERVADO | AW10: 19 | AY10: 1 | AZ10: =NETWORKDAYS(G10,AU10) -> -32711
A11: =1+A10 -> 10 | B11: 40074075 | C11: 0 | D11: Capacitación Plan Comunicacional y Socio educación Ambiental, Castro | E11: Castro | F11: Prov. Chiloé | G11: 45862 | H11: 129990 | I11: Ejecución | J11: 2026 | K11: Recursos Naturales | L11: Obs. Comité 06-02-26.1. Diagnóstico y Definición del Problema. - Redefinir el problema del programa de acuerdo a metodología no como la "falta de un plan comunicacional y capacidad para realizar jornadas". 2. Análisis de Población - Ajustar la población potencial ya que el programa es comunal no provincial. Por tanto, limitarse a quienes presentan el problema en el área de influencia directa. (objetivo y beneficiarios directos). 3. Estrategia - Justificar la viabilidad operativa de los 900 talleres en 24 meses (37 talleres mensuales). 4. De la MML - Redefinir el propósito no puede ser realizar los 900 talleres. - Revisar la coherencia entre propósito, componente y actividades, - El indicador del componente 1 debe ser de eficacia no de asistentes a los talleres, (Nro de talleres realizados v/s Planificados). 5. De los TTR. - Inconsistencia de la duración entre la ficha IDI, Perfil y TTR (son 24 o 30 meses). - Se reitera inconsistencia entre talleres e indicadores. - Ajustar el indicador de impacto, meta del 2% para una línea base del 0,1% es optimista, incorporar metas intermedias. - Especificar método de rendición de cuentas. 6. Adjuntar la Documentación al BIP. | N11: Se encuentra dentro de los lineamientos de la ERD en: Ordenamiento territorial sustentable y resiliente. Ítem: Protección del patrimonio natural. Obj.: Promover el reconocimiento de los humedales urbanos por parte de los municipios Ley Nº21.202 sobre Humedales Urbanos. Política de Sostenibilidad Hídrica de la Región de Los Lagos (2021) - Seguridad hídrica para los ecosistemas. - Estrategia de acceso al agua para la prevención de eventos extremos: “Evaluar el rol hidráulico de los humedales urbanos. Actividad: Programa de tecnificación dirigido a la sector ganadero y lácteos con enfoque de exportación. | O11: Se enlaza con el programa del Gobernador Regional en el - Pilar 4. Protección del Medio Ambiente. - Letra a) Conservación de Recursos Naturales: Promover prácticas sostenibles y la conservación de nuestros ecosistemas. | P11: 22832 | Q11: 24165 | R11: =SUM(P11:Q11) -> 46997 | T11: Municipalidad Castro | U11: Municipalidad Castro | V11: 677 | W11: 45839 | AA11: 45862 | AB11: =WORKDAY(AA11,15,'Feriados y Comunas'!A$2:A$39) -> 45883 | AI11: 2058 261 | AJ11: 19-08-2025 05-02-2026 | AK11: 08-08-2025 05-02-2026 | AL11: OBSERVADO | AM11: 1154 | AN11: 45960 | AP11: 46031 | AR11: 2058 261 | AS11: 19-08-2025 05-02-2026 | AV11: OBSERVADO | AW11: 11 | AX11: OK | AY11: 1 | AZ11: =NETWORKDAYS(G11,AU11) -> -32759
A12: =1+A11 -> 11 | B12: 40076275 | C12: 0 | D12: Transferencia Centro de Referencia Oncologica Integral Prov. Osorno | E12: Osorno | F12: Prov. Osorno | G12: 45929 | H12: 4396017 | I12: Ejecución | J12: 2026 | K12: Salud | L12: Obs. Comité 06-02-26.● Se reiteran las observaciones anteriores, ya que no se encuentra documentación cargada en el Bip, imposibilitando realizar un análisis técnico de la iniciativa.. ● De acuerdo al instructivo de pertinencia de programas establecidos en la Res. Ex. 2645 del 28-06-25, los programas deben presentar Oficio Conductor, Perfil, Presupuesto detallado y Términos Técnicos de Referencia, los cuales deben estar en el Banco Integrado de Proyectos. Con el objeto de realizar un análisis de pertinencia y técnico de la iniciativa. Por lo tanto, se solicita: ● Incorporar perfil. ● Adjuntar Términos Técnicos de Referencia. ● Anexar Presupuesto Desglosado. ● Oficio Conductor. ● Adjuntar la documentación al BIP. | N12: Se encuentra dentro de los lineamientos de la ERD en: Bienestar Socio territorial Ítem: Salud. Obj.: Ampliar la cobertura de atención primaria en salud en las comunas de la región. Aumentar oferta de especialistas en CESFAM. Actividad: No hay. | O12: Se enlaza con el programa del Gobernador Regional en el - Pilar: 3. Inclusión Social y Mejoramiento de la Calidad de Vida. - Letra: e) Acceso a Servicios de Salud: Ampliar y mejorar la red de servicios de salud, especialmente en zonas rurales, garantizando atención médica de calidad para todos. | P12: 1 | Q12: 1 | R12: =SUM(P12:Q12) -> 2 | T12: Servicio Salud Osorno | U12: Servicio Salud Osorno | V12: 2945 | W12: 45912 | AA12: 45929 | AB12: =WORKDAY(AA12,15,'Feriados y Comunas'!A$2:A$39) -> 45950 | AI12: 2987 257 | AJ12: 07-11-2025 05-02-2026 | AK12: 07-11-2025 05-02-2026 | AL12: OBSERVADO | AM12: 4200 2994 | AN12: 28-11-2025 10-09-2026 | AP12: 22-01-2025 10-09-2026 | AR12: 2987 257 | AS12: 07-11-2025 05-02-2026 | AV12: OBSERVADO | AW12: 29 | AY12: 1 | AZ12: =NETWORKDAYS(G12,AU12) -> -32806
A13: =1+A12 -> 12 | B13: 40072522 | C13: 0 | D13: Transferencia Fortalecimiento del Turismo Rural de San La Costa. | E13: San Juan de la Costa | F13: Prov. Osorno | G13: 45945 | H13: 501270 | I13: Ejecución | J13: 2026 | K13: Turismo | L13: Obs. Comité 19-12-25. 1. Falta Profesional Experto Se requerirá un profesional, dada las limitaciones de Infraestructura para tener las resoluciones sanitarias, parece necesario incorporar un asesor experto en la materia que gestione, facilite y asesore a la Unidad Ejecutoras y a los beneficiarios, que acompañe en la gestión de la Resolución Sanitaria, hasta obtenerla y hasta el término del programa. 2. Justificar el destino de experiencia técnica a la Isla de Pascua: El perfil del programa contempla en el componente “Acceso a Mercados y Visibilidad Turística Comercial”; la realización de dos giras técnicas bajo el ítem “Acciones de visitas y aprendizaje en terreno”. La Gira a la Isla de Pascua tiene un costo de 35 millones para 15 personas, consume casi un 7.4% del presupuesto total del programa, lo cual si miramos el diagnóstico que se presenta, lo más críticos es la infraestructura habilitante, considerando necesario (baños, cocinas). Se considera un costo unitario de 2.3 millones por persona lo que es un costo elevado, además no se justifica como llegaron a priorizar esas 15 personas de los 110 beneficiarios, porque algunos pueden participar y otros no, cual es el criterio de selección. Se recomienda tres alternativas, si tuviera que reemplazar la Gira a Isla de Pascua: a) Valle del Elqui (Región de Coquimbo) Esta alternativa tiene relación con la compra de un domo planetario móvil y capacitación en astronomía, a diferencia de Isla de Pascua que no es el referente nacional en astroturismo comercial, en cambio el Valle del Elqui si lo es. b) Curarrehue y Pucón (Región de la Araucanía) Esta alternativa refuerza el componente de la pertinencia cultural. Curarrehue es un referente turismo Indígena de alta gama y gastronomía con identidad (red de turismo mapuche). c) Archipiélago de Chiloé (Región de Los Lagos) Esta alternativa comparte condiciones geográficas (borde costero, clima) y culturales (fuerte sincretismo y presencia Williche) con San Juan de la Costa. | N13: Se encuentra dentro de los lineamientos de la ERD en: Competitividad Regional Sustentable. Ítem: Apoyo al emprendimiento y al Empleo Local. Obj.: Mayor apoyo financiero y asociatividad entre emprendedores de la región. Actividad: Programa de acompañamiento a los emprendedores. | O13: Se enlaza con el programa del Gobernador Regional en el - Pilar 2. Desarrollo Económico Sostenible: una Alianza Público-Privada. - Letra b)Potenciar los desarrollos locales: incentivar la creatividad de los pequeños y medianos emprendedores mediante programas dirigidos específicamente para escalar sus iniciativas. | T13: Municipalidad San Juan de La Costa | U13: Municipalidad San Juan de La Costa | V13: 940 | W13: 45945 | AA13: 45945 | AB13: =WORKDAY(AA13,15,'Feriados y Comunas'!A$2:A$39) -> 45967 | AI13: 3369 | AJ13: 46010 | AK13: 46010 | AL13: OBSERVADO | AV13: OBSERVADO | AW13: 45 | AY13: 1 | AZ13: =NETWORKDAYS(G13,AU13) -> -32818
A14: =1+A13 -> 13 | B14: 0 | C14: 0 | D14: Programa de Transferencia Sector Bentónico Artesanal de Los Lagos. | E14: Regional | F14: Regional | G14: 45964 | H14: 326600 | I14: Ejecución | J14: 2026 | K14: Pesca | L14: Obs. Comité 19-12-25. 1. De acuerdo al instructivo de pertinencia de programas establecidos en la Res. Ex. 2645 del 28-06-25, los programas deben presentar Oficio Conductor, Perfil, Presupuesto detallado y Términos Técnicos de Referencia, los cuales deben estar en el Banco Integrado de Proyectos. Con el objeto de realizar un análisis de pertinencia y técnico de la iniciativa. Por lo tanto, se solicita: 2. Incorporar perfil. 3. Adjuntar Términos Técnicos de Referencia. 4. Anexar Presupuesto Desglosado. 5. Oficio Conductor. 6. Adjuntar la Documentación al BIP. | N14: Se encuentra dentro de los lineamientos de la ERD en: Competitividad Regional Sustentable. Ítem: Apoyo al emprendimiento y al Empleo Local. Obj.: Mayor apoyo financiero y asociatividad entre emprendedores de la región. Actividad: Programa de acompañamiento a los emprendedores. Capital Humano Calificado. Ítem: Acceso a capacitación en emprendimiento y áreas prioritarias. Obj: Mejorar la oferta de capacitación para mejorar y fomentar el emprendimiento local. Actividad: No Hay. | O14: Se enlaza con el programa del Gobernador Regional en el - Pilar 2. Desarrollo Económico Sostenible: una Alianza Público-Privada. - Letra f) Fondo de Emprendimiento Regional: Establecer un fondo destinado a apoyar a emprendedores locales con un enfoque especial en mujeres y jóvenes. | T14: INDESPA | U14: INDESPA | V14: 544 | W14: 45964 | AA14: 45964 | AB14: =WORKDAY(AA14,15,'Feriados y Comunas'!A$2:A$39) -> 45985 | AI14: 3352 | AJ14: 46009 | AK14: 46009 | AL14: OBSERVADO | AV14: OBSERVADO | AW14: 31 | AY14: 1 | AZ14: =NETWORKDAYS(G14,AU14) -> -32831
A15: =1+A14 -> 14 | B15: 0 | C15: 0 | D15: Programa de Asistencia Técnica para la Pesca Artesanal de la Región de Los Lagos”. | E15: Regional | F15: Regional | G15: 45964 | H15: 326600 | I15: Ejecución | J15: 2026 | K15: Pesca | L15: Obs. Comité 19-12-25. 1. De acuerdo al instructivo de pertinencia de programas establecidos en la Res. Ex. 2645 del 28-06-25, los programas deben presentar Oficio Conductor, Perfil, Presupuesto detallado y Términos Técnicos de Referencia, los cuales deben estar en el Banco Integrado de Proyectos. Con el objeto de realizar un análisis de pertinencia y técnico de la iniciativa. Por lo tanto, se solicita: 2. Incorporar perfil. 3. Adjuntar Términos Técnicos de Referencia. 4. Anexar Presupuesto Desglosado. 5. Oficio Conductor. 6. Adjuntar la Documentación al BIP. | N15: Se encuentra dentro de los lineamientos de la ERD en: Competitividad Regional Sustentable. Ítem: Apoyo al emprendimiento y al Empleo Local. Obj.: Mayor apoyo financiero y asociatividad entre emprendedores de la región. Actividad: Programa de acompañamiento a los emprendedores. Capital Humano Calificado. Ítem: Acceso a capacitación en emprendimiento y áreas prioritarias. Obj: Mejorar la oferta de capacitación para mejorar y fomentar el emprendimiento local. Actividad: No Hay. | O15: Se enlaza con el programa del Gobernador Regional en el - Pilar 2. Desarrollo Económico Sostenible: una Alianza Público-Privada. - Letra f) Fondo de Emprendimiento Regional: Establecer un fondo destinado a apoyar a emprendedores locales con un enfoque especial en mujeres y jóvenes. | T15: INDESPA | U15: INDESPA | V15: 547 | W15: 45964 | AA15: 45964 | AB15: =WORKDAY(AA15,15,'Feriados y Comunas'!A$2:A$39) -> 45985 | AI15: 3353 | AJ15: 46009 | AK15: 46009 | AL15: OBSERVADO | AV15: OBSERVADO | AW15: 31 | AY15: 1 | AZ15: =NETWORKDAYS(G15,AU15) -> -32831
A16: =1+A15 -> 15 | B16: 40077572 | C16: 0 | D16: Transferencia Mecanización Agrícola, Provincia de Osorno. | E16: Prov. Osorno | F16: Prov. Osorno | G16: 46009 | H16: 1789000 | I16: Ejecución | J16: 2026 | K16: Recursos Naturales | L16: Obs. Comité 19-12-25. 1. De acuerdo al instructivo de pertinencia de programas establecidos en la Res. Ex. 2645 del 28-06-25, los programas deben presentar Oficio Conductor, Perfil, Presupuesto detallado y Términos Técnicos de Referencia, los cuales deben estar en el Banco Integrado de Proyectos. Con el objeto de realizar un análisis de pertinencia y técnico de la iniciativa. Por lo tanto, se solicita: 2. Incorporar perfil. 3. Adjuntar Términos Técnicos de Referencia. 4. Anexar Presupuesto Desglosado. 5. Oficio Conductor. 6. Adjuntar la Documentación al BIP. Aun cuanto la información proporcionada por la entidad formuladora es de carácter informal podemos sugerir. - La separación de subtítulos es un requisito técnico indispensable para la admisibilidad financiera del programa, garantizando que los gastos operacionales cuenten con la cobertura legal de las Transferencias Corrientes (Glosa 06) y que la inversión en activos fijos se mantenga íntegra en Transferencias de Capital (Glosa 11 y generales de inversión), evitando observaciones de legalidad por parte de la Dirección de Presupuestos o Contraloría General de la República. - Al igual se sugiere incorporar convenio de colaboración con INDAP como Unidad Técnica. - Respecto al diagnóstico, problema y estrategia: El documento menciona que la falta de mecanización limita la "soberanía alimentaria". Si bien es un argumento válido a nivel de Fin, se debe tener cuidado de no sobre-prometer este impacto a nivel de Propósito si no se acompaña de estrategias de comercialización o acceso a agua (aunque se menciona articulación con riego, esta es externa al programa). - De la Población Potencial y Objetivo: Al igualar la PO a la Población Beneficiaria (57 comunidades), se está ocultando la brecha real que el Estado deja sin atender. - De los indicadores: Revisar y precisar indicador de propósito ya que es intermedio. No mide el impacto final de la intervención. | N16: Se encuentra dentro de los lineamientos de la ERD en: Competitividad Regional Sustentable. Ítem: Apoyo al emprendimiento y al Empleo Local. Obj.: Mayor apoyo financiero y asociatividad entre emprendedores de la región. Actividad: Programa de acompañamiento a los emprendedores. Capital Humano Calificado. Ítem: Acceso a capacitación en emprendimiento y áreas prioritarias. Obj: Mejorar la oferta de capacitación para mejorar y fomentar el emprendimiento local. Actividad: No Hay. | O16: Se enlaza con el programa del Gobernador Regional en el - Pilar 2. Desarrollo Económico Sostenible: una Alianza Público-Privada. - Letra f) Fondo de Emprendimiento Regional: Establecer un fondo destinado a apoyar a emprendedores locales con un enfoque especial en mujeres y jóvenes. | T16: CONADI | U16: CONADI | V16: 659 | W16: 46009 | AA16: 46009 | AB16: =WORKDAY(AA16,15,'Feriados y Comunas'!A$2:A$39) -> 46034 | AI16: 3418 | AJ16: 46020 | AK16: 46020 | AL16: OBSERVADO | AV16: OBSERVADO | AW16: 7 | AX16: OK | AY16: 1 | AZ16: =NETWORKDAYS(G16,AU16) -> -32864
A17: =1+A16 -> 16 | B17: 40079402 | C17: 0 | D17: Programa Continuidad de Funcionamiento Servicio de Referencia Oncologica | E17: Prov. Chiloé | F17: Prov. Chiloé | G17: 46160 | H17: 1504562 | I17: Ejecución | J17: 2026 | K17: Salud | L17: Obs. Comité 23-06-26. 1. En primer lugar, es importante señalar que el programa anterior (N° 40057611-0) ya presenta un compromiso de continuidad, tal como se encuentra estipulado en la página 8 de los Términos de Referencia (TTR). En cuanto a su alcance y proyección, este programa abarca a toda la Provincia de Chiloé a través de instalaciones físicas ubicadas en la comuna de Ancud. Estas instalaciones dependen del Hospital de Ancud, debido a que en dicho recinto se encuentran activas las prestaciones de quimioterapia oral a cargo de la Hematóloga del centro. Además, se proyecta a mediano plazo que sea en el nuevo Hospital de Ancud donde se le dé continuidad definitiva a este programa tras sus actuales 24 meses de ejecución. | N17: Se encuentra dentro de los lineamientos de la ERD en: Bienestar Socio territorial Ítem: Salud. Obj.: Ampliar la cobertura de atención primaria en salud en las comunas de la región. Aumentar oferta de especialistas en CESFAM. Actividad: No hay. | O17: Se encuentra dentro de la Política Regional de Adulto Mayor en Lineamiento: Salud Obj.: Mejorar la calidad de vida de las personas mayores en situación de discapacidad en la región, mediante la promoción de la salud y la prevención de enfermedades. Actividad: Sistema de acceso oportuno a atención de salud de calidad para personas mayores. | P17: 598 | Q17: 602 | R17: =SUM(P17:Q17) -> 1200 | T17: SSChiloe | U17: SSChailoe | V17: 1017 | W17: 46157 | AA17: 46160 | AB17: =WORKDAY(AA17,15,'Feriados y Comunas'!A$2:A$39) -> 46182 | AI17: 1981 | AJ17: 46230 | AK17: 46196 | AL17: OBSERVADO | AV17: OBSERVADO | AW17: 25 | AZ17: =NETWORKDAYS(G17,AU17) -> -32971
A18: =1+A17 -> 17 | B18: 40080526 | C18: 0 | D18: Transferencia Mef Seadfood: Consolidacion de Unidades Productivas Formales Fotalecimiento de Beneficiarias | E18: Regional | F18: Regional | G18: 46254 | H18: 270000000 | I18: Ejecución | J18: 2026 | K18: Pesca | L18: Obs. Comité 04-09-26. 1. De conformidad con el Instructivo de Pertinencia de Programas, aprobado mediante la Res. Ex. N° 2645 del 28/06/2025, la iniciativa debe disponer en la plataforma del Banco Integrado de Proyectos (BIP) de los antecedentes mínimos obligatorios para efectuar su correcta evaluación técnica y de pertinencia. Por lo anterior, se solicita incorporar a la plataforma la siguiente documentación: 2. Perfil: Información técnica de la propuesta cargada y completada en el sistema. 3. Términos Técnicos de Referencia (TTR): Documento formal con el alcance de la ejecución. 4. Presupuesto desglosado: Detalle e ítemizado del cálculo de los costos proyectados. 5. Oficio conductor: Remisión debidamente firmado por la autoridad competente. De igual forma se sugiere aclarar: 6. Ficha IDI debe presentar a la etapa de ejecución. 7. Identificar claramente, si las 25 unidades productivas corresponden a 25 mujeres, ¿cómo lo indica la ficha IDI? Ya que además se indica que hay una población objetivo de 28 salas. De igual forma se indica que habrá una población potencial de 12.000 mujeres, por lo que no deja claro si podrían ser más mujeres o no. Se contradice en temas de cuantificación ya que indica 100 personas, 25 familias, un promedio de 4 personas, pero a la vez en la ficha IDI indica 25 mujeres beneficiadas. No se entiende en definitiva cuantos serán los beneficiarios. 8. Población: Debe identificar y detallar los beneficiaros directos, la cantidad de beneficiarios por provincia o comuna 9. Identificar como el programa seguirá ejecutando, después de los 24 meses 10. Presentar carta de compromiso, que indique el compromiso con el programa. 11. Incorporar cronograma. 12. Adjuntar Presupuesto en archivo aparte. 13. Anexar perfil de cargos a honorarios, si los hubiera en el presupuesto, si no presenta el detalle y cotizaciones, no se puede identificar si corresponde o no los gastos. 14. Adjuntar la Documentación al BIP. | N18: Se encuentra dentro del lineamiento "Competitividad Regional Sustentable" Item: Diversificación de la matriz productiva con enfoque sustentable Objetivo: Constribuir al desarrollo económico sostenible, la autonomía económica y la equidad de género en el borde costero de la Región. | O18: Se enlaza con Desarrollo Económico Sostenible b)Potenciar los desarrollos locales: incentivar la creatividad de los pequeños y medianos emprendedores mediante programas dirigidos específicamente para escalar sus iniciativas | Q18: 25 | R18: =SUM(P18:Q18) -> 25 | T18: Sercotec | U18: Sercotec | V18: 15 | W18: 46254 | AA18: 46254 | AB18: =WORKDAY(AA18,15,'Feriados y Comunas'!A$2:A$39) -> 46275 | AI18: 2657 | AJ18: 46272 | AK18: 46269 | AL18: OBSERVADO | AV18: OBSERVADO | AW18: 11 | AX18: OK | AZ18: =NETWORKDAYS(G18,AU18) -> -33039
A19: =1+A18 -> 18 | B19: 4005730110 | C19: 0 | D19: Transferencia Emporios Rurales en la Región de Los Lagos | E19: Regional | F19: Regional | G19: 46254 | H19: 194000000 | I19: Ejecución | J19: 2026 | K19: Turismo | L19: Obs. Comité 04-09-26.1. De conformidad con el Instructivo de Pertinencia de Programas, aprobado mediante la Res. Ex. N° 2645 del 28/06/2025, la iniciativa debe disponer en la plataforma del Banco Integrado de Proyectos (BIP) de los antecedentes mínimos obligatorios para efectuar su correcta evaluación técnica y de pertinencia. Por lo anterior, se solicita incorporar a la plataforma la siguiente documentación: 2. Perfil: Información técnica de la propuesta cargada y completada en el sistema. 3. Términos Técnicos de Referencia (TTR): Documento formal con el alcance de la ejecución. 4. Presupuesto desglosado: Detalle e ítemizado del cálculo de los costos proyectados. 5. Oficio conductor: Remisión debidamente firmado por la autoridad competente. De igual forma se sugiere aclarar: 6. Inconsistencia en Ficha IDI y perfil respecto al presupuesto 7. Beneficiarios: En ficha IDI presenta 80 beneficiarios, pero en el perfil identifica 40 almaceneros, se solicita aclarar y presentar información por provincia. 8. Matriz Marco Lógico: Error en el Fin y Propósito, presenta el mismo texto. 9. Adjuntar cronograma de actividades 10. Anexar presupuesto en archivo aparte. 11. Incorporar carta compromiso de la institución 12. Indicar de que forma el programa se podrá mantener, después de terminado el financiamiento de parte del Gore. Si el mismo servicio hará un plan de continuidad o tendrá alguna alianza con los municipios. 13. Adjuntar cotizaciones. 14. Incorporar perfil de cargos a honorarios, si los hubiera en el presupuesto, si no presenta el detalle y cotizaciones, no se puede identificar si se contemplan en el presupuesto. 15. Adjuntar la Documentación al BIP. | R19: =SUM(P19:Q19) -> 0 | T19: Sercotec | U19: Sercotec | V19: 16 | W19: 46254 | AA19: 46254 | AB19: =WORKDAY(AA19,15,'Feriados y Comunas'!A$2:A$39) -> 46275 | AI19: 2658 | AJ19: 46272 | AK19: 46269 | AL19: OBSERVADO | AV19: OBSERVADO | AW19: 11 | AX19: OK | AZ19: =NETWORKDAYS(G19,AU19) -> -33039
A20: =1+A19 -> 19 | B20: 40057322 | C20: 0 | D20: Transferencia desarrollo de tu barrio Comercial Región de Los Lagos | E20: Regional | F20: Regional | G20: 46254 | H20: 323394000 | I20: Ejecución | J20: 2026 | K20: Turismo | L20: Obs. Comité 04-09-26.1. De conformidad con el Instructivo de Pertinencia de Programas, aprobado mediante la Res. Ex. N° 2645 del 28/06/2025, la iniciativa debe disponer en la plataforma del Banco Integrado de Proyectos (BIP) de los antecedentes mínimos obligatorios para efectuar su correcta evaluación técnica y de pertinencia. Por lo anterior, se solicita incorporar a la plataforma la siguiente documentación: 2. Perfil: Información técnica de la propuesta cargada y completada en el sistema. 3. Términos Técnicos de Referencia (TTR): Documento formal con el alcance de la ejecución. 4. Presupuesto desglosado: Detalle e ítemizado del cálculo de los costos proyectados. 5. Oficio conductor: Remisión debidamente firmado por la autoridad competente. De igual forma se sugiere aclarar: 6. Diagnóstico: Se presenta a nivel nacional, no regional. La información presentada posee una antigüedad entre 5 a 7 años, se debe actualizar. El diagnóstico no logra dimensionar la población potencial y los objetivos de los barrios comerciales en la región. 7. El objetivo no es claro habla de 3 barrios, pero no se indica si son de la región, de la provincia de la comuna o abarca toda la región, se solicita focalizar. 8. Población: No se identifica cual será la población y quienes serán los beneficiarios. 9. Estrategia de intervención: No se identifica claramente la intervención, ya que no queda claro los 80 millones como serán distribuidos, que estrategia ocuparán para llegar a la población que requiere. 10. Cargos honorarios: Como no presentan cotizaciones, no se sabe si va existir gastos de honorarios, por lo que es importante presentar los antecedentes necesarios para respaldar el programa. 11. Adjuntar cronograma de actividades, presupuesto en archivo aparte, carta compromiso de la institución. 12. Indicar después de terminado el programa como se va a sustentar a largo plazo. 13. Adjuntar la Documentación al BIP. | R20: =SUM(P20:Q20) -> 0 | T20: Sercotec | U20: Sercotec | V20: 17 | W20: 46254 | AA20: 46254 | AB20: =WORKDAY(AA20,15,'Feriados y Comunas'!A$2:A$39) -> 46275 | AI20: 2659 | AJ20: 46272 | AK20: 46269 | AL20: OBSERVADO | AV20: OBSERVADO | AW20: 11 | AX20: OK | AZ20: =NETWORKDAYS(G20,AU20) -> -33039
A21: =1+A20 -> 20 | B21: 40082979 | C21: 0 | D21: Protección Fauna Silvestre Chiloé | E21: Prov. Chiloé | F21: Prov. Chiloé | G21: 46255 | H21: 398800 | I21: Ejecución | J21: 2026 | K21: Recursos Naturales | L21: Obs. Comite 04-09-26. 1. Del diagnóstico: mezcla causas estructurales directas con falencias de gestión municipal, sin cuantificar adecuadamente la línea de base del cambio conductual esperado. 2. Análisis de las poblaciones: Presenta inconsistencia entre el perfil y los TTR en cuanto a la población referencial y potencial. 3. Inconsistencia con la población objetivo entre perfil y TTR. Además, debe especificar los criterios de focalización, como los componentes atenderán directamente a un grupo acotado (1.345 beneficiarios directos: 20 profesionales municipales, 30 familias en fondo concursable, 400 en talleres), asumir 75.400 personas como población objetivo vicia el cálculo de cobertura real y el costo unitario por beneficiario. 4. De los componentes: componente1 especifica contratación de 2 profesionales para prestar servicios en municipios (TDR páginas 11 y 21). Según el Capítulo 2 de la Res. 2348 (página 39), los gastos destinados a suplir personal o gestión interna de otras instituciones no deben ser formulados como el bien/servicio principal de un programa de inversión regional. Asimismo, el Componente 2 considera inversión física (M$20.000) en terrenos del CEREFAS pertenecientes a la ONG Chiloé Silvestre (TDR página 12), lo cual requiere regularizar las condiciones de dominio, uso público o cláusulas de reversión según la Glosa 03 y Glosa 08 de la Ley de Presupuestos. 5. Reformular estructura presupuestaria de acuerdo a instructivo y por componentes. 6. De la MML. Propósito revisar redacción como un estado final/resultado alcanzado en la población u objeto de intervención. 7. Revisar componente 3 e indicadores de la matriz. De igual forma se sugiere aclarar: 8. Ficha IDI: Presenta Nombre del programa, distinto a los presentados en perfil y TTR, se solicita corregir. 9. Identificación de la Población: En la ficha IDI presenta un total de beneficiarios directos de 1.345, distribuidos en 550 hombres y 795 mujeres. Esa cifra no figura ni en el perfil ni en los TTR del programa, por lo que se necesita que se incorporé o corrija donde corresponda si hubiera un error. 10. Cotizaciones: No presenta cotizaciones 11. Perfil de cargos: No presenta perfil de cargo de las personas a honorarios que se contratará, además hay inconsistencia, en el perfil indica que son 2 profesionales para cuatro municipios por 6 meses, en los TTR indica que esos dos profesionales son para 12 meses, por lo que se contradice. Adicionalmente habla de que después el municipio los contratará, no indica cual, de los cuatro municipios, ni tampoco existe una carta de compromiso del o los municipios que van hacer la contratación. 12. Presupuesto: Presenta gastos de compra de container equipado y mejoramiento CEREFAS, como no presenta cotizaciones, no se puede identificar el detalle de este presupuesto por $60.000.000. Se solicita además presentar el presupuesto ordenado, ya que al sumar los presupuestos no queda claro la suma porque no hay un orden. Ya que por ejemplo el ítem de publicidad no suma $6.000.000, suma $6.610.000, de acuerdo al último cuadro de los TTR. 13. Presupuesto Referencial: El presupuesto que se presenta en el perfil si se suma el aporte propio, da un total de $439.403.018, no 438.603.018 como se indica, se solicita corregir. 14. Gastos operacionales: 15. Archivo Ppto y Carta Gantt: Se solicita que ambos documentos vengan en archivo a parte desglosados y detallados. 16. Mantención Centros de Rescate: Se solicita carta de compromiso de la Municipalidad de Quellón y Castro, las cuales serán las encargadas de la mantención y tratamiento inicial de los pacientes. 17. Propósito y Fin: El propósito que se presenta en la ficha IDI no es el mismo que se presenta en el perfil y TTR. De igual forma pasa con el “Fin”, no es el mismo que se presenta en ficha IDI. 18. Aportes de Terceros: Se solicita acreditar los aportes propios con un certificado de la Directora Regional del Servicio. Además, hay contradicciones en los TTR dice que el aporte será de $36.000.000 y el Perfil de $54.000.000. Existe una diferencia de $18.000.000 19. Carta compromiso ejecución programa: Se solicita carta compromiso que el Servicio se hará responsable de seguir el programa después de terminado el financiamiento. 20. Adjuntar la Documentación al BIP. | P21: 550 | Q21: 795 | R21: =SUM(P21:Q21) -> 1345 | T21: Servicio Biodiversidad y Areas Protegidas | U21: Servicio Biodiversidad y Areas Protegidas | V21: 1481 | W21: 46265 | AA21: 46266 | AB21: =WORKDAY(AA21,15,'Feriados y Comunas'!A$2:A$39) -> 46288 | AI21: 2701 | AJ21: 46275 | AK21: 46269 | AL21: OBSERVADO | AV21: OBSERVADO | AW21: 3 | AX21: OK | AZ21: =NETWORKDAYS(G21,AU21) -> -33040
A22: =1+A21 -> 21 | B22: 40080639 | C22: 0 | D22: Prevencion Cuidados Continuos Renales | E22: Puerto Montt | F22: Llanquihue | G22: 46256 | H22: 500000 | I22: Ejecución | J22: 2026 | K22: Salud | L22: Obs. Comité 04-09-261. De conformidad con el Instructivo de Pertinencia de Programas, aprobado mediante la Res. Ex. N° 2645 del 28/06/2025, la iniciativa debe disponer en la plataforma del Banco Integrado de Proyectos (BIP) de los antecedentes mínimos obligatorios para efectuar su correcta evaluación técnica y de pertinencia (Perfil TTR, PPto., Cotizaciones, entre otros). 2. Las glosas de los Gobiernos Regionales en su glosa 06 expresa claramente que solo podrán financiar “programas planes de resolución de lista de espera en coordinación con el ministerio de Salud”. ¿Cómo se justifica su programa?. 1. Ajustar perfil a formato establecido El nombre que indica en el perfil, no es el mismo presentado en la Ficha IDI Y oficio de presentación del programa, firmar responsable de formulación, se solicita corregir. 2. Reformular definición del problema, expresarse como una situación negativa de la realidad que afecta directamente el bienestar de la población. por ejemplo: "Alta tasa de progresión acelerada de la Enfermedad Renal Crónica en etapas 1 a 3 en usuarios de la Red de Atención Primaria de Salud de la comuna de Puerto Montt". 3. La cuantificación numérica de los beneficiarios directos del Año1 corresponde a Información no declarada en el documento de perfil principal. Adicionalmente incorporar los criterios de selección de la población objetivo. 4. Los Componentes 1 y 5 corresponden a actividades de difusión operativa, reuniones o capacitaciones intermedias/de gestión, no a la provisión directa de bienes o servicios finales entregados al paciente con ERC. 5. Ajustar la MML ya que presenta Indicadores de procesos y ejecución financiera asignados erróneamente en el nivel de componentes y actividades. 6. Reformular indicadores, mide avance de proceso/actividades, violando la definición de componente y para las actividades mide gestión financiera, no el avance físico en la realización de tareas. 7. Corregir Ficha IDI, Falta clasificación descriptor, Los gastos están cargados al ítem de consultora, de acuerdo a las Ris, debe imputarse el gasto como “Contratación de Programa” y no como consultoría. Falta identificar beneficiarios directos, se indican datos que no reflejan los presentados en la ficha. 8. Estrategia de intervención: El municipio no es claro en su estrategia de intervención, habla de 3 alternativas y presenta 6, deben definir su estrategia. 9. Presentar cotizaciones 10. Ejecución: Solo se permite duración del programa hasta 24 meses, se solicita reformular. 11. Ajustar cronograma a 24 meses de ejecución. 12. TTR: No presenta documento de Términos Técnicos de Referencia 13. Presupuesto: No se puede evaluar el presupuesto si no existe los respaldos necesarios de los gastos, para evaluar de forma correcta el programa. 14. Aportes de Terceros o Propios: Incorporar carta de compromiso Municipio que indique el aporte de la institución. 15. Carta compromiso de continuidad programa: Falta carta con el compromiso de que el Municipio realizará continuidad al programa, después de que se termine el financiamiento del programa. 16. Adjuntar la Documentación al BIP. | P22: 113000 | Q22: 100000 | R22: =SUM(P22:Q22) -> 213000 | T22: Municipalidad Puerto Montt | U22: Municipalidad Puerto Montt | V22: 712 | W22: 46266 | AA22: 46266 | AB22: =WORKDAY(AA22,15,'Feriados y Comunas'!A$2:A$39) -> 46288 | AI22: 2797 | AJ22: 46279 | AK22: 46269 | AL22: OBSERVADO | AV22: OBSERVADO | AW22: 3 | AX22: OK | AZ22: =NETWORKDAYS(G22,AU22) -> -33040
A23: =1+A22 -> 22 | R23: =SUM(P23:Q23) -> 0 | AB23: =WORKDAY(AA23,15,'Feriados y Comunas'!A$2:A$39) -> 20 | AL23: OBSERVADO | AV23: OBSERVADO | AX23: OK | AZ23: =NETWORKDAYS(G23,AU23) -> 0
A24: =1+A23 -> 23 | R24: =SUM(P24:Q24) -> 0 | AB24: =WORKDAY(AA24,15,'Feriados y Comunas'!A$2:A$39) -> 20 | AL24: OBSERVADO | AV24: OBSERVADO | AX24: OK | AZ24: =NETWORKDAYS(G24,AU24) -> 0
A25: =1+A24 -> 24 | R25: =SUM(P25:Q25) -> 0 | AB25: =WORKDAY(AA25,15,'Feriados y Comunas'!A$2:A$39) -> 20 | AL25: OBSERVADO | AV25: OBSERVADO | AX25: OK | AZ25: =NETWORKDAYS(G25,AU25) -> 0
AZ26: =NETWORKDAYS(G26,AU26) -> 0
AZ27: =NETWORKDAYS(G27,AU27) -> 0
AZ28: =NETWORKDAYS(G28,AU28) -> 0

Sheet Feriados y Comunas
A1: Feriados | C1: Comuna | D1: PROVINCIA
A2: 45658 | C2: Puerto Montt | D2: LLANQUIHUE
A3: 45765 | C3: Puerto Varas | D3: LLANQUIHUE
A4: 45778 | C4: Cochamó | D4: LLANQUIHUE
A5: 45798 | C5: Calbuco | D5: LLANQUIHUE
A6: 45828 | C6: Maullín | D6: LLANQUIHUE
A7: 45854 | C7: Los Muermos | D7: LLANQUIHUE
A8: 45884 | C8: Fresia | D8: LLANQUIHUE
A9: 45918 | C9: Llanquihue | D9: LLANQUIHUE
A10: 45919 | C10: Frutillar | D10: LLANQUIHUE
A11: 45961 | C11: Prov. Llanquihue | D11: LLANQUIHUE
A12: 45999 | C12: Ancud | D12: CHILOÉ
A13: 46016 | C13: Castro | D13: CHILOÉ
... A23: 46381 | C23: Osorno | D23: OSORNO
C24: San Pablo | D24: OSORNO
C25: Puyehue | D25: OSORNO
C26: Puerto Octay | D26: OSORNO
C27: Purranque | D27: OSORNO
C28: Río Negro | D28: OSORNO
C29: San Juan de la Costa | D29: OSORNO
C30: Prov. Osorno | D30: OSORNO
C31: Palena | D31: PALENA
C32: Chaitén | D32: PALENA
C33: Hualaihué | D33: PALENA
C34: Futaleufú | D34: PALENA
C35: Prov. Palena | D35: PALENA
C36: Regional | D36: REGIONAL
