Workbook

Sheet 2026
B1: Código | D1: Nombre | E1: Comuna | F1: Provincia | G1: Ingreso Of. Partes | H1: Monto M$ | I1: Etapa | J1: Proceso | K1: Sector | L1: Observaciones | M1: Objetivo del Pladeco | N1: Lineamiento ERD | O1: Plan del Gobernador | P1: H | Q1: M | R1: TOT | T1: Unidad Tecnica | U1: Formulador Proyecto | V1: ORD. Ingreso N° | W1: Fecha Ord. | X1: N° Exped. | Y1: Ingreso Of. Partes | Z1: Ingreso Of. Planificación | AA1: Fecha Derivado a Evaluador | AB1: Plazo evaluación | AC1: Derivado Unidad Técnica Evaluadora | AD1: Fecha Derivación | AE1: Reingreso Depto. Planif. | AF1: Fecha Evaluación | AH1: observaciones Ord. Gore N° | AI1: Fecha Ord. | AJ1: Fecha Ficha Evaluación | AK1: Informa | AL1: Ord.Resp. Obs. | AM1: Fecha Ord. | AN1: N° EXP. | AO1: Ingreso Oficina | AQ1: ORD. GORE Observaciones | AR1: Fecha Ord. | AS1: Ord. a MDSF | AT1: Fecha ORD. | AU1: Estado Proyecto SEGÚN Haroldt | AV1: Dentro de 15 días
A2: 1 | B2: 40073933 | C2: 0 | D2: Reposición con Relocalización Centro Rehabilitación Chiloé, Ancud | E2: Ancud | F2: CHILOÉ | G2: 45981 | H2: 189147 | I2: Diseño | J2: 2026 | K2: Salud | L2: Ok - Oficio 3289 15-12-25 | N2: Se encuentra dentro de los de la ERD en - lineamientos: Conectividad y Movilidad Regional Sustentable. - Ítem Conectividad insular y de lugares aislados. - Obj.: Disminuir el déficit de infraestructura de conectividad para territorios insulares y aislados de la región. | O2: Se enlaza con el Programa Regional del Gobernador en el - Pilar: 2. Desarrollo Económico Sostenible: una Alianza Público-Privada. - Letra: c) Inversiones en Infraestructura: Mejorar la conectividad y la infraestructura regional para atraer inversiones y generar empleo. | T2: Municipalidad Castro | U2: Municipalidad Castro | W2: 45973 | AA2: 45981 | AB2: =WORKDAY(AA2,15,'Feriados y Comunas'!A$2:A$25) -> 46003 | AS2: 3289 | AT2: 46006 | AU2: RECOMENDADO | AV2: OK | AW2: 15
A3: =1+A2 -> 2 | B3: 30116040 | C3: 0 | D3: Reposición Bodega y Galpon Municipal | E3: Palena | F3: PALENA | G3: 45681 | H3: 2152920 | I3: Ejecucion | J3: 2026 | K3: MultiSectorial | L3: Ok - Oficio 1017 23-05-25 | N3: La iniciativa se orienta dentro de la ERD en el, - Lineamiento: Conectividad y Movilidad Regional Sustentable. - Ítem: Conectividad Insular y Lugares Aislados. - Objetivo: Disminuir el déficit de infraestructura de conectividad para territorios aislados de la región. - Actividad: Plan de infraestructura de conectividad para territorios aislados. | O3: Se enlaza con el Programa Regional del Gobernador - Pilar: 6. Gobernanza y Participación Ciudadana. - Letra: c) Modernización Administrativa: Digitalizar los trámites y servicios administrativos para hacerlos más eficientes y accesibles. | P3: 922 | Q3: 768 | R3: 1690 | T3: Municipalidad Palena | U3: Municipalidad Palena | V3: 50 | W3: 45681 | X3: 113293/2025 | Y3: 45681 | Z3: 45684 | AA3: 45684 | AB3: =WORKDAY(AA3,15,'Feriados y Comunas'!A$2:A$25) -> 45705 | AH3: 394 | AI3: 45726 | AJ3: 45695 | AK3: OBSERVADO | AL3: 252 | AM3: 45764 | AO3: 45764 | AQ3: 394 | AR3: 45726 | AS3: 1017 | AT3: 45800 | AU3: RECOMENDADO
A4: =1+A3 -> 3 | B4: 40021925 | C4: 0 | D4: Reposición Estadio Municipal | E4: Quellón | F4: CHILOÉ | G4: 45811 | H4: 3688993 | I4: Ejecución | J4: 2026 | K4: Deporte | L4: Ok - Oficio 064 12-01-26 | N4: La iniciativa se orienta dentro de la ERD en el: - Lineamiento: Bienestar Socio Territorial. - Ítem: Espacios y Equipamiento Público - Objetivo: Aumentar el Nro. De espacios polideportivos en la región con criterios de genero e inclusividad. - Actividad: No hay. | O4: Se enlaza con el Programa Regional del Gobernador: - Pilar 3. Inclusión Social y Mejoramiento de la Calidad de Vida. - Letra c) Programas de Apoyo Social: Desarrollar iniciativas para apoyar a los sectores más vulnerables de nuestra comunidad. | P4: 18390 | Q4: 15830 | R4: 34220 | T4: Municipalidad Quellón | U4: Municipalidad Quellón | V4: 472 | W4: 45803 | Y4: 45811 | Z4: 45811 | AA4: 45811 | AB4: =WORKDAY(AA4,15,'Feriados y Comunas'!A$2:A$25) -> 45833 | AH4: 1500 2934 | AI4: 30-06-2025 04-11-2025 | AJ4: 27-06-2025 30-10-2025 | AK4: OBSERVADO | AL4: 849 | AM4: 45925 | AO4: 45929 | AQ4: 1500 2934 | AR4: 30-06-2025 04-11-2025 | AS4: 64 | AT4: 46034 | AU4: RECOMENDADO | AW4: 17
A5: =1+A4 -> 4 | B5: 40026214 | C5: 0 | D5: Reposición Reten San Juan de la Costa | E5: San Juan de La Costa | F5: OSORNO | G5: 46052 | H5: 154450 | I5: Diseño | J5: 2026 | K5: Seguridad | L5: Ok - Oficio 275 06-02-26 | N5: Se encuentra dentro de los lineamientos de la ERD en - Lineamiento: Bienestar Socio Territorial. - Ítem: Espacios y Equipamiento Público. - Obj.: Reducir el numero de delitos de mayor connotación social en la región. - Actividad: | O5: Se enlaza con el Programa Regional del Gobernador en el -Pilar: 1.Políticas Públicas en Materia de Seguridad Ciudadana -Letra: a)Fortalecimiento de las Fuerzas de Seguridad: Incrementar la presencia policial en las comunidades, disponiendo los recursos necesarios para dotarlas de mejor equipamiento y formación. | P5: 4011 | Q5: 3501 | R5: 7512 | T5: MOP - DA | U5: Carabineros de Chile | V5: 18 | W5: 46052 | Y5: 46052 | AA5: 46052 | AB5: =WORKDAY(AA5,15,'Feriados y Comunas'!A$2:A$25) -> 46073 | AS5: 275 | AT5: 46059 | AU5: RECOMENDADO | AV5: OK | AW5: 5
A6: =1+A5 -> 5 | B6: 40032330 | C6: 0 | D6: Analisis Alternativas de Abastecimiento de Agua Potable en Zonas de Rezago | E6: Regional | F6: REGIONAL | G6: 46009 | H6: 246829 | I6: Ejecución | J6: 2026 | K6: Recursos Hidricos | L6: Ok - Oficio 280 06-02-26 | N6: Se encuentra dentro de los lineamientos de la ERD en Lineamiento: Bienestar Socio Territorial. Ítem: Servicio Básicos. Obj.: Ampliar red de alcantarillado para dar soluciones sustentables a la población en la región. Actividad: Plan Construcción y Mejoramiento de infraestructura de agua potable y alcantarillado urbano y rural. | O6: Se enlaza con el Programa Regional del Gobernador en el lineamiento «Crear Condiciones Para Dar Acceso Al Agua - Plan Integral De Recursos Hídricos». | P6: 0 | Q6: 0 | R6: 0 | T6: Gobierno Regional de Los Lagos | U6: Gobierno Regional de Los Lagos | V6: 1426 | W6: 46009 | AA6: 46009 | AB6: =WORKDAY(AA6,15,'Feriados y Comunas'!A$2:A$25) -> 46031 | AS6: 280 | AT6: 46059 | AU6: RECOMENDADO | AW6: 35
A7: =1+A6 -> 6 | B7: 40035805 | C7: 0 | D7: Construcción Gimnasio Escuela Mirasol | E7: Puerto Montt | F7: =+IFERROR(VLOOKUP(E7,'Feriados y Comunas'!$C$1:$D$36,2,FALSE),"") -> LLANQUIHUE | G7: 45676 | H7: 1169652 | I7: Ejecución | J7: 2026 | K7: Educación | L7: Ok - Oficio 281 06-02-26 | N7: Se encuentra dentro de los lineamientos de la ERD en lineamiento Bienestar Socio Territorial, Ítem Educación, (Obj. Aumentar la cobertura territorial a los establecimientos de educación publica en los territorios rurales de la región). | O7: Se enlaza con el Programa Regional del Gobernador en el lineamiento “Priorización de Inversiones Sectoriales y del FNDR para Nuevos Desafíos”, Acción “Proyectos que aporten a la equidad territorial”. | P7: 305 | Q7: 354 | R7: =SUM(P7:Q7) -> 659 | T7: Municipalidad Puerto Montt | U7: Municipalidad Puerto Montt | V7: 33 | W7: 46037 | AA7: 46041 | AB7: =WORKDAY(AA7,15,'Feriados y Comunas'!A$2:A$25) -> 46062 | AS7: 281 | AT7: 46059 | AU7: RECOMENDADO | AV7: OK | AW7: 10
A8: =1+A7 -> 7 | B8: 40039645 | C8: 0 | D8: Habilitación SS EE ST Chapaco y Otros | E8: Río Negro | F8: =+IFERROR(VLOOKUP(E8,'Feriados y Comunas'!$C$1:$D$36,2,FALSE),"") -> OSORNO | G8: 46050 | H8: 647283 | I8: Ejecución | J8: 2026 | K8: Energía | L8: Ok - Oficio 515 16-03-26 | N8: Se encuentra dentro de los lineamientos de la ERD en Bienestar Socio Territorial. Ítem Medioambiente y Eficiencia Energética, (Obj. Reducir la Pobreza Energética en las viviendas de la Región). | O8: Se enlaza con el Programa Regional del Gobernador - Pilar: 3. Inclusión Social y Mejoramiento de la Calidad de Vida. - Letra: c) Programas de Apoyo Social: Desarrollar iniciativas para apoyar a los sectores más vulnerables de nuestra comunidad. | P8: 16 | Q8: 22 | R8: =SUM(P8:Q8) -> 38 | T8: Municipalidad Rio Negro | U8: Municipalidad Rio Negro | V8: 141 | W8: 46049 | AA8: 46050 | AB8: =WORKDAY(AA8,15,'Feriados y Comunas'!A$2:A$25) -> 46071 | AH8: 289 | AI8: 46059 | AJ8: 46059 | AK8: OBSERVADO | AL8: 196 | AM8: 46065 | AO8: 46065 | AQ8: 289 | AR8: 46059 | AS8: 515 | AT8: 46097 | AU8: RECOMENDADO | AV8: OK | AW8: 7
A9: =1+A8 -> 8 | B9: 40074574 | C9: 0 | D9: Mejoramiento y Ampliación SSR ST Pichihuilma | E9: Río Negro | F9: =+IFERROR(VLOOKUP(E9,'Feriados y Comunas'!$C$1:$D$36,2,FALSE),"") -> OSORNO | G9: 45924 | H9: 844156 | I9: Ejecución | J9: 2026 | K9: Recursos Hidricos | L9: Ok - Oficio 518 16-03-26 | N9: Se encuentra dentro de la ERD en: - Lineamiento: Bienestar Socio territorial. - Ítem: Servicio Básicos. - Obj.: Ampliar la Red de alcantarillado para dar soluciones sustentables. Reducir el numero de vivienda desconectadas de un sistema de suministro de agua en las áreas rurales de la región. - Actividad: Plan de construcción y mejoramiento de infraestructura agua potable y alcantarillado urbano y rural. | O9: Se enlaza con el Programa Regional del Gobernador en el - Pilar: 3. Inclusión Social y Mejoramiento de la Calidad de Vida - Letra: c)Programas de Apoyo Social: Desarrollar iniciativas para apoyar a los sectores más vulnerables de nuestra comunidad. | P9: 134 | Q9: 136 | R9: =SUM(P9:Q9) -> 270 | T9: Municipalidad Rio Negro | U9: Municipalidad Rio Negro | V9: 1161-79 | W9: 45909 | Y9: 45924 | Z9: 45924 | AA9: 45924 | AB9: =WORKDAY(AA9,15,'Feriados y Comunas'!A$2:A$25) -> 45945 | AH9: 2911 | AI9: 45964 | AJ9: 45960 | AK9: OBSERVADO | AL9: 293 | AM9: 46084 | AO9: 46084 | AQ9: 2911 | AR9: 45964 | AS9: 518 | AT9: 46097 | AU9: RECOMENDADO | AW9: 26
A10: =1+A9 -> 9 | B10: 40074940 | C10: 0 | D10: Diagnostico Plan de Manejo Area Protegida Lagos Huillinco y Cucao | E10: Chonchi | F10: =+IFERROR(VLOOKUP(E10,'Feriados y Comunas'!$C$1:$D$36,2,FALSE),"") -> CHILOÉ | G10: 45933 | H10: 55000 | I10: Ejecución | J10: 2026 | K10: Recursos Naturales | L10: Ok - Oficio 513 16-03-26 | N10: Se encuentra dentro de la ERD en: Lineamiento: Cohesión e Identidad Cultural. Ítem: Patrimonio Cultural. Obj.:. Actividad:. | O10: Se enlaza con el Programa Regional del Gobernador en el Pilar: 3. Protección del Medio Ambiente. Letra: d) Protección de Ecosistemas: Implementar políticas de conservación para proteger los ecosistemas de la región, especialmente los lagos y parques nacionales. | P10: 0 | Q10: 0 | R10: =SUBTOTAL(9,P10:Q10) -> 0 | T10: Municipalidad Chonchi | U10: Municipalidad Chonchi | V10: 839 | W10: 45926 | Y10: 45933 | Z10: 45933 | AA10: 45933 | AB10: =WORKDAY(AA10,15,'Feriados y Comunas'!A$2:A$25) -> 45954 | AH10: 2902 3281 292 | AI10: 3-11-2025 15-12-2025 06-02-2026 | AJ10: 30-10-2025 12-12-2025 06-02-2026 | AK10: OBSERVADO | AL10: 1116 152 | AM10: 23-12-2025 03-03-2026 | AO10: 23-12-2025 03-03-2026 | AQ10: 2902 3281 292 | AR10: 3-11-2025 15-12-2025 06-02-2026 | AS10: 513 | AT10: 46097 | AU10: RECOMENDADO | AW10: 19
A11: =1+A10 -> 10 | B11: 50000852 | C11: 0 | D11: Construcción Centro Deportivo V Centenario | E11: Osorno | F11: =+IFERROR(VLOOKUP(E11,'Feriados y Comunas'!$C$1:$D$36,2,FALSE),"") -> OSORNO | G11: 46086 | H11: 1756123 | I11: Ejecución | J11: 2026 | K11: Deporte | L11: Ok - Oficio 652 31-03-26 | N11: La iniciativa se orienta dentro de la ERD en el: - Lineamiento: Bienestar Socio Territorial. - Ítem: Espacios y Equipamiento Público - Objetivo: Aumentar el Nro. De espacios polideportivos en la región con criterios de genero e inclusividad. - Actividad: No hay. | O11: Se enlaza con el Programa Regional del Gobernador: - Pilar: 3. Inclusión Social y Mejoramiento de la Calidad de Vida. - Letra: c) Programas de Apoyo Social: Desarrollar iniciativas para apoyar a los sectores más vulnerables de nuestra comunidad. | P11: 0 | Q11: 0 | R11: =SUM(P11:Q11) -> 0 | T11: Municipalidad Osorno | U11: Municipalidad Osorno | V11: 4670 | W11: 46086 | AA11: 46086 | AB11: =WORKDAY(AA11,15,'Feriados y Comunas'!A$2:A$25) -> 46107 | AH11: 520 | AI11: 46097 | AJ11: 46094 | AK11: OBSERVADO | AL11: 6776 | AM11: 46106 | AO11: 46106 | AQ11: 520 | AR11: 46097 | AS11: 652 | AT11: 46112 | AU11: RECOMENDADO | AV11: OK | AW11: 7
A12: =1+A11 -> 11 | B12: 50000492 | C12: 0 | D12: Reposición Gimnasio Pedro Aguirre Cerda | E12: Osorno | F12: =+IFERROR(VLOOKUP(E12,'Feriados y Comunas'!$C$1:$D$36,2,FALSE),"") -> OSORNO | G12: 46079 | H12: 76160 | I12: Diseño | J12: 2026 | K12: Deporte | L12: Ok - Oficio 653 31-03-26 | N12: La iniciativa se orienta dentro de la ERD en el: - Lineamiento: Bienestar Socio Territorial. - Ítem: Espacios y Equipamiento Público - Objetivo: Aumentar el Nro. De espacios polideportivos en la región con criterios de genero e inclusividad. - Actividad: No hay. | O12: Se enlaza con el Programa Regional del Gobernador: - Pilar: 3. Inclusión Social y Mejoramiento de la Calidad de Vida. - Letra: c) Programas de Apoyo Social: Desarrollar iniciativas para apoyar a los sectores más vulnerables de nuestra comunidad. | P12: 0 | Q12: 0 | R12: =SUM(P12:Q12) -> 0 | T12: Municipalidad Osorno | U12: Municipalidad Osorno | V12: 4208 | W12: 46079 | AA12: 46079 | AB12: =WORKDAY(AA12,15,'Feriados y Comunas'!A$2:A$25) -> 46100 | AH12: 516 | AI12: 46097 | AJ12: 46094 | AK12: OBSERVADO | AL12: 6960 | AM12: 46108 | AO12: 46108 | AQ12: 516 | AR12: 46097 | AS12: 653 | AT12: 46112 | AU12: RECOMENDADO | AV12: OK | AW12: 11
A13: =1+A12 -> 12 | B13: 40049194 | C13: 0 | D13: MejoramientoVias Locales Sector Cañitas Etapa II | E13: Los Muermos | F13: =+IFERROR(VLOOKUP(E13,'Feriados y Comunas'!$C$1:$D$36,2,FALSE),"") -> LLANQUIHUE | G13: 46107 | H13: 1208289 | I13: Ejecución | J13: 2026 | K13: Transporte | L13: Ok - Oficio 720 07-04-26 | N13: Se encuentra dentro de los de la ERD en - lineamientos: Conectividad y Movilidad Regional Sustentable. - Ítem Conectividad insular y de lugares aislados. - Obj.: Disminuir el déficit de infraestructura de conectividad para territorios insulares y aislados de la región. | O13: Se enlaza con el Programa Regional del Gobernador en el - Pilar: 2. Desarrollo Económico Sostenible: una Alianza Público-Privada. - Letra: c) Inversiones en Infraestructura: Mejorar la conectividad y la infraestructura regional para atraer inversiones y generar empleo. | P13: 209 | Q13: 191 | T13: Municipalidad Los Muermos | U13: Municipalidad Los Muermos | V13: 554 | W13: 46106 | AA13: 46107 | AB13: =WORKDAY(AA13,15,'Feriados y Comunas'!A$2:A$25) -> 46128 | AS13: 720 | AT13: 46119 | AU13: RECOMENDADO | AV13: OK | AW13: 12
A14: =1+A13 -> 13 | B14: 40060318 | C14: 0 | D14: Habilitación SS EE Varios ST. Los Muermos | E14: Los Muermos | F14: =+IFERROR(VLOOKUP(E14,'Feriados y Comunas'!$C$1:$D$36,2,FALSE),"") -> LLANQUIHUE | G14: 45771 | H14: 311706 | I14: Ejecución | J14: 2027 | K14: Energía | L14: Ok - Oficio 778 13-04-26 | N14: Se encuentra dentro de los lineamientos de la ERD en Bienestar Socio Territorial. Ítem Medioambiente y Eficiencia Energética, (Obj. Reducir la Pobreza Energética en las viviendas de la Región). | O14: Se enlaza con el Programa Regional del Gobernador - Pilar: 3. Inclusión Social y Mejoramiento de la Calidad de Vida. - Letra: c) Programas de Apoyo Social: Desarrollar iniciativas para apoyar a los sectores más vulnerables de nuestra comunidad. | P14: 35 | Q14: 34 | R14: =SUM(P14:Q14) -> 69 | T14: Municipalidad Los Muermos | U14: Municipalidad Los Muermos | V14: 311 | W14: 46084 | AA14: 46086 | AB14: =WORKDAY(AA14,15,'Feriados y Comunas'!A$2:A$25) -> 46107 | AH14: 527 | AI14: 46098 | AJ14: 46094 | AK14: OBSERVADO | AL14: 355 | AM14: 46099 | AO14: 46100 | AS14: 778 | AT14: 46125 | AU14: RECOMENDADO | AV14: OK | AW14: 7
A15: =1+A14 -> 14 | B15: 40072627 | C15: 0 | D15: Habilitación SS EE Coihueria Complementario | E15: San Juan de la Costa | F15: =+IFERROR(VLOOKUP(E15,'Feriados y Comunas'!$C$1:$D$36,2,FALSE),"") -> OSORNO | G15: 45876 | H15: 798241 | I15: Ejecución | J15: 2026 | K15: Energía | L15: Ok - Oficio 777 13-04-26 | N15: Se encuentra dentro de los lineamientos de la ERD en Bienestar Socio Territorial. Ítem Medioambiente y Eficiencia Energética, (Obj. Reducir la Pobreza Energética en las viviendas de la Región). | O15: Se enlaza con el Programa Regional del Gobernador - Pilar: 3. Inclusión Social y Mejoramiento de la Calidad de Vida. - Letra: c) Programas de Apoyo Social: Desarrollar iniciativas para apoyar a los sectores más vulnerables de nuestra comunidad. | P15: 88 | Q15: 76 | R15: =SUM(P15:Q15) -> 164 | T15: Municipalidad San Juan de La Costa | U15: Municipalidad San Juan de La Costa | V15: 668 | W15: 45867 | Y15: 45876 | Z15: 45876 | AA15: 45876 | AB15: =WORKDAY(AA15,15,'Feriados y Comunas'!A$2:A$25) -> 45898 | AH15: 2123 | AI15: 45894 | AJ15: 45891 | AK15: OBSERVADO | AL15: 382 | AM15: 46099 | AO15: 46104 | AQ15: 2123 | AR15: 45894 | AS15: 777 | AT15: 46125 | AU15: RECOMENDADO | AV15: OK | AW15: 10
A16: =1+A15 -> 15 | B16: 40075419 | C16: 0 | D16: Reposición Gimnasio Municipal El Tepual | E16: Hualaihué | F16: =+IFERROR(VLOOKUP(E16,'Feriados y Comunas'!$C$1:$D$36,2,FALSE),"") -> PALENA | G16: 46036 | H16: 211597 | I16: Diseño | J16: 2026 | K16: Deporte | L16: Ok - Oficio 776 13-04-26 | N16: La iniciativa se orienta dentro de la ERD en el: - Lineamiento: Bienestar Socio Territorial. - Ítem: Espacios y Equipamiento Público - Objetivo: Aumentar el Nro. De espacios polideportivos en la región con criterios de genero e inclusividad. - Actividad: No hay. | O16: Se enlaza con el Programa Regional del Gobernador: - Pilar: 3. Inclusión Social y Mejoramiento de la Calidad de Vida. - Letra: c) Programas de Apoyo Social: Desarrollar iniciativas para apoyar a los sectores más vulnerables de nuestra comunidad. | T16: Municipalidad Hualaihue | U16: Municipalidad Hualaihue | V16: 10 | W16: 46030 | AA16: 46036 | AB16: =WORKDAY(AA16,15,'Feriados y Comunas'!A$2:A$25) -> 46057 | AH16: 293 | AI16: 46062 | AJ16: 46059 | AK16: OBSERVADO | AL16: 225 | AM16: 46105 | AO16: 46105 | AQ16: 293 | AR16: 46062 | AS16: 776 | AT16: 46125 | AU16: RECOMENDADO | AW16: 17
A17: =1+A16 -> 16 | B17: 40059318 | C17: 0 | D17: Reposición Segunda Cia. De Bomberos de Entre Lagos | E17: Puyehue | F17: OSORNO | G17: 45427 | H17: 71464 | I17: Diseño | J17: 2026 | K17: Seguridad | L17: Ok - Oficio 775 13-04-26 | N17: Se encuentra dentro de los lineamientos de la ERD Bienes Socio Territorial Ítem Espacios y Equipamiento Publico(Obj. Construir equipamiento publico y espacios de carácter cívico en la Región). | O17: Se enlaza con el Programa Regional del Gobernador en el - Pilar: 3. Inclusión Social y Mejoramiento de la Calidad de Vida. - Letra: c) Programas de Apoyo Social: Desarrollar iniciativas para apoyar a los sectores más vulnerables de nuestra comunidad. | P17: 5958 | Q17: 5709 | R17: =SUM(P17:Q17) -> 11667 | T17: Municipalidad Puyehue | U17: Municipalidad Puyehue | V17: 198 | W17: 46091 | AA17: 46092 | AB17: =WORKDAY(AA17,15,'Feriados y Comunas'!A$2:A$25) -> 46113 | AS17: 775 | AT17: 46125 | AU17: RECOMENDADO | AW17: 22
A18: =1+A17 -> 17 | B18: 50000703 | C18: 0 | D18: Construcción SSR de Puchilco | E18: Puqueldón | F18: =+IFERROR(VLOOKUP(E18,'Feriados y Comunas'!$C$1:$D$36,2,FALSE),"") -> CHILOÉ | G18: 46069 | H18: 2076098 | I18: Ejecución | J18: 2026 | K18: Recursos Hidricos | L18: Ok - Oficio 774 13-04-26 | N18: Se encuentra dentro de la ERD en: - Lineamiento: Bienestar Socio territorial. - Ítem: Servicio Básicos. - Obj.: Ampliar la Red de alcantarillado para dar soluciones sustentables. Reducir el numero de vivienda desconectadas de un sistema de suministro de agua en las áreas rurales de la región. - Actividad: Plan de construcción y mejoramiento de infraestructura agua potable y alcantarillado urbano y rural. | O18: Se enlaza con el Programa Regional del Gobernador en el - Pilar: 3. Inclusión Social y Mejoramiento de la Calidad de Vida - Letra: c)Programas de Apoyo Social: Desarrollar iniciativas para apoyar a los sectores más vulnerables de nuestra comunidad. | P18: 0 | Q18: 0 | R18: =SUM(P18:Q18) -> 0 | T18: Municipalidad Puqueldon | U18: Municipalidad Puqueldon | V18: 787 | W18: 46069 | AA18: 46069 | AB18: =WORKDAY(AA18,15,'Feriados y Comunas'!A$2:A$25) -> 46090 | AH18: 524 | AI18: 46097 | AJ18: 46094 | AK18: OBSERVADO | AL18: 155 | AM18: 46119 | AO18: 46120 | AQ18: 524 | AR18: 46097 | AS18: 774 | AT18: 46125 | AU18: RECOMENDADO | AW18: 19
A19: =1+A18 -> 18 | B19: 40025369 | C19: 0 | D19: Construcción PSR de Pichil | E19: Osorno | F19: =+IFERROR(VLOOKUP(E19,'Feriados y Comunas'!$C$1:$D$36,2,FALSE),"") -> OSORNO | G19: 46112 | H19: 1288486 | I19: Ejecución | J19: 2027 | K19: Salud | L19: Ok - Oficio 973 27-04-26 | N19: Se encuentra dentro de la ERD en el - Lineamiento: Bienestar Socio Territorial. - Ítem: Salud. - Objetivo: Aumentar Cobertura de atención primaria en salud en la comunas de la región. - Actividad: Convenio de Programación. | O19: Se enlaza con el programa del Gobernador Regional en el - Pilar: 3. Inclusión Social y Mejoramiento de la Calidad de Vida. - Letra: e) Acceso a Servicios de Salud: Ampliar y mejorar la red de servicios de salud, especialmente en zonas rurales, garantizando atención médica de calidad para todos. | P19: 330 | Q19: 357 | R19: =SUM(P19:Q19) -> 687 | T19: Muicipalidad Osorno | U19: Municipalidad Osorno | V19: 501 | W19: 46112 | AA19: 46121 | AB19: =WORKDAY(AA19,15,'Feriados y Comunas'!A$2:A$25) -> 46142 | AS19: 973 | AT19: 46139 | AU19: RECOMENDADO | AV19: OK | AW19: 12
A20: =1+A19 -> 19 | B20: 40043226 | C20: 0 | D20: Construcción APR St Llicaldad | E20: Castro | F20: =+IFERROR(VLOOKUP(E20,'Feriados y Comunas'!$C$1:$D$36,2,FALSE),"") -> CHILOÉ | G20: 45685 | H20: 2696176 | I20: Ejecución | J20: 2026 | K20: Recursos Hidricos | L20: Ok - Oficio 1215 20-05-26 | N20: Se encuentra dentro de la ERD en: - Lineamiento: Bienestar Socio territorial. - Ítem: Servicio Básicos. - Obj.: Ampliar la Red de alcantarillado para dar soluciones sustentables. Reducir el numero de vivienda desconectadas de un sistema de suministro de agua en las áreas rurales de la región. - Actividad: Plan de construcción y mejoramiento de infraestructura agua potable y alcantarillado urbano y rural. | O20: Se enlaza con el Programa Regional del Gobernador en el - Pilar: 3. Inclusión Social y Mejoramiento de la Calidad de Vida - Letra: c)Programas de Apoyo Social: Desarrollar iniciativas para apoyar a los sectores más vulnerables de nuestra comunidad. | P20: 550 | Q20: 590 | R20: =SUM(P20:Q20) -> 1140 | T20: Municipalidad Castro | U20: Municipalidad Castro | V20: 96 | W20: 45684 | X20: 113380/2025 | Y20: 45685 | Z20: 45692 | AA20: 45692 | AB20: =WORKDAY(AA20,15,'Feriados y Comunas'!A$2:A$25) -> 45713 | AH20: 349 1225 796 | AI20: 05-03-2025 09-06-2025 14-04-2026 | AJ20: 05-03-2025 09-06-2025 10-04-2026 | AK20: OBSERVADO | AL20: 227 287 477 | AM20: 04-03-2025 10-03-2026 27-04-2026 | AO20: 26-05-2025 23-03-2026 04-05-2026 | AQ20: 349 1225 796 | AR20: 05-03-2025 09-06-2025 14-04-2026 | AS20: 1215 | AT20: 46162 | AU20: RECOMENDADO | AV20: OK | AW20: 3
A21: =1+A20 -> 20 | B21: 40072664 | C21: 0 | D21: Reposición Parcial y Habilitación 3° Cía. De Bomberos, Osorno. | E21: Osorno | F21: OSORNO | G21: 45987 | H21: 75863 | I21: Diseño | J21: 2026 | K21: Seguridad | L21: Ok - Oficio 1216 20-05-26 | N21: Se encuentra dentro de los lineamientos de la ERD - Lineamiento: Bienes Socio Territorial. Ítem: Espacios y Equipamiento Publico. Obj.: Construir equipamiento publico y espacios de carácter cívico en la Región. | O21: Se enlaza con el Programa Regional del Gobernador en el - Pilar: 3. Inclusión Social y Mejoramiento de la Calidad de Vida. - Letra: c) Programas de Apoyo Social: Desarrollar iniciativas para apoyar a los sectores más vulnerables de nuestra comunidad. | T21: Municipalidad Osorno | U21: Municipalidad Osorno | V21: 12702 | W21: 45987 | AA21: 45987 | AB21: =WORKDAY(AA21,15,'Feriados y Comunas'!A$2:A$25) -> 46009 | AH21: 3280 792 | AI21: 15-12-2025 14-04-2026 | AJ21: 12-12-2025 10-04-2026 | AK21: OBSERVADO | AL21: 7058 9908 | AM21: 30-03-2026 24-04-2026 | AO21: 31-03-2026 24-04-2026 | AQ21: 3280 792 | AR21: 15-12-2025 14-04-2026 | AS21: 1216 | AT21: 46162 | AU21: RECOMENDADO | AV21: OK | AW21: 13
A22: =1+A21 -> 21 | B22: 40076987 | C22: 0 | D22: Construcción Servicio APR Lago Chapo | E22: Puerto Montt | F22: =+IFERROR(VLOOKUP(E22,'Feriados y Comunas'!$C$1:$D$36,2,FALSE),"") -> LLANQUIHUE | G22: 46021 | H22: 3368057 | I22: Ejecución | J22: 2027 | K22: Recursos Hidricos | L22: Ok - Oficio 1217 20-05-26 | N22: Se encuentra dentro de la ERD en: - Lineamiento: Bienestar Socio territorial. - Ítem: Servicio Básicos. - Obj.: Ampliar la Red de alcantarillado para dar soluciones sustentables. Reducir el numero de vivienda desconectadas de un sistema de suministro de agua en las áreas rurales de la región. - Actividad: Plan de construcción y mejoramiento de infraestructura agua potable y alcantarillado urbano y rural. | O22: Se enlaza con el Programa Regional del Gobernador en el - Pilar: 3. Inclusión Social y Mejoramiento de la Calidad de Vida - Letra: c)Programas de Apoyo Social: Desarrollar iniciativas para apoyar a los sectores más vulnerables de nuestra comunidad. | P22: 265 | Q22: 280 | T22: Municipalidad Puerto Montt | U22: Municipalidad Puerto Montt | V22: 2755 | W22: 46021 | AA22: 46021 | AB22: =WORKDAY(AA22,15,'Feriados y Comunas'!A$2:A$25) -> 46042 | AH22: 291 795 | AI22: 06-02-2026 14-04-2026 | AJ22: 06-02-2026 10-04-2026 | AK22: OBSERVADO | AL22: 247 423 | AM22: 11-03-2026 14-05-2026 | AO22: 11-03-2026 14-05-2026 | AQ22: 291 795 | AR22: 06-02-2026 14-04-2026 | AS22: 1217 | AT22: 46162 | AU22: RECOMENDADO | AW22: 33
A23: =1+A22 -> 22 | B23: 30171875 | C23: 0 | D23: Reposición PSR Coligual | E23: Purranque | F23: =+IFERROR(VLOOKUP(E23,'Feriados y Comunas'!$C$1:$D$36,2,FALSE),"") -> OSORNO | G23: 46113 | H23: 1153997 | I23: Ejecución | J23: 2027 | K23: Salud | L23: Ok - Oficio 1250 25-05-26 | N23: Se encuentra dentro de la ERD en el - Lineamiento: Bienestar Socio Territorial. - Ítem: Salud. - Objetivo: Aumentar Cobertura de atención primaria en salud en la comunas de la región. - Actividad: Convenio de Programación. | O23: Se enlaza con el programa del Gobernador Regional en el - Pilar: 3. Inclusión Social y Mejoramiento de la Calidad de Vida. - Letra: e) Acceso a Servicios de Salud: Ampliar y mejorar la red de servicios de salud, especialmente en zonas rurales, garantizando atención médica de calidad para todos. | P23: 307 | Q23: 285 | R23: =SUM(P23:Q23) -> 592 | T23: Municipalidad Purranque | U23: Municipalidad Purranque | V23: 208 | W23: 46112 | AA23: 46113 | AB23: =WORKDAY(AA23,15,'Feriados y Comunas'!A$2:A$25) -> 46134 | AH23: 794 | AI23: 46126 | AJ23: 46122 | AK23: OBSERVADO | AL23: 255 | AM23: 46141 | AO23: 46141 | AQ23: 794 | AR23: 46126 | AS23: 255 | AT23: 46167 | AU23: RECOMENDADO | AV23: OK | AW23: 7
A24: =1+A23 -> 23 | B24: 40072839 | C24: 0 | D24: Habilitación SSEE Monte Verde | E24: San Juan de la Costa | F24: =+IFERROR(VLOOKUP(E24,'Feriados y Comunas'!$C$1:$D$36,2,FALSE),"") -> OSORNO | G24: 46136 | H24: 734710 | I24: Ejecución | J24: 2027 | K24: Energía | L24: Ok - Oficio 1269 26-05-26 | N24: Se encuentra dentro de los lineamientos de la ERD en Bienestar Socio Territorial. Ítem Medioambiente y Eficiencia Energética, (Obj. Reducir la Pobreza Energética en las viviendas de la Región). | O24: Se enlaza con el Programa Regional del Gobernador - Pilar: 3. Inclusión Social y Mejoramiento de la Calidad de Vida. - Letra: c) Programas de Apoyo Social: Desarrollar iniciativas para apoyar a los sectores más vulnerables de nuestra comunidad. | P24: 45 | Q24: 52 | R24: =SUM(P24:Q24) -> 97 | T24: Municipalidad San Juan de La Costa | U24: Municipalidad San Juan de La Costa | V24: 581 | W24: 46136 | AA24: 46136 | AB24: =WORKDAY(AA24,15,'Feriados y Comunas'!A$2:A$25) -> 46157 | AS24: 1269 | AT24: 46168 | AU24: RECOMENDADO | AV24: OK | AW24: 15
A25: =1+A24 -> 24 | B25: 40071483 | C25: 0 | D25: Construcción SSR ST Quiao | E25: Chonchi | F25: =+IFERROR(VLOOKUP(E25,'Feriados y Comunas'!$C$1:$D$36,2,FALSE),"") -> CHILOÉ | G25: 46135 | H25: 90116 | I25: Diseño | J25: 2027 | K25: Recursos Hidricos | L25: Ok - Oficio 1270 26-05-26 | N25: Se encuentra dentro de la ERD en: Lineamiento: Bienestar Socio territorial. Ítem: Servicio Básicos. Obj.: Ampliar la Red de alcantarillado para dar soluciones sustentables. Reducir el numero de vivienda desconectadas de un sistema de suministro de agua en las áreas rurales de la región. Actividad: Plan de construcción y mejoramiento de infraestructura agua potable y alcantarillado urbano y rural. Se vincula con la Política de Sostenibilidad Hídrica: - Lineamiento: Seguridad Hídrica Para las Personas. - Línea: Fortalecimiento de la inversión en infraestructura para los SSR. - Iniciativa: Aumento de la Inversión en acceso al agua potable y saneamiento. | O25: Se vincula con la Política de Sostenibilidad Hídrica: - Lineamiento: Seguridad Hídrica Para las Personas. - Línea: Fortalecimiento de la inversión en infraestructura para los SSR. - Iniciativa: Aumento de la Inversión en acceso al agua potable y saneamiento. | P25: 120 | Q25: 123 | R25: =SUM(P25:Q25) -> 243 | T25: Municipalidad Chonchi | U25: Municipalidad Chonchi | V25: 321 | W25: 46135 | AA25: 46135 | AB25: =WORKDAY(AA25,15,'Feriados y Comunas'!A$2:A$25) -> 46156 | AS25: 1270 | AT25: 46168 | AU25: RECOMENDADO | AV25: OK | AW25: 13
A26: =1+A25 -> 25 | B26: 40071267 | C26: 0 | D26: Reposición Cancha Municipal Bahia Mansa | E26: San Juan de la Costa | F26: =+IFERROR(VLOOKUP(E26,'Feriados y Comunas'!$C$1:$D$36,2,FALSE),"") -> OSORNO | G26: 46112 | H26: 131100 | I26: Diseño | J26: 2027 | K26: Deporte | L26: Ok - Oficio 1330 01-05-26 | N26: La iniciativa se orienta dentro de la ERD en el: - Lineamiento: Bienestar Socio Territorial. - Ítem: Espacios y Equipamiento Público - Objetivo: Aumentar el Nro. De espacios polideportivos en la región con criterios de genero e inclusividad. - Actividad: No hay. | O26: Se enlaza con el Programa Regional del Gobernador: - Pilar: 3. Inclusión Social y Mejoramiento de la Calidad de Vida. - Letra: c) Programas de Apoyo Social: Desarrollar iniciativas para apoyar a los sectores más vulnerables de nuestra comunidad. | P26: 1533 | Q26: 1521 | R26: =SUM(P26:Q26) -> 3054 | T26: Municipalidad San Juan de La Costa | U26: Municipalidad San Juan de La Costa | V26: 440 | W26: 46112 | AA26: 46136 | AB26: =WORKDAY(AA26,15,'Feriados y Comunas'!A$2:A$25) -> 46157 | AS26: 1330 | AT26: 46174 | AU26: RECOMENDADO | AV26: OK | AW26: 15
A27: =1+A26 -> 26 | B27: 40026493 | C27: 0 | D27: Construcción Cuartel 2° Cía. De Bomberos de Dalcahue | E27: Dalcahue | F27: =+IFERROR(VLOOKUP(E27,'Feriados y Comunas'!$C$1:$D$36,2,FALSE),"") -> CHILOÉ | G27: 46169 | H27: 70559 | I27: Diseño | J27: 2027 | K27: Seguridad | L27: Ok - Oficio 1469 16-06-26 | N27: Se encuentra dentro de los lineamientos de la ERD - Lineamiento: Bienes Socio Territorial. Ítem: Espacios y Equipamiento Publico. Obj.: Construir equipamiento publico y espacios de carácter cívico en la Región. | O27: Se enlaza con el Programa Regional del Gobernador en el - Pilar: 3. Inclusión Social y Mejoramiento de la Calidad de Vida. - Letra: c) Programas de Apoyo Social: Desarrollar iniciativas para apoyar a los sectores más vulnerables de nuestra comunidad. | P27: 5986 | Q27: 5986 | R27: =SUM(P27:Q27) -> 11972 | T27: Municipalidad Dalcahue | U27: Municipalidad Dalcahue | V27: 588 | W27: 46169 | AA27: 46169 | AB27: =WORKDAY(AA27,15,'Feriados y Comunas'!A$2:A$25) -> 46190 | AS27: 1469 | AT27: 46189 | AU27: RECOMENDADO | AV27: OK | AW27: 12
A28: =1+A27 -> 27 | B28: 30080921 | C28: 0 | D28: Reposición PSR Piedra Azul | E28: Puerto Montt | F28: =+IFERROR(VLOOKUP(E28,'Feriados y Comunas'!$C$1:$D$36,2,FALSE),"") -> LLANQUIHUE | G28: 46079 | H28: 1402405 | I28: Ejecución | J28: 2026 | K28: Salud | L28: Ok - Oficio 1471 16-06-26 | N28: Se encuentra dentro de la ERD en el - Lineamiento: Bienestar Socio Territorial. - Ítem: Salud. - Objetivo: Aumentar Cobertura de atención primaria en salud en la comunas de la región. - Actividad: Convenio de Programación. | O28: Se enlaza con el programa del Gobernador Regional en el - Pilar: 3. Inclusión Social y Mejoramiento de la Calidad de Vida. - Letra: e) Acceso a Servicios de Salud: Ampliar y mejorar la red de servicios de salud, especialmente en zonas rurales, garantizando atención médica de calidad para todos. | P28: 162 | Q28: 203 | R28: =SUM(P28:Q28) -> 365 | T28: Municipalidad Puerto Montt | U28: Municipalidad Puerto Montt | V28: 235 | W28: 46079 | AA28: 46079 | AB28: =WORKDAY(AA28,15,'Feriados y Comunas'!A$2:A$25) -> 46100 | AH28: 517 | AI28: 46097 | AJ28: 46094 | AK28: OBSERVADO | AL28: 453 | AM28: 46168 | AO28: 46169 | AQ28: 517 | AR28: 46097 | AS28: 1471 | AT28: 46189 | AU28: RECOMENDADO | AV28: OK | AW28: 11
A29: =1+A28 -> 28 | B29: 40005337 | C29: 0 | D29: Reposición PSR Trapen | E29: Puerto Montt | F29: =+IFERROR(VLOOKUP(E29,'Feriados y Comunas'!$C$1:$D$36,2,FALSE),"") -> LLANQUIHUE | G29: 46079 | H29: 1404623 | I29: Ejecución | J29: 2026 | K29: Salud | L29: Ok - Oficio 1467 16-06-26 | N29: Se encuentra dentro de la ERD en el - Lineamiento: Bienestar Socio Territorial. - Ítem: Salud. - Objetivo: Aumentar Cobertura de atención primaria en salud en la comunas de la región. - Actividad: Convenio de Programación. | O29: Se enlaza con el programa del Gobernador Regional en el - Pilar: 3. Inclusión Social y Mejoramiento de la Calidad de Vida. - Letra: e) Acceso a Servicios de Salud: Ampliar y mejorar la red de servicios de salud, especialmente en zonas rurales, garantizando atención médica de calidad para todos. | P29: 659 | Q29: 714 | R29: =SUM(P29:Q29) -> 1373 | T29: Municipalidad Puerto Montt | U29: Municipalidad Puerto Montt | V29: 457 | W29: 46169 | AA29: 46170 | AB29: =WORKDAY(AA29,15,'Feriados y Comunas'!A$2:A$25) -> 46191 | AS29: 1467 | AT29: 46189 | AU29: RECOMENDADO | AV29: OK | AW29: 11
A30: =1+A29 -> 29 | B30: 40052180 | C30: 0 | D30: Construcción SSR Tehuaco | E30: Dalcahue | F30: =+IFERROR(VLOOKUP(E30,'Feriados y Comunas'!$C$1:$D$36,2,FALSE),"") -> CHILOÉ | G30: 46141 | H30: 1853604 | I30: Ejecución | J30: 2027 | K30: Recursos Hidricos | L30: Ok - Oficio 1628 26-06-26 | N30: Se encuentra dentro de la ERD en: Lineamiento: Bienestar Socio territorial. Ítem: Servicio Básicos. Obj.: Ampliar la Red de alcantarillado para dar soluciones sustentables. Reducir el numero de vivienda desconectadas de un sistema de suministro de agua en las áreas rurales de la región. Actividad: Plan de construcción y mejoramiento de infraestructura agua potable y alcantarillado urbano y rural. Se vincula con la Política de Sostenibilidad Hídrica: - Lineamiento: Seguridad Hídrica Para las Personas. - Línea: Fortalecimiento de la inversión en infraestructura para los SSR. - Iniciativa: Aumento de la Inversión en acceso al agua potable y saneamiento. | O30: Se vincula con la Política de Sostenibilidad Hídrica: - Lineamiento: Seguridad Hídrica Para las Personas. - Línea: Fortalecimiento de la inversión en infraestructura para los SSR. - Iniciativa: Aumento de la Inversión en acceso al agua potable y saneamiento. | P30: 108 | Q30: 118 | R30: =SUM(P30:Q30) -> 226 | T30: Municipalidad Dalcahue | U30: Municipalidad Dalcahue | V30: 144 | W30: 46140 | AA30: 46141 | AB30: =WORKDAY(AA30,15,'Feriados y Comunas'!A$2:A$25) -> 46162 | AH30: 1266 | AI30: 46168 | AJ30: 46157 | AK30: OBSERVADO | AL30: 177 | AM30: 46171 | AO30: 46171 | AS30: 1470 1628 | AT30: 16-06-2026 26-06-2026 | AU30: RECOMENDADO | AV30: OK | AW30: 10
A31: =1+A30 -> 30 | B31: 40078953 | C31: 0 | D31: Mejoramiento 2 Tramos Calle Inmaculada, ST Barrio Industrial | E31: Puerto Montt | F31: =+IFERROR(VLOOKUP(E31,'Feriados y Comunas'!$C$1:$D$36,2,FALSE),"") -> LLANQUIHUE | G31: 46154 | H31: 1568046 | I31: Ejecución | J31: 2027 | K31: Transporte | L31: Ok - Oficio 1626 26-06-26 | N31: Se encuentra dentro de los de la ERD en - lineamientos: Conectividad y Movilidad Regional Sustentable. - Ítem Conectividad insular y de lugares aislados. - Obj.: Disminuir el déficit de infraestructura de conectividad para territorios insulares y aislados de la región. | O31: Se enlaza con el Programa Regional del Gobernador en el - Pilar: 2. Desarrollo Económico Sostenible: una Alianza Público-Privada. - Letra: c) Inversiones en Infraestructura: Mejorar la conectividad y la infraestructura regional para atraer inversiones y generar empleo. | P31: 170 | Q31: 187 | R31: =SUM(P31:Q31) -> 357 | T31: Municipalidad Puerto Montt | U31: Municipalidad Puerto Montt | V31: 410 | W31: 46153 | AA31: 46154 | AB31: =WORKDAY(AA31,15,'Feriados y Comunas'!A$2:A$25) -> 46175 | AH31: 1264 | AI31: 46168 | AJ31: 46157 | AK31: OBSERVADO | AS31: 1626 | AT31: 46199 | AU31: RECOMENDADO | AV31: OK | AW31: 3
A32: =1+A31 -> 31 | B32: 40071481 | C32: 0 | D32: Construcción Servicio APR Sector Cahuala - Coipo | E32: Chonchi | F32: =+IFERROR(VLOOKUP(E32,'Feriados y Comunas'!$C$1:$D$36,2,FALSE),"") -> CHILOÉ | G32: 46129 | H32: 3083768 | I32: Ejecución | J32: 2027 | K32: Recursos Hidricos | L32: Ok - Oficio 1627 26-06-26 | N32: Se encuentra dentro de la ERD en: Lineamiento: Bienestar Socio territorial. Ítem: Servicio Básicos. Obj.: Ampliar la Red de alcantarillado para dar soluciones sustentables. Reducir el numero de vivienda desconectadas de un sistema de suministro de agua en las áreas rurales de la región. Actividad: Plan de construcción y mejoramiento de infraestructura agua potable y alcantarillado urbano y rural. Se vincula con la Política de Sostenibilidad Hídrica: - Lineamiento: Seguridad Hídrica Para las Personas. - Línea: Fortalecimiento de la inversión en infraestructura para los SSR. - Iniciativa: Aumento de la Inversión en acceso al agua potable y saneamiento. | O32: Se vincula con la Política de Sostenibilidad Hídrica: - Lineamiento: Seguridad Hídrica Para las Personas. - Línea: Fortalecimiento de la inversión en infraestructura para los SSR. - Iniciativa: Aumento de la Inversión en acceso al agua potable y saneamiento. | P32: 228 | Q32: 226 | R32: =SUM(P32:Q32) -> 454 | T32: Municipalidad Chonchi | U32: Municipalidad Chonchi | V32: 299 | W32: 46129 | AA32: 46129 | AB32: =WORKDAY(AA32,15,'Feriados y Comunas'!A$2:A$25) -> 46150 | AH32: 1263 | AI32: 46168 | AJ32: 46157 | AK32: OBSERVADO | AS32: 1627 | AT32: 46199 | AU32: RECOMENDADO | AW32: 20
A33: =1+A32 -> 32 | B33: 40080095 | C33: 0 | D33: Habilitación SS EE ST Costa Norte | E33: San Juan de la Costa | F33: =+IFERROR(VLOOKUP(E33,'Feriados y Comunas'!$C$1:$D$36,2,FALSE),"") -> OSORNO | G33: 46216 | H33: 1058627 | I33: Ejecución | J33: 2027 | K33: Energía | L33: Ok - Oficio 1836 21-07-26 | N33: Se encuentra dentro de los lineamientos de la ERD en Bienestar Socio Territorial. Ítem Medioambiente y Eficiencia Energética, (Obj. Reducir la Pobreza Energética en las viviendas de la Región). | O33: Se enlaza con el Programa Regional del Gobernador - Pilar: 3. Inclusión Social y Mejoramiento de la Calidad de Vida. - Letra: c) Programas de Apoyo Social: Desarrollar iniciativas para apoyar a los sectores más vulnerables de nuestra comunidad. | P33: 100 | Q33: 100 | R33: =SUM(P33:Q33) -> 200 | T33: Municipalidad San Juan de La Costa | U33: Municipalidad San Juan de La Costa | V33: 1032 | W33: 46216 | AA33: 46216 | AB33: =WORKDAY(AA33,15,'Feriados y Comunas'!A$2:A$25) -> 46237 | AS33: 1836 | AT33: 46224 | AU33: RECOMENDADO | AV33: OK | AW33: 3
A34: =1+A33 -> 33 | B34: 40039318 | C34: 0 | D34: Habilitación SS EE ST Piedra Azul Alto | E34: Puerto Montt | F34: =+IFERROR(VLOOKUP(E34,'Feriados y Comunas'!$C$1:$D$36,2,FALSE),"") -> LLANQUIHUE | G34: 46210 | H34: 675071 | I34: Ejecución | J34: 2027 | K34: Energía | L34: Ok - Oficio 1837 21-07-26 | N34: Se encuentra dentro de los lineamientos de la ERD en Bienestar Socio Territorial. Ítem Medioambiente y Eficiencia Energética, (Obj. Reducir la Pobreza Energética en las viviendas de la Región). | O34: Se enlaza con el Programa Regional del Gobernador - Pilar: 3. Inclusión Social y Mejoramiento de la Calidad de Vida. - Letra: c) Programas de Apoyo Social: Desarrollar iniciativas para apoyar a los sectores más vulnerables de nuestra comunidad. | P34: 49 | Q34: 38 | R34: =SUM(P34:Q34) -> 87 | T34: Municipalidad Puerto Montt | U34: Municipalidad Puerto Montt | V34: 581 | W34: 46210 | AA34: 46210 | AB34: =WORKDAY(AA34,15,'Feriados y Comunas'!A$2:A$25) -> 46231 | AS34: 1837 | AT34: 46224 | AU34: RECOMENDADO | AV34: OK | AW34: 6
A35: =1+A34 -> 34 | B35: 40019279 | C35: 0 | D35: Construcción Sistema Fotovoltaico Habitacional INIO | E35: Quellón | F35: =+IFERROR(VLOOKUP(E35,'Feriados y Comunas'!$C$1:$D$36,2,FALSE),"") -> CHILOÉ | G35: 46136 | H35: 91500 | I35: Diseño | J35: 2027 | K35: Energía | L35: Ok - Oficio 1835 21-07-26 | N35: Se encuentra dentro de los lineamientos de la ERD en Bienestar Socio Territorial. Ítem Medioambiente y Eficiencia Energética, (Obj. Reducir la Pobreza Energética en las viviendas de la Región). | O35: Se enlaza con el Programa Regional del Gobernador - Pilar: 3. Inclusión Social y Mejoramiento de la Calidad de Vida. - Letra: c) Programas de Apoyo Social: Desarrollar iniciativas para apoyar a los sectores más vulnerables de nuestra comunidad. | P35: 37 | Q35: 19 | R35: =SUM(P35:Q35) -> 56 | T35: Municipalidad Quellón | U35: Municipalidad Quellón | V35: 338 | W35: 46136 | AA35: 46136 | AB35: =WORKDAY(AA35,15,'Feriados y Comunas'!A$2:A$25) -> 46157 | AH35: 1261 1641 | AI35: 26-05-2026 30-06-2026 | AJ35: 15-05-2026 26-06-2026 | AK35: OBSERVADO | AL35: 561 597 | AM35: 23-06-2026 09-07-2026 | AO35: 24-06-2026 29-07-2026 | AQ35: 1261 1641 | AR35: 26-05-2026 30-06-2026 | AS35: 1835 | AT35: 46224 | AU35: RECOMENDADO | AV35: OK | AW35: 15
A36: =1+A35 -> 35 | B36: 40069812 | C36: 0 | D36: Reposicion Casa de la Musica | E36: Frutillar | F36: =+IFERROR(VLOOKUP(E36,'Feriados y Comunas'!$C$1:$D$36,2,FALSE),"") -> LLANQUIHUE | G36: 46206 | H36: 1695748 | I36: Ejecución | J36: 2027 | K36: Cultura | L36: Ok - Oficio 1855 22-07-26 Ok - Oficio 2941 28-09-26 | N36: La iniciativa se orienta dentro de la ERD en el - Lineamiento: Cohesión e Identidad Socio Cultural. - Ítem: Arte y Cultura. - Objetivo: Construir y renovar infraestructura cultural de alto estándar para habilitar el acceso y desarrollo de las culturas y las artes locales y regional. - Actividad: No Hay. | O36: Se enlaza con el Programa Regional del Gobernador Regional. - Pilar: 5. Desarrollo Cultural y Turismo. - Letra: c) Centros Culturales: Crear y mantener centros culturales en las principales ciudades y localidades para promover la cultura local. | P36: 74 | Q36: 78 | R36: =SUM(P36:Q36) -> 152 | T36: Municipalidad Frutillar | U36: Municipalidad Frutillar | V36: 1007 | W36: 46205 | AA36: 46206 | AB36: =WORKDAY(AA36,15,'Feriados y Comunas'!A$2:A$25) -> 46227 | AS36: 1855 2941 | AT36: 22-07-2026 28-09-2026 | AU36: RECOMENDADO | AV36: OK | AW36: 9 8
A37: =1+A36 -> 36 | B37: 40063885 | C37: 0 | D37: Construcción Istema Integral SSR ST Rivera Norte | E37: Maullín | F37: =+IFERROR(VLOOKUP(E37,'Feriados y Comunas'!$C$1:$D$36,2,FALSE),"") -> LLANQUIHUE | G37: 46213 | H37: 324729 | I37: Prefactibilidad | J37: 2027 | K37: Recursos Hidricos | L37: Ok - Oficio 2050 31-07-26 | N37: Se encuentra dentro de la ERD en: Lineamiento: Bienestar Socio territorial. Ítem: Servicio Básicos. Obj.: Ampliar la Red de alcantarillado para dar soluciones sustentables. Reducir el numero de vivienda desconectadas de un sistema de suministro de agua en las áreas rurales de la región. Actividad: Plan de construcción y mejoramiento de infraestructura agua potable y alcantarillado urbano y rural. Se vincula con la Política de Sostenibilidad Hídrica: - Lineamiento: Seguridad Hídrica Para las Personas. - Línea: Fortalecimiento de la inversión en infraestructura para los SSR. - Iniciativa: Aumento de la Inversión en acceso al agua potable y saneamiento. | O37: Se vincula con la Política de Sostenibilidad Hídrica: - Lineamiento: Seguridad Hídrica Para las Personas. - Línea: Fortalecimiento de la inversión en infraestructura para los SSR. - Iniciativa: Aumento de la Inversión en acceso al agua potable y saneamiento. | P37: 787 | Q37: 762 | R37: =SUM(P37:Q37) -> 1549 | T37: Municipalidad Maullin | U37: Municipalidad Maullin | V37: 72 | W37: 46181 | AA37: 46213 | AB37: =WORKDAY(AA37,15,'Feriados y Comunas'!A$2:A$25) -> 46234 | AS37: 2050 | AT37: 46234 | AU37: RECOMENDADO | AV37: OK | AW37: 3
A38: =1+A37 -> 37 | B38: 40080197 | C38: 0 | D38: Habilitación SSEE Varios ST Costa | E38: San Pablo | F38: =+IFERROR(VLOOKUP(E38,'Feriados y Comunas'!$C$1:$D$36,2,FALSE),"") -> OSORNO | G38: 46160 | H38: 546610 | I38: Ejecución | J38: 2027 | K38: Energía | L38: Ok - Oficio 2617 01-09-26 | N38: Se encuentra dentro de los lineamientos de la ERD en Bienestar Socio Territorial. Ítem Medioambiente y Eficiencia Energética, (Obj. Reducir la Pobreza Energética en las viviendas de la Región). | O38: Se enlaza con el Programa Regional del Gobernador - Pilar: 3. Inclusión Social y Mejoramiento de la Calidad de Vida. - Letra: c) Programas de Apoyo Social: Desarrollar iniciativas para apoyar a los sectores más vulnerables de nuestra comunidad. | P38: 17 | Q38: 14 | R38: =SUM(P38:Q38) -> 31 | T38: Municipalidad San Pablo | U38: Municipalidad San Pablo | V38: 297 | W38: 46157 | AA38: 46160 | AB38: =WORKDAY(AA38,15,'Feriados y Comunas'!A$2:A$25) -> 46181 | AH38: 1464 1848 | AI38: 15-06-2026 22-07-2026 | AJ38: 12-06-2026 15-07-2026 | AK38: OBSERVADO | AL38: 365 522 | AM38: 17-06-2026 17-08-2026 | AO38: 26-06-2026 26-08-2026 | AQ38: 1464 | AR38: 46188 | AS38: 2617 | AT38: 46266 | AU38: RECOMENDADO | AW38: 19
A39: =1+A38 -> 38 | B39: 40077279 | C39: 0 | D39: Analisis de Implementacion para la Construcción de Terminal de Buses | E39: Castro | F39: =+IFERROR(VLOOKUP(E39,'Feriados y Comunas'!$C$1:$D$36,2,FALSE),"") -> CHILOÉ | G39: 46258 | H39: 352500 | I39: Ejecución | J39: 2027 | K39: Transporte | L39: Ok - Oficio 2618 01-09-26 | N39: Se encuentra dentro de los de la ERD en - lineamientos: Conectividad y Movilidad Regional Sustentable. - Ítem Conectividad insular y de lugares aislados. - Obj.: Disminuir el déficit de infraestructura de conectividad para territorios insulares y aislados de la región. | O39: Se enlaza con el Programa Regional del Gobernador en el - Pilar: 2. Desarrollo Económico Sostenible: una Alianza Público-Privada. - Letra: c) Inversiones en Infraestructura: Mejorar la conectividad y la infraestructura regional para atraer inversiones y generar empleo. | P39: 22832 | Q39: 24165 | R39: =SUM(P39:Q39) -> 46997 | T39: Municipalidad Castro | U39: Municipalidad Castro | V39: 1009 | W39: 46252 | AA39: 46258 | AB39: =WORKDAY(AA39,15,'Feriados y Comunas'!A$2:A$25) -> 46279 | AL39: 1116 1009 | AM39: 22-10-2025 18-09-2026 | AO39: 27-10-2025 24-08-2026 | AQ39: 2134 3029 | AR39: 25-08-2025 11-11-2025 | AS39: 2618 | AT39: 46266 | AU39: RECOMENDADO | AV39: OK | AW39: 4
A40: =1+A39 -> 39 | B40: 40043232 | C40: 0 | D40: Reposición Cuartel de Bomberos 2° Cía. | E40: Calbuco | F40: LLANQUIHUE | G40: 46240 | H40: 2031826 | I40: Ejecución | J40: 2027 | K40: Seguridad | L40: Ok - Oficio 3297 15-12-25 OK - Oficio 063 12-01-26 OK - Oficio 2619 01-09-26 | N40: Se encuentra dentro de los lineamientos de la ERD - Lineamiento: Bienes Socio Territorial. Ítem: Espacios y Equipamiento Publico. Obj.: Construir equipamiento publico y espacios de carácter cívico en la Región. | O40: Se enlaza con el Programa Regional del Gobernador en el - Pilar: 3. Inclusión Social y Mejoramiento de la Calidad de Vida. - Letra: c) Programas de Apoyo Social: Desarrollar iniciativas para apoyar a los sectores más vulnerables de nuestra comunidad. | P40: 875 | Q40: 910 | R40: 1785 | T40: Municipalidad Calbuco | U40: Municipalidad Calbuco | V40: 678 | W40: 46237 | Y40: 46240 | Z40: 46240 | AA40: 46240 | AB40: =WORKDAY(AA40,15,'Feriados y Comunas'!A$2:A$25) -> 46261 | AS40: 2619 | AT40: 46266 | AU40: RECOMENDADO | AV40: OK | AW40: 15
A41: =1+A40 -> 40 | B41: 40068279 | C41: 0 | D41: Reposición con Relocalizacion PSR Butalcura | E41: Dalcahue | F41: CHILOÉ | G41: 46289 | H41: 1632207 | I41: Ejecución | J41: 2027 | K41: Salud | L41: Ok - Oficio 22940 28-09-26 | N41: Se encuentra dentro de la ERD en el - Lineamiento: Bienestar Socio Territorial. - Ítem: Salud. - Objetivo: Aumentar Cobertura de atención primaria en salud en la comunas de la región. - Actividad: Convenio de Programación. | O41: Se enlaza con el programa del Gobernador Regional en el - Pilar: 3. Inclusión Social y Mejoramiento de la Calidad de Vida. - Letra: e) Acceso a Servicios de Salud: Ampliar y mejorar la red de servicios de salud, especialmente en zonas rurales, garantizando atención médica de calidad para todos. | P41: 704 | Q41: 655 | R41: =SUM(P41:Q41) -> 1359 | T41: SSChiloé | U41: SSChiloé | V41: 346 | W41: 46289 | AA41: 46289 | AB41: =WORKDAY(AA41,15,'Feriados y Comunas'!A$2:A$25) -> 46310 | AS41: 2940 | AT41: 46293 | AU41: RECOMENDADO | AV41: OK | AW41: 1
A42: =1+A41 -> 41 | B42: 40081122 | C42: 0 | D42: Construcción Polideportivo Sur | E42: Castro | F42: =+IFERROR(VLOOKUP(E42,'Feriados y Comunas'!$C$1:$D$36,2,FALSE),"") -> CHILOÉ | G42: 46211 | H42: 180000 | I42: Ejecución | J42: 2027 | K42: Deporte | L42: Ok - Oficio 2942 28-09-26 | N42: La iniciativa se orienta dentro de la ERD en el: - Lineamiento: Bienestar Socio Territorial. - Ítem: Espacios y Equipamiento Público - Objetivo: Aumentar el Nro. De espacios polideportivos en la región con criterios de genero e inclusividad. - Actividad: No hay. | O42: Se enlaza con el Programa Regional del Gobernador: - Pilar: 3. Inclusión Social y Mejoramiento de la Calidad de Vida. - Letra: c) Programas de Apoyo Social: Desarrollar iniciativas para apoyar a los sectores más vulnerables de nuestra comunidad. | P42: 9102 | Q42: 9100 | R42: =SUM(P42:Q42) -> 18202 | T42: Municipalidad Castro | U42: Municipalidad Castro | V42: 780 | W42: 46196 | AA42: 46211 | AB42: =WORKDAY(AA42,15,'Feriados y Comunas'!A$2:A$25) -> 46232 | AH42: 1844 2641 | AI42: 22-07-2026 03-09-2026 | AJ42: 15-07-2026 28-08-2026 | AK42: OBSERVADO | AL42: 946 1110 | AM42: 06-08-2026 08-09-2026 | AO42: 12-08-2026 09-09-2026 | AQ42: 1844 2641 | AR42: 22-07-2026 03-09-2026 | AS42: 2942 | AT42: 46293 | AU42: RECOMENDADO | AV42: OK | AW42: 5
A43: =1+A42 -> 42 | B43: 40037891 | C43: 0 | D43: Reposición Estadio Municipal de Contao | E43: Hualaihué | F43: =+IFERROR(VLOOKUP(E43,'Feriados y Comunas'!$C$1:$D$36,2,FALSE),"") -> PALENA | G43: 46128 | H43: 2294874 | I43: Ejecución | J43: 2026 | K43: Deporte | L43: Ok - Oficio 2943 28-09-26 | N43: La iniciativa se orienta dentro de la ERD en el: - Lineamiento: Bienestar Socio Territorial. - Ítem: Espacios y Equipamiento Público - Objetivo: Aumentar el Nro. De espacios polideportivos en la región con criterios de genero e inclusividad. - Actividad: No hay. | O43: Se enlaza con el Programa Regional del Gobernador: - Pilar: 3. Inclusión Social y Mejoramiento de la Calidad de Vida. - Letra: c) Programas de Apoyo Social: Desarrollar iniciativas para apoyar a los sectores más vulnerables de nuestra comunidad. | P43: 111 | Q43: 110 | R43: =SUBTOTAL(9,P43:Q43) -> 221 | T43: Municipalidad Hualaihue | U43: Municipalidad Hualaihue | V43: 337 | W43: 46128 | AA43: 46128 | AB43: =WORKDAY(AA43,15,'Feriados y Comunas'!A$2:A$25) -> 46149 | AH43: 1260 2644 | AI43: 26-05-2026 03-09-2026 | AJ43: 15-05-2026 28-08-2026 | AK43: OBSERVADO | AL43: 697 836 | AM43: 03-08-2026 21-09-2026 | AO43: 04-08-2026 21-09-2026 | AQ43: 1260 2644 | AR43: 26-05-2026 03-09-2026 | AS43: 2943 | AT43: 46293 | AU43: RECOMENDADO | AW43: 22
A44: =1+A43 -> 43 | B44: 30125824 | C44: 0 | D44: Ampliación y Remodelación Integral Consistorial | E44: Los Muermos | F44: =+IFERROR(VLOOKUP(E44,'Feriados y Comunas'!$C$1:$D$36,2,FALSE),"") -> LLANQUIHUE | G44: 45799 | H44: 7981161 | I44: Ejecución | J44: 2027 | K44: MultiSectorial | L44: Ok - Oficio 2944 28-09-26 | N44: Se encuentra dentro de la ERD en: - Lineamiento: Bienestar Socio Territorial. - Ítem: Espacios y Equipamiento Publico. - Obj.: Construir equipamientos públicos y espacios de carácter cívico en la región. - Actividad: Habilitación edificios públicos sin accesibilidad universal. | O44: Se enlaza con el Programa Regional del Gobernador - Pilar: 6. Gobernanza y Participación Ciudadana. - Letra: c) Modernización Administrativa: Digitalizar los trámites y servicios administrativos para hacerlos más eficientes y accesibles. | P44: 2814 | Q44: 2893 | R44: =SUM(P44:Q44) -> 5707 | T44: Municipalidad Los Muermos | U44: Municipalidad Los Muermos | V44: 508 | W44: 45792 | Y44: 45799 | Z44: 45799 | AA44: 45799 | AB44: =WORKDAY(AA44,15,'Feriados y Comunas'!A$2:A$25) -> 45820 | AH44: 1223 1512 2124 525 2643 | AI44: 09-06-2025 02-07-2025 25-08-2025 16-03-2026 03-09-2026 | AJ44: 06-06-2025 27-06-2025 22-08-2025 13-03-2026 28-08-2026 | AK44: OBSERVADO | AL44: 508 599 704 277 822 945 | AM44: 15-05-2025 16-06-2025 24-06-2025 17-02-2026 14-08-2026 21-09-2026 | AO44: 22-05-2025 19-06-2025 31-07-2025 26-02-2026 17-08-2026 21-09-2026 | AQ44: 1223 1512 2124 525 | AR44: 09-06-2025 02-07-2025 25-08-2025 16-03-2026 | AS44: 2944 | AT44: 46293 | AU44: RECOMENDADO | AV44: OK | AW44: 11
A45: =1+A44 -> 44 | B45: 40004598 | C45: 0 | D45: Reposicion Centro Cultural | E45: Los Muermos | F45: =+IFERROR(VLOOKUP(E45,'Feriados y Comunas'!$C$1:$D$36,2,FALSE),"") -> LLANQUIHUE | G45: 46211 | H45: 2563661 | I45: Ejecución | J45: 2027 | K45: Cultura | L45: Ok - Oficio 2945 28-09-26 | N45: La iniciativa se orienta dentro de la ERD en el - Lineamiento: Cohesión e Identidad Socio Cultural. - Ítem: Arte y Cultura. - Objetivo: Construir y renovar infraestructura cultural de alto estándar para habilitar el acceso y desarrollo de las culturas y las artes locales y regional. - Actividad: No Hay. | O45: Se enlaza con el Programa Regional del Gobernador Regional. - Pilar: 5. Desarrollo Cultural y Turismo. - Letra: c) Centros Culturales: Crear y mantener centros culturales en las principales ciudades y localidades para promover la cultura local. | P45: 8681 | Q45: 8387 | R45: =SUM(P45:Q45) -> 17068 | T45: Municipalidad Los Muermos | U45: Municipalidad Los Muermos | V45: 457 | W45: 46211 | AA45: 46211 | AB45: =WORKDAY(AA45,15,'Feriados y Comunas'!A$2:A$25) -> 46232 | AH45: 1847 2640 | AI45: 22-07-2026 03-09-2026 | AJ45: 15-07-2026 28-08-2026 | AK45: OBSERVADO | AL45: 793 946 | AM45: 06-08-2026 21-09-2026 | AO45: 07-08-2026 21-09-2026 | AQ45: 1847 2640 | AR45: 22-07-2026 03-09-2026 | AS45: 2945 | AT45: 46293 | AU45: RECOMENDADO | AV45: OK | AW45: 5
A46: =1+A45 -> 45 | B46: 40080415 | C46: 0 | D46: Habilitación SS EE ST Costa y Llano | E46: San Pablo | F46: =+IFERROR(VLOOKUP(E46,'Feriados y Comunas'!$C$1:$D$36,2,FALSE),"") -> OSORNO | G46: 46188 | H46: 1133751 | I46: Ejecución | J46: 2026 | K46: Energía | L46: Ok - Oficio 2946 28-09-26 | N46: Se encuentra dentro de los lineamientos de la ERD en Bienestar Socio Territorial. Ítem Medioambiente y Eficiencia Energética, (Obj. Reducir la Pobreza Energética en las viviendas de la Región). | O46: Se enlaza con el Programa Regional del Gobernador - Pilar: 3. Inclusión Social y Mejoramiento de la Calidad de Vida. - Letra: c) Programas de Apoyo Social: Desarrollar iniciativas para apoyar a los sectores más vulnerables de nuestra comunidad. | P46: 31 | Q46: 37 | R46: =SUM(P46:Q46) -> 68 | T46: Gobierno Regional de Los Lagos | U46: Municipalidad San Pablo | V46: 311 | W46: 46162 | AA46: 46188 | AB46: =WORKDAY(AA46,15,'Feriados y Comunas'!A$2:A$25) -> 46209 | AH46: 1611 | AI46: 46199 | AJ46: 46199 | AK46: OBSERVADO | AL46: 590 | AM46: 46282 | AO46: 46283 | AQ46: 1611 | AR46: 46199 | AS46: 2946 | AT46: 46293 | AU46: OBSERVADO | AV46: OK | AW46: 9
A47: =1+A46 -> 46 | B47: 40062963 | C47: 0 | D47: Construcción Batería Sanitaria Reserva Nacional Futaleufú | E47: Futaleufú | F47: =+IFERROR(VLOOKUP(E47,'Feriados y Comunas'!$C$1:$D$36,2,FALSE),"") -> PALENA | G47: 45412 | H47: 178293 | I47: Ejecución | J47: 2025 | K47: Recursos Naturales | L47: Obs. Comité 10-05-24. 1. Adjuntar EETT Firmadas por Unidad Técnica. (Se sugiere UT la DA-MOP). 2. Anexar Participación Ciudadana. 3. Incorporar Permiso Edificación, si corresponde. 4. Adjuntar Mecánica. 5. Anexar Memoria. 6. Incorporar Proyecto Ingeniería. 7. Adjuntar Revisores Independientes, si corresponde. 8. Anexar Cronograma. 9. Incorporar Modelo de Gestión. 10. Adjuntar Dominio Vigente o Destinación. 11. Anexar Factibilidades. 12. Incorporar Costos Operacionales. 13. Adjuntar Documentación al BIP. | N47: Se encuentra dentro de los lineamientos de la ERD en Ordenamiento Territorial Sustentable y Resiliente, Ítem Protección del Patrimonio Natural (Obj. Implementar programas de protección y conservación de áreas protegidas en la región en calidad de áreas de valor natural, asegurando sus resguardos, funcionamientos y mantenciones). | O47: Se enlaza con el programa del Gobernador Regional en el lineamiento «Hagamos una Región de Acceso Universal» Acción “Facilitar el acceso a servicios, tanto en lo estructural como en la información”. | P47: 2448 | Q47: 2400 | R47: =SUM(P47:Q47) -> 4848 | T47: Conaf | U47: Conaf | V47: 192 | W47: 45412 | X47: 109624/2024 | Y47: 45412 | Z47: 45412 | AA47: 45412 | AB47: =WORKDAY(AA47,15,'Feriados y Comunas'!A$2:A$25) -> 45435 | AH47: 957 | AI47: 45435 | AJ47: 45435 | AK47: OBSERVADO | AQ47: 957 | AR47: 45435 | AU47: OBSERVADO | AV47: OK | AW47: 7
A48: =1+A47 -> 47 | B48: 40006863 | C48: 0 | D48: Reposición Escuela Juan Soler Manfredini | E48: Cochamó | F48: =+IFERROR(VLOOKUP(E48,'Feriados y Comunas'!$C$1:$D$36,2,FALSE),"") -> LLANQUIHUE | G48: 45460 | H48: 16201380 | I48: Ejecución | J48: 2025 | K48: Educación | L48: Obs. Comité 05-07-24 1. Crear Ficha 2025. 2. Corregir ficha y perfil. 3. Actualizar Factibilidad Energía y APR (2018 y 2022). 4. Actualizar Participación Ciudadana. 5. Incorporar Resolución de Calificación Ambiental (RCA). 6. Actualizar Factibilidades. 7. Finalizar Etapa de diseño. 8. Adjuntar documentación al BIP. | N48: Se encuentra dentro de los lineamientos de la ERD en lineamiento Bienestar Socio Territorial, Ítem Educación, (Obj. Aumentar la cobertura territorial a los establecimientos de educación publica en los territorios rurales de la región). | O48: Se enlaza con el Programa Regional del Gobernador en el lineamiento “Priorización de Inversiones Sectoriales y del FNDR para Nuevos Desafíos”, Acción “Proyectos que aporten a la equidad territorial”. | P48: 131 | Q48: 121 | R48: =SUM(P48:Q48) -> 252 | T48: Municipalidad Fresia | U48: Municipalidad Fresia | V48: 457 | W48: 45460 | X48: 110469/2024 | Y48: 45460 | Z48: 45461 | AA48: 45462 | AB48: =WORKDAY(AA48,15,'Feriados y Comunas'!A$2:A$25) -> 45484 | AH48: 1494 | AI48: 45481 | AJ48: 45481 | AK48: OBSERVADO | AQ48: 1494 | AR48: 45481 | AU48: OBSERVADO | AV48: OK | AW48: 11
A49: =1+A48 -> 48 | B49: 40033056 | C49: 0 | D49: Construcción Planta de Compostaje | E49: Ancud | F49: =+IFERROR(VLOOKUP(E49,'Feriados y Comunas'!$C$1:$D$36,2,FALSE),"") -> CHILOÉ | G49: 45490 | H49: 2036401 | I49: Ejecución | J49: 2025 | K49: Recursos Naturales | L49: Obs. Comité 26-07-24. 1. Incorporar EETT Firmadas por UT. 2. Actualizar Factibilidad Eléctrica. 3. Actualizar Permiso edificación. 4. Incorporar Desglose presupuestario Trincheras Firmadas. 5. Adjuntar en la Carta Gantt la Partida Ecotrincheras. 6. Acceso Falta detalle constructivo proyectado desde ruta. (Ppto. Y EETT), además del pronunciamiento de Vialidad o DOM. 7. Proyecto Eléctrico incorporar sistema para ecotrincheras y sistema para agua potable. 8. Por lo anterior se deben verificar los kw del sistema versus la factibilidad. 9. Proyecto Agua Potable, desglose partidas, EETT Incompletas (partidas como estanque sistema de cloración, bomba, tuberías de conexión a red APR.) 10. Adjuntar documentación al BIP. | N49: La iniciativa se orienta dentro de la ERD en el, Lineamiento: Bienestar Socio Territorial. Ítem: Medioambiente y Eficiencia Energética. Objetivo: Reducir el volumen de generación de residuos y potenciar su valorización en la región. Actividad: Estrategia Regional de RSD (No Hay) | O49: Se enlaza con el Programa Regional del Gobernador Ítem “Priorización de Inversiones Sectoriales y del FNDR para Nuevos Desafíos”, Acción “Proyectos que aporten a la equidad territorial”. | P49: 7141 | Q49: 7432 | R49: =SUM(P49:Q49) -> 14573 | T49: Municipalidad Ancud | U49: Municipalidad Ancud | V49: 1081 | W49: 45483 | X49: 110884/2024 | Y49: 45490 | Z49: 45490 | AA49: 45490 | AB49: =WORKDAY(AA49,15,'Feriados y Comunas'!A$2:A$25) -> 45511 | AH49: 1670 | AI49: 45503 | AJ49: 45503 | AK49: OBSERVADO | AQ49: 1670 | AR49: 45503 | AU49: OBSERVADO | AV49: OK | AW49: 7
A50: =1+A49 -> 49 | B50: 40066005 | C50: 0 | D50: Construcción Sanitarios Sector Río Blanco, PN Hornopiren. | E50: Hualaihué | F50: =+IFERROR(VLOOKUP(E50,'Feriados y Comunas'!$C$1:$D$36,2,FALSE),"") -> PALENA | G50: 45532 | H50: 166777 | I50: Ejecución | J50: 2025 | K50: Recursos Naturales | L50: Comité 04-10-24. 1. Adjuntar Permiso Edificación, si corresponde. 2. Anexar Mecánica de Suelos. 3. Incorporar Memoria de Cálculo. 4. Anexar Proyecto Ingeniería. 5. Adjuntar Revisores Independientes, si corresponde. 6. Incorporar Modelo de Gestión. 7. Adjuntar Factibilidades de Servicios Básicos. 8. Anexar Certificado de Costos Operacionales. 9. Se sugiere postular a <5000 UTM, esto implica cambiar descriptor en ficha IDI. 10. Incorporar la documentación al Banco Integrado de Proyecto (BIP). | N50: Se encuentra dentro de los lineamientos de la ERD en Ordenamiento Territorial Sustentable y Resiliente, Ítem Protección del Patrimonio Natural (Obj. Implementar programas de protección y conservación de áreas protegidas en la región en calidad de áreas de valor natural, asegurando sus resguardos, funcionamientos y mantenciones). | O50: Se enlaza con el programa del Gobernador Regional en el lineamiento «Hagamos una Región de Acceso Universal» Acción “Facilitar el acceso a servicios, tanto en lo estructural como en la información”. | P50: 5520 | Q50: 6500 | R50: =SUM(P50:Q50) -> 12020 | T50: Conaf | U50: Conaf | V50: 340 | W50: 45530 | Y50: 45532 | Z50: 45532 | AA50: 45534 | AB50: =WORKDAY(AA50,15,'Feriados y Comunas'!A$2:A$25) -> 45559 | AH50: 2404 | AI50: 45572 | AJ50: 45572 | AK50: OBSERVADO | AQ50: 2404 | AR50: 45572 | AU50: OBSERVADO | AW50: 21
A51: =1+A50 -> 50 | B51: 40053830 | C51: 0 | D51: Normalización y Ampliación Liceo de Hombres Manuel Montt | E51: Puerto Montt | F51: =+IFERROR(VLOOKUP(E51,'Feriados y Comunas'!$C$1:$D$36,2,FALSE),"") -> LLANQUIHUE | G51: 45586 | H51: 18007811 | I51: Ejecución | J51: 2025 | K51: Educación | L51: Obs. Comité 08-11-24. 1. Adjuntar TTR. Firmados por UT. 2. Anexar Ppto. OC. Firmado por UT. 3. Incorporar Ppto. Consultorías y AITO firmados por UT. 4. Adjuntar Ppto. De Equipos y Equipamiento Firmados por UT. 5. Anexar Permiso de edificación. 6. Actualizar EISTU. 7. Actualizar Factibilidades. 8. Incorporar Certificado de Hipotecas y Gravámenes. 9. Anexar Informe técnico situación actual con fotografías. 10. Se sugiere Explorar financiamiento compartido. 11. Adjuntar documentación al BIP. | N51: Se encuentra dentro de los lineamientos de la ERD en lineamiento Bienestar Socio Territorial, Ítem Educación, (Obj. Aumentar la cobertura territorial a los establecimientos de educación publica en los territorios rurales de la región). | O51: Se enlaza con el Programa Regional del Gobernador en el lineamiento “Priorización de Inversiones Sectoriales y del FNDR para Nuevos Desafíos”, Acción “Proyectos que aporten a la equidad territorial”. | P51: 966 | Q51: 0 | R51: =SUM(P51:Q51) -> 966 | T51: Municipalidad Puerto Montt | U51: Municipalidad Puerto Montt | V51: 1762 | W51: 45583 | X51: 112174/2024 | Y51: 45586 | Z51: 45587 | AA51: 45588 | AB51: =WORKDAY(AA51,15,'Feriados y Comunas'!A$2:A$25) -> 45611 | AH51: 2755 | AI51: 45604 | AJ51: 45604 | AK51: OBSERVADO | AQ51: 2755 | AR51: 45604 | AU51: OBSERVADO | AV51: OK | AW51: 12
A52: =1+A51 -> 51 | B52: 40064335 | C52: 0 | D52: Construcción Centro Cultural | E52: Puqueldón | F52: =+IFERROR(VLOOKUP(E52,'Feriados y Comunas'!$C$1:$D$36,2,FALSE),"") -> CHILOÉ | G52: 45631 | H52: 2031129 | I52: Ejecución | J52: 2025 | K52: Cultura | L52: Comité 13-12-24 1. Adjuntar Especificaciones Técnicas firmadas por la UT. 2. Anexar Presupuesto Equipamiento. 3. Incorporar Participación Ciudadana. 4. Adjuntar Permiso de edificación. 5. Anexar Mecánica de suelos. 6. Incorporar Revisores independientes. 7. Adjuntar Cronograma. 8. Anexar Plan de mitigación. 9. Incorporar IMIV. 10. Adjuntar Dominio Vigente. 11. Anexar Hipotecas y Gravámenes. 12. Incorporar Factibilidades de servicios básicos. 13. Adjuntar documentación al BIP. | N52: La iniciativa se orienta dentro de la ERD en el Lineamiento: Cohesión e Identidad Socio Cultural. Ítem: Arte y Cultura. Obj.: Construir y renovar infraestructura cultural de alto estándar para habilitar el acceso y desarrollo de las culturas y las artes locales y regional. | O52: Se enlaza con el Programa Regional del Gobernador Regional. - Pilar: 5. Desarrollo Cultural y Turismo. - Letra: c) Centros Culturales: Crear y mantener centros culturales en las principales ciudades y localidades para promover la cultura local. | P52: 955 | Q52: 781 | R52: =SUM(P52:Q52) -> 1736 | T52: Municipalidad Puqueldon | U52: Municipalidad Puqueldon | V52: 571 | W52: 45629 | X52: 112798/2024 | Y52: 45631 | Z52: 45631 | AA52: 45631 | AB52: =WORKDAY(AA52,15,'Feriados y Comunas'!A$2:A$25) -> 45653 | AH52: 2 | AI52: 45659 | AJ52: 45659 | AK52: OBSERVADO | AQ52: 2 | AR52: 45659 | AU52: OBSERVADO | AV52: OK | AW52: 6
A53: =1+A52 -> 52 | B53: 40057688 | C53: 0 | D53: Reposición Liceo Hornopiren | E53: Hualaihué | F53: =+IFERROR(VLOOKUP(E53,'Feriados y Comunas'!$C$1:$D$36,2,FALSE),"") -> PALENA | G53: 45707 | H53: 486517 | I53: Diseño | J53: 2025 | K53: Educación | L53: Obs. Comité 07-03-25.1. Se solicita cartas de compromiso financiero compartido en la etapa de ejecución. 2. Confirmar incorporación al Programa PDZE y su unidad ejecutora. 3. Ajuntar sensibilización en las proyecciones de los valores en ejecución. 4. Adjuntar Documentación al BIP. | N53: Se encuentra dentro de la ERD en, - Lineamiento: Bienestar Socio Territorial. - Ítem: Educación. - Objetivo: Mejorar el desempeño de los establecimientos educacionales públicos y subvencionados de la Región . - Actividad: No hay. | O53: Se enlaza con el Programa Regional del Gobernador en el lineamiento - Pilar: 3. Inclusión Social y Mejoramiento de la Calidad de Vida. - Letra: i) Infraestructura Educativa: Renovar y construir nuevas instalaciones educativas para garantizar ambientes de aprendizaje adecuados. | P53: 172 | Q53: 173 | R53: =SUM(P53:Q53) -> 345 | T53: Municipalidad Hualaihue | U53: Municipalidad Hualaihue | V53: 168 | W53: 45707 | X53: 113551/2025 | Y53: 45707 | Z53: 45709 | AA53: 45709 | AB53: =WORKDAY(AA53,15,'Feriados y Comunas'!A$2:A$25) -> 45730 | AH53: 456 | AI53: 45735 | AJ53: 00-03-2025 | AK53: OBSERVADO | AQ53: 456 | AR53: 45735 | AU53: OBSERVADO | AV53: OK | AW53: 10
A54: =1+A53 -> 53 | B54: 40044514 | C54: 0 | D54: Construcción Sistema APR ST Choroy Triguén | E54: San Juan de la Costa | F54: =+IFERROR(VLOOKUP(E54,'Feriados y Comunas'!$C$1:$D$36,2,FALSE),"") -> OSORNO | G54: 45744 | H54: 1083125 | I54: Ejecución | J54: 2026 | K54: Recursos Hidricos | L54: Obs. Comité 16-05-25. 1. Actualizar Presupuesto. 2. Actualizar certificaciones sectoriales. 3. Actualizar Comité APR. 4. Adjuntar Documentación al BIP. | N54: Lineamiento: Bienestar Socio territorial. - Ítem: Servicio Básicos. - Obj.: Ampliar la Red de alcantarillado para dar soluciones sustentables. Reducir el numero de vivienda desconectadas de un sistema de suministro de agua en las áreas rurales de la región. - Actividad: Plan de Construcción y mejoramiento de infraestructura agua potable y alcantarillado urbano y rural. | O54: Se vincula con la Política de Sostenibilidad Hídrica: - Lineamiento: Seguridad Hídrica Para las Personas. - Línea: Fortalecimiento de la inversión en infraestructura para los SSR. - Iniciativa: Aumento de la Inversión en acceso al agua potable y saneamiento. | P54: 197 | Q54: 192 | R54: =SUM(P54:Q54) -> 389 | T54: Municipalidad San Juan de La Costa | U54: Municipalidad San Juan de La Costa | V54: 239 | W54: 45744 | AA54: 45744 | AB54: =WORKDAY(AA54,15,'Feriados y Comunas'!A$2:A$25) -> 45768 | AH54: 987 | AI54: 45797 | AJ54: 45793 | AK54: OBSERVADO | AQ54: 987 | AR54: 45797 | AU54: OBSERVADO | AV54: OK | AW54: 31
A55: =1+A54 -> 54 | B55: 40007573 | C55: 0 | D55: Reposición Esc. Jose Abelardo Nuñez | E55: Maullín | F55: =+IFERROR(VLOOKUP(E55,'Feriados y Comunas'!$C$1:$D$36,2,FALSE),"") -> LLANQUIHUE | G55: 45726 | H55: 354959 | I55: Diseño | J55: 2026 | K55: Educación | L55: Comité 12-12-25. 1. Se mantiene la observación de adjuntar Financiamiento Compartido especificado porcentaje de participación. 2. Adjuntar Documentación al BIP. | N55: Se encuentra dentro de la ERD en: - Lineamiento: Bienestar Socio Territorial. - Ítem: Educación. - Obj.: Aumentar la cobertura territorial a los establecimientos de educación publica en los territorios rurales de la región. - Actividad: Programa de fortalecimiento de infraestructura pre escolar. | O55: Se enlaza con el Programa Regional del Gobernador en el - Pilar: 3. Inclusión Social y Mejoramiento de la Calidad de Vida. - Letra: i) Infraestructura Educativa: Renovar y construir nuevas instalaciones educativas para garantizar ambientes de aprendizaje adecuados. | P55: 124 | Q55: 140 | R55: =SUM(P55:Q55) -> 264 | T55: MOP - DA | U55: Municipalidad Maullin | V55: 215 | W55: 45726 | AA55: 45726 | AB55: =WORKDAY(AA55,15,'Feriados y Comunas'!A$2:A$25) -> 45747 | AH55: 988 2128 3279 | AI55: 20-05-2025 25-08-2025 15-12-2025 | AJ55: 16-05-2025 22-08-2025 12-12-2025 | AK55: OBSERVADO | AQ55: 988 2128 3279 | AR55: 20-05-2025 25-08-2025 15-12-2025 | AU55: OBSERVADO | AV55: OK | AW55: 47
A56: =1+A55 -> 55 | B56: 40045283 | C56: 0 | D56: Reposición Escuela Rural Julio Mohr Chifca | E56: San Pablo | F56: =+IFERROR(VLOOKUP(E56,'Feriados y Comunas'!$C$1:$D$36,2,FALSE),"") -> OSORNO | G56: 45840 | H56: 146333 | I56: Diseño | J56: 2026 | K56: Educación | L56: Comité 12-09-25. 1. Adjuntar Financiamiento Compartido. 2. Se sugiere explorar financiamiento FRC, Subdere. 3. Adjuntar Documentación al BIP. | N56: Se encuentra dentro de la ERD en, - Lineamiento: Bienestar Socio Territorial. - Ítem: Educación. - Objetivo: Mejorar el desempeño de los establecimientos educacionales públicos y subvencionados de la Región . - Actividad: No hay. | O56: Se enlaza con el Programa Regional del Gobernador en el lineamiento - Pilar: 3. Inclusión Social y Mejoramiento de la Calidad de Vida. -Letra: i) Infraestructura Educativa: Renovar y construir nuevas instalaciones educativas para garantizar ambientes de aprendizaje adecuados. | P56: 134 | Q56: 156 | R56: =SUM(P56:Q56) -> 290 | T56: Munciplidad San Pablo | U56: Munciplidad San Pablo | V56: 382 | W56: 45838 | Y56: 45840 | Z56: 45840 | AA56: 45840 | AB56: =WORKDAY(AA56,15,'Feriados y Comunas'!A$2:A$25) -> 45862 | AH56: 1581 2382 | AI56: 08-07-2025 16-09-2025 | AJ56: 04-07-2025 12-09-2025 | AK56: OBSERVADO | AL56: 405 | AM56: 45849 | AO56: 45894 | AQ56: 1581 2382 | AR56: 08-07-2025 16-09-2025 | AU56: OBSERVADO | AV56: OK | AW56: 2
A57: =1+A56 -> 56 | B57: 40054435 | C57: 0 | D57: Construcción Sistema Integral Servicios Sanitarios ST Ten Ten y Entre Ríos. | E57: Maullín | F57: =+IFERROR(VLOOKUP(E57,'Feriados y Comunas'!$C$1:$D$36,2,FALSE),"") -> LLANQUIHUE | G57: 45841 | H57: 669935 | I57: Diseño | J57: 2026 | K57: Recursos Hidricos | L57: Comité 04-07-25. 1. Adjuntar Ppto consultorías firmado UT. 2. Anexar Cronograma. 3. Incorporar Modelo gestión. 4. Adjuntar Plan Mitigación. 5. Anexar Visación DOH, o antecedentes del 52 Bis si correspondiera. 6. Incorporar Visación DOM. 7. Adjuntar Documentación al BIP. | N57: Se encuentra dentro de la ERD en: - Lineamiento: Bienestar Socio territorial. - Ítem: Servicio Básicos. - Obj.: Ampliar la Red de alcantarillado para dar soluciones sustentables. Reducir el numero de vivienda desconectadas de un sistema de suministro de agua en las áreas rurales de la región. - Actividad: Plan de construcción y mejoramiento de infraestructura agua potable y alcantarillado urbano y rural. Política Sostenibilidad Hídrica: - Lineamiento: Seguridad Hídrica para las Personas. - Obj.: Mejorar estándares de recolección y tratamiento de aguas servidas en sectores rurales. - Iniciativa: Proyecto de mejora de infraestructura Sanitaria en sectores desconectados. | O57: Se enlaza con el Programa Regional del Gobernador en el - Pilar: 3. Inclusión Social y Mejoramiento de la Calidad de Vida - Letra: c)Programas de Apoyo Social: Desarrollar iniciativas para apoyar a los sectores más vulnerables de nuestra comunidad. | P57: 667 | Q57: 680 | R57: =SUM(P57:Q57) -> 1347 | T57: Municipalidad Maullín | U57: Municipalidad Maullín | V57: 557 | W57: 45835 | Y57: 45841 | Z57: 45841 | AA57: 45841 | AB57: =WORKDAY(AA57,15,'Feriados y Comunas'!A$2:A$25) -> 45863 | AH57: 1586 | AI57: 45846 | AJ57: 45842 | AK57: OBSERVADO | AQ57: 1586 | AR57: 45846 | AU57: OBSERVADO | AV57: OK | AW57: 1
A58: =1+A57 -> 57 | B58: 40071800 | C58: 0 | D58: Reposición Edificio Municipal de Quinchao | E58: Quinchao | F58: =+IFERROR(VLOOKUP(E58,'Feriados y Comunas'!$C$1:$D$36,2,FALSE),"") -> CHILOÉ | G58: 45852 | H58: 334471 | I58: Diseño | J58: 2026 | K58: MultiSectorial | L58: Comité 25-07-25. 1. Adjuntar Cronograma. 2. Anexar Participación Ciudadana. 3. Incorporar Modelo de Gestión. 4. Adjuntar Plan de Mitigación. 5. Anexar Certificado DOM. 6. Incorporar Hipotecas y Gravámenes. 7. Adjuntar Informe Técnico Situación Actual. 8. Revisar costo m2 de diseño por sobre el promedio. 9. Se sugiere ver financiamiento programa Subdere. 10. Adjuntar Documentación al BIP. | N58: Se encuentra dentro de la ERD en: - Lineamiento: Bienestar Socio Territorial. - Ítem: Espacios y Equipamiento Publico. - Obj.: Construir equipamientos públicos y espacios de carácter cívico en la región. - Actividad: Habilitación edificios públicos sin accesibilidad universal. | O58: Se enlaza con el Programa Regional del Gobernador - Pilar: 6. Gobernanza y Participación Ciudadana. - Letra: c) Modernización Administrativa: Digitalizar los trámites y servicios administrativos para hacerlos más eficientes y accesibles. | P58: 6050 | Q58: 6100 | R58: =SUM(P58:Q58) -> 12150 | T58: Nunicipalidad Quinchao | U58: Nunicipalidad Quinchao | V58: 421 | W58: 45852 | Y58: 45852 | Z58: 45852 | AA58: 45852 | AB58: =WORKDAY(AA58,15,'Feriados y Comunas'!A$2:A$25) -> 45874 | AH58: 1750 | AI58: 45866 | AJ58: 45863 | AK58: OBSERVADO | AQ58: 1750 | AR58: 45866 | AU58: OBSERVADO | AV58: OK | AW58: 8
A59: =1+A58 -> 58 | B59: 40074881 | C59: 0 | D59: Diagnostico Elaboración y Prediseño del PACC | E59: Puyehue | F59: =+IFERROR(VLOOKUP(E59,'Feriados y Comunas'!$C$1:$D$36,2,FALSE),"") -> OSORNO | G59: 45876 | H59: 16000 | I59: Ejecución | J59: 2026 | K59: Recursos Naturales | L59: Comité 22-08-25. 1. Antecedentes El documento &quot; Antecedentes&quot; no incluye la identificación de las instituciones que actuarán como contrapartes técnicas, ni adjunta el documento de respaldo requerido. 2. Definición del problema en los TTR (Sin Firma UT) La definición actual del problema se limita a señalar la falta del instrumento PACCC o de diagnósticos comunales, junto con la insuficiencia de capacidades municipales. Se recomienda que la definición del problema se enfoque en los impactos potenciales del cambio climático sobre la comuna, considerando vulnerabilidades, riesgos y capacidades locales. 3. Presupuesto (Sin Firma) El presupuesto desglosado no incluye el detalle de horas por profesional, como lo exige el MDSF. Faltan cotizaciones de respaldo (al menos dos). 4. Uso de información disponible Los TTR no incorporan suficientemente el reporte comunal de Futuros Climáticos para Puyehue (adjunto), pese a que ya contiene información sobre contexto climático, ambiental, socioeconómico y demográfico. 5. Objetivos específicos Los objetivos específicos propuestos exceden el alcance del objetivo general. Se sugiere reducirlos o reformularlos, de manera que tributen directamente al objetivo general: “Elaborar un diagnóstico climático comunal para la comuna de Puyehue que permita identificar sus principales vulnerabilidades, riesgos, oportunidades y capacidades frente al cambio climático, como base técnica para la formulación del Plan de Acción Comunal de Cambio Climático (PACCC).” Algunos objetivos como la definición de lineamientos estratégicos o la propuesta de medidas de mitigación y adaptación corresponden a una etapa posterior (elaboración del PACCC). 6. Actividades en los TTR Las actividades 5 (Definición de visión y objetivos de un posible Plan de Acción) y 6 (Definición de medidas) exceden el alcance del estudio básico, pues corresponden al municipio una vez concluido este diagnóstico inicial. Asimismo, no aplica la etapa de prediseño, ya que también escapa al objetivo general propuesto. (RIS, sección 2, exige que las actividades sean coherentes con el diagnóstico y objetivos generales). 7. Cronograma El cronograma de actividades carece del nivel de detalle requerido. Debe expresarse en semanas o meses mediante una Carta Gantt completa. (RIS, sección 2, lo establece explícitamente). 8. Se sugiere reformular la iniciativa ya que para ser un estudio básico este debe ser conducente a una cartera de inversión de acuerdo a lo expresado en las NIP. 9. Adjuntar Documentación al BIP. | N59: Se encuentra dentro de la ERD - Lineamientos: Ordenamiento Territorial Sustentable y Resiliente. - Ítem: Cambio Climático y Riesgo de Desastres. - Obj.: Fortalecer el enfoque de la reducción de riesgo de desastre en instrumentos de Planificación y OT en sus diversas escalas.. - Actividad: Definición de una metodología de coordinación entre instrumentos de la gestión de riesgos en distintos niveles. | O59: Se enlaza con el programa del Gobernador Regional en el - Pilar: 4. Protección del Medo Ambiente. - Letra: d) Protección de Ecosistemas: Implementar políticas de conservación para proteger los ecosistemas de la región, especialmente los lagos y parques nacionales. | P59: 0 | Q59: 0 | R59: =SUM(P59:Q59) -> 0 | T59: Municipalidad Puyehue | U59: Municipalidad Puyehue | V59: 569 | W59: 45874 | Y59: 45876 | Z59: 45876 | AA59: 45876 | AB59: =WORKDAY(AA59,15,'Feriados y Comunas'!A$2:A$25) -> 45898 | AH59: 2135 | AI59: 45894 | AJ59: 45891 | AK59: OBSERVADO | AQ59: 2135 | AR59: 45894 | AU59: OBSERVADO | AV59: OK | AW59: 10
A60: =1+A59 -> 59 | B60: 40073040 | C60: 0 | D60: Construcción Extensión Red APR ST Aeródromo | E60: Futaleufú | F60: =+IFERROR(VLOOKUP(E60,'Feriados y Comunas'!$C$1:$D$36,2,FALSE),"") -> PALENA | G60: 45896 | H60: 980000 | I60: Ejecución | J60: 2026 | K60: Recursos Hidricos | L60: Comité 12-09-25. 1. Adjuntar documentación de acuerdo a las NIP y a las Orientaciones Regionales de Pre Inversión. 2. Adjuntar Documentación al BIP. | N60: Se encuentra dentro de la ERD en: - Lineamiento: Bienestar Socio territorial. - Ítem: Servicio Básicos. - Obj.: Ampliar la Red de alcantarillado para dar soluciones sustentables. Reducir el numero de vivienda desconectadas de un sistema de suministro de agua en las áreas rurales de la región. - Actividad: Plan de construcción y mejoramiento de infraestructura agua potable y alcantarillado urbano y rural. | O60: Se enlaza con el Programa Regional del Gobernador en el - Pilar: 3. Inclusión Social y Mejoramiento de la Calidad de Vida - Letra: c)Programas de Apoyo Social: Desarrollar iniciativas para apoyar a los sectores más vulnerables de nuestra comunidad. | P60: 30 | Q60: 30 | R60: =SUM(P60:Q60) -> 60 | T60: Municipalidad Futaleufu | U60: Municipalidad Futaleufu | V60: 213 | W60: 45803 | Y60: 45896 | Z60: 45896 | AA60: 45896 | AB60: =WORKDAY(AA60,15,'Feriados y Comunas'!A$2:A$25) -> 45917 | AH60: 2386 | AI60: 45916 | AJ60: 45912 | AK60: OBSERVADO | AQ60: 2386 | AR60: 45916 | AU60: OBSERVADO | AV60: OK | AW60: 12
A61: =1+A60 -> 60 | B61: 40015899 | C61: 0 | D61: Mejoramiento Cancha Liga Rural Union Sur Quilquico | E61: Castro | F61: CHILOÉ | G61: 45939 | H61: 2755673 | I61: Ejecución | J61: 2026 | K61: Deporte | L61: Obs. Comité 30-10-25. 1. Adjuntar Financiamiento mixto. 2. Adjuntar Documentación al BIP. | N61: La iniciativa se orienta dentro de la ERD en el: - Lineamiento: Bienestar Socio Territorial. - Ítem: Espacios y Equipamiento Público - Objetivo: Aumentar el Nro. De espacios polideportivos en la región con criterios de genero e inclusividad. - Actividad: No hay. | O61: Se enlaza con el Programa Regional del Gobernador: - Pilar: 3. Inclusión Social y Mejoramiento de la Calidad de Vida. - Letra: c) Programas de Apoyo Social: Desarrollar iniciativas para apoyar a los sectores más vulnerables de nuestra comunidad. | P61: 22336 | Q61: 21471 | R61: 43807 | T61: Municipalidad Castro | U61: Municipalidad Castro | V61: 1011 | W61: 45931 | Y61: 45939 | Z61: 45939 | AA61: 45939 | AB61: =WORKDAY(AA61,15,'Feriados y Comunas'!A$2:A$25) -> 45960 | AH61: 2904 | AI61: 45964 | AJ61: 45960 | AK61: OBSERVADO | AQ61: 2904 | AR61: 45964 | AU61: OBSERVADO | AV61: OK | AW61: 15
A62: =1+A61 -> 61 | B62: 30118609 | C62: 0 | D62: Habilitación SS EE ST Molulco | E62: Quellón | F62: =+IFERROR(VLOOKUP(E62,'Feriados y Comunas'!$C$1:$D$36,2,FALSE),"") -> CHILOÉ | G62: 45959 | H62: 658620 | I62: Ejecución | J62: 2026 | K62: Energía | L62: Comté 30-10-25. 1. Incorporar Oficio Conductor. 2. Adjuntar Participación Ciudadana. 3. Anexar Estratificación Social. 4. Incorporar Actividades Productivas. 5. Adjuntar Paralelismo. 6. Anexar Listado Beneficiarios. 7. Incorporar Copia Rut. 8. Adjuntar Instalaciones Interiores. 9. Anexar Certificado Conadi. 10. Incorporar Dominio Vigente. 11. Adjuntar Informe Unidad Energización GORE. 12. Anexar Georreferenciación v/s área de concesión. 13. Adjuntar Documentación al BIP. | N62: Se encuentra dentro de los lineamientos de la ERD en Bienestar Socio Territorial. Ítem Medioambiente y Eficiencia Energética, (Obj. Reducir la Pobreza Energética en las viviendas de la Región). | O62: Se enlaza con el Programa Regional del Gobernador - Pilar: 3. Inclusión Social y Mejoramiento de la Calidad de Vida. - Letra: c) Programas de Apoyo Social: Desarrollar iniciativas para apoyar a los sectores más vulnerables de nuestra comunidad. | P62: 67 | Q62: 58 | R62: =SUM(P62:Q62) -> 125 | T62: Municipalidad Quellon | U62: Municipalidad Quellon | W62: 45953 | Y62: 45959 | Z62: 45959 | AA62: 45959 | AB62: =WORKDAY(AA62,15,'Feriados y Comunas'!A$2:A$25) -> 45981 | AH62: 2913 | AI62: 45964 | AJ62: 45960 | AK62: OBSERVADO | AQ62: 2913 | AR62: 45964 | AU62: OBSERVADO | AV62: OK | AW62: 1
A63: =1+A62 -> 62 | B63: 30095595 | C63: 0 | D63: Habilitacion SS EE ST Colonia Yungay Nahuelpani | E63: Quellón | F63: =+IFERROR(VLOOKUP(E63,'Feriados y Comunas'!$C$1:$D$36,2,FALSE),"") -> CHILOÉ | G63: 45960 | H63: 833063 | I63: Ejecución | J63: 2026 | K63: Energía | L63: Comté 30-10-25. 1. Incorporar Oficio Conductor. 2. Adjuntar Participación Ciudadana. 3. Anexar Estratificación Social. 4. Incorporar Actividades Productivas. 5. Adjuntar Paralelismo. 6. Anexar Listado Beneficiarios. 7. Incorporar Copia Rut. 8. Adjuntar Instalaciones Interiores. 9. Anexar Certificado Conadi. 10. Incorporar Dominio Vigente. 11. Adjuntar Informe Unidad Energización GORE. 12. Anexar Georreferenciación v/s área de concesión. 13. Adjuntar Documentación al BIP. | N63: Se encuentra dentro de los lineamientos de la ERD en Bienestar Socio Territorial. Ítem Medioambiente y Eficiencia Energética, (Obj. Reducir la Pobreza Energética en las viviendas de la Región). | O63: Se enlaza con el Programa Regional del Gobernador - Pilar: 3. Inclusión Social y Mejoramiento de la Calidad de Vida. - Letra: c) Programas de Apoyo Social: Desarrollar iniciativas para apoyar a los sectores más vulnerables de nuestra comunidad. | P63: 71 | Q63: 65 | R63: =SUM(P63:Q63) -> 136 | T63: Municipalidad Quellon | U63: Municipalidad Quellon | V63: 978 | W63: 45953 | Y63: 45959 | Z63: 45959 | AA63: 45959 | AB63: =WORKDAY(AA63,15,'Feriados y Comunas'!A$2:A$25) -> 45981 | AH63: 2903 | AI63: 45964 | AJ63: 45960 | AK63: OBSERVADO | AQ63: 2903 | AR63: 45964 | AU63: OBSERVADO | AV63: OK | AW63: 1
A64: =1+A63 -> 63 | B64: 50000242 | C64: 0 | D64: Reposición Cuartel 7° Cía de Bomberos | E64: Osorno | F64: =+IFERROR(VLOOKUP(E64,'Feriados y Comunas'!$C$1:$D$36,2,FALSE),"") -> OSORNO | G64: 46050 | H64: 157800 | I64: Diseño | J64: 2026 | K64: Seguridad | L64: Comité 10-04-26. 1. Adjuntar Cronograma. 2. Anexara Participación Ciudadana. 3. Incorporar Informe Técnico Situación Actual. 4. Ajustar valor m2 de diseño a valor promedio provincial (2,99). 5. Modificar UT. 6. Adjuntar la Documentación al BIP. | N64: Se encuentra dentro de los lineamientos de la ERD - Lineamiento: Bienes Socio Territorial. Ítem: Espacios y Equipamiento Publico. Obj.: Construir equipamiento publico y espacios de carácter cívico en la Región. | O64: Se enlaza con el Programa Regional del Gobernador en el - Pilar: 3. Inclusión Social y Mejoramiento de la Calidad de Vida. - Letra: c) Programas de Apoyo Social: Desarrollar iniciativas para apoyar a los sectores más vulnerables de nuestra comunidad. | P64: 0 | Q64: 0 | R64: 0 | T64: MOP - DA | U64: Delegacion Presidencial Osorno | V64: 54 | W64: 46043 | AA64: 46050 | AB64: =WORKDAY(AA64,15,'Feriados y Comunas'!A$2:A$25) -> 46071 | AH64: 290 890 | AI64: 06-02-2026 17-04-2026 | AJ64: 06-02-2026 10-04-2026 | AK64: OBSERVADO | AL64: 54 117 | AM64: 21-01-2026 05-03-2026 | AO64: 13-02-2026 09-03-2026 | AQ64: 290 890 | AR64: 06-02-2026 17-04-2026 | AU64: OBSERVADO | AV64: OK | AW64: 7
A65: =1+A64 -> 64 | B65: 40072882 | C65: 0 | D65: Diseño Plan Maestro Parque Nacional Vicente Perez Rosales | E65: Puerto Varas | F65: =+IFERROR(VLOOKUP(E65,'Feriados y Comunas'!$C$1:$D$36,2,FALSE),"") -> LLANQUIHUE | G65: 46064 | H65: 118250 | I65: Ejecución | J65: 2026 | K65: Recursos Naturales | L65: Comité 13-03-26. 1. Anexar TDR con Firma por parte de la UT. 2. Incorporar como contraparte técnica a CONAF. 3. Adjuntar Cotizaciones. 4. Se sugiere contrarrestar el perfil y TDR con la contraparte técnica. 5. Adjuntar Documentación al BIP. | N65: Se encuentra dentro de la ERD en: Lineamiento: Ordenamiento Territorial Sustentable y Resiliente. Ítem: Protección del Patrimonio Natural. Obj.: Implementar programas de protección y conservación de áreas protegidas en la región en calidad de áreas de valor natural, asegurando sus resguardos, funcionamientos y mantenciones. Actividad: Programa de Protección de áreas protegidas existentes y santuarios de la naturaleza. | O65: Se enlaza con el programa del Gobernador Regional en el lineamiento «Hagamos una Región de Acceso Universal» Acción “Facilitar el acceso a servicios, tanto en lo estructural como en la información”. | P65: 306149 | Q65: 246411 | R65: =SUM(P65:Q65) -> 552560 | T65: Conaf | U65: Conaf | V65: 403 | W65: 46059 | Y65: 46064 | Z65: 46064 | AA65: 46064 | AB65: =WORKDAY(AA65,15,'Feriados y Comunas'!A$2:A$25) -> 46085 | AH65: 519 | AI65: 46097 | AJ65: 46094 | AK65: OBSERVADO | AQ65: 519 | AR65: 46097 | AU65: OBSERVADO | AW65: 22
A66: =1+A65 -> 65 | B66: 40005957 | C66: 0 | D66: Reposición Museo Municipal y Biblioteca Publica | E66: Castro | F66: =+IFERROR(VLOOKUP(E66,'Feriados y Comunas'!$C$1:$D$36,2,FALSE),"") -> CHILOÉ | G66: 46274 | H66: 8731320 | I66: Ejecución | J66: 2026 | K66: Educación | L66: Comité 26-06-26. 1. Se mantienen las Observaciones: 2. Actualizar Participación Ciudadana (2019). 3. Anexar Cronograma o Carta Gantt. 4. Incorporar Informe técnico situación Actual. 5. Actualizar Factibilidades (2022 - 2023). 6. Adjuntar Certificado de Costos Operacionales Firmado por el consejo Municipal. 7. Incorporar Carta Mesa Regional de Patrimonio. 8. Adjuntar Documentación al BIP. | N66: Se encuentra dentro de la ERD en: - Lineamiento: Cohesión e Identidad Socio Cultural. - Ítem: Arte y Cultura. - Objetivo: Construir y renovar infraestructura cultural de alto estándar para habilitar el acceso y desarrollo de las culturas y las artes locales y regional. - Actividad: No Hay. | O66: Se enlaza con el Programa Regional del Gobernador - Pilar: 5. Desarrollo Cultural y Turismo”, - Letra: c) Centros Culturales: Crear y mantener centros culturales en las principales ciudades y localidades para promover la cultura local. | P66: 21471 | Q66: 22336 | R66: =SUM(P66:Q66) -> 43807 | T66: Municipalidad Castro | U66: Municipalidad Castro | V66: 276 | W66: 46086 | AA66: 46090 | AB66: =WORKDAY(AA66,15,'Feriados y Comunas'!A$2:A$25) -> 46111 | AH66: 791 | AI66: 46126 | AJ66: 46122 | AK66: OBSERVADO | AL66: 674 969 | AM66: 01-06-2026 11-08-2026 | AO66: 16-06-2026 12-08-2026 | AQ66: 791 | AR66: 46126 | AU66: OBSERVADO | AW66: 24
A67: =1+A66 -> 66 | B67: 40043228 | C67: 0 | D67: Reposición Cancha Villa San Pablo | E67: San Pablo | F67: =+IFERROR(VLOOKUP(E67,'Feriados y Comunas'!$C$1:$D$36,2,FALSE),"") -> OSORNO | G67: 46108 | H67: 1861874 | I67: Ejecución | J67: 2026 | K67: Deporte | L67: Comité 18-05-26. 1. 1. Finalizar Etapa de diseño. (Se sugiere coordinar reunión DIPIR – Jurídica Gore). 2. Adjuntar Ppto. AITO. 3. Anexar Ppto. Equipos. 4. Incorporar Mecánica de suelos. 5. Adjuntar Revisores Independientes. 6. Anexar Plan de Mitigación. 7. Incorporar Modelos de Gestión. 8. Adjuntar Informe Técnico Situación Actual. 9. Anexar IMIV. 10. Incorporar Dominio Vigente. 11. Adjuntar Hipotecas y Gravámenes. 12. Anexar Certificado Informes Previos. 13. Incorporar Factibilidades. 14. Adjuntar Costos Operacionales firmado por el consejo. 15. Anexar Certificado IND. 16. Adjuntar Documentación al BIP. | N67: La iniciativa se orienta dentro de la ERD en el: - Lineamiento: Bienestar Socio Territorial. - Ítem: Espacios y Equipamiento Público - Objetivo: Aumentar el Nro. De espacios polideportivos en la región con criterios de genero e inclusividad. - Actividad: No hay. | O67: Se enlaza con el Programa Regional del Gobernador: - Pilar: 3. Inclusión Social y Mejoramiento de la Calidad de Vida. - Letra: c) Programas de Apoyo Social: Desarrollar iniciativas para apoyar a los sectores más vulnerables de nuestra comunidad. | P67: 500 | Q67: 130 | R67: =SUM(P67:Q67) -> 630 | T67: Municipalidad San Pablo | U67: Municipalidad San Pablo | V67: 700 | W67: 45945 | AA67: 46108 | AB67: =WORKDAY(AA67,15,'Feriados y Comunas'!A$2:A$25) -> 46129 | AH67: 793 1258 1612 | AI67: 14-04-2026 26-05-2026 26-06-2026 | AJ67: 10-04-2026 15-05-2026 26-06-2026 | AK67: OBSERVADO | AL67: 14 674 | AM67: 16-04-2026 01-06-2026 | AO67: 16-04-2026 16-06-2026 | AQ67: 793 1258 1612 | AR67: 14-04-2026 26-05-2026 26-06-2026 | AU67: OBSERVADO | AV67: OK | AW67: 10
A68: =1+A67 -> 67 | B68: 40071293 | C68: 0 | D68: Reposición PSR de Buill | E68: Chaitén | F68: =+IFERROR(VLOOKUP(E68,'Feriados y Comunas'!$C$1:$D$36,2,FALSE),"") -> PALENA | G68: 46133 | H68: 1643325 | I68: Ejecución | J68: 2026 | K68: Salud | L68: Comité 12-06-26.1. Se solicita proporcionar antecedentes del terreno al momento de la ejecución original, con el objeto que el departamento jurídico del GORE Los Lagos analice el comodato ya que se está postulando una nueva infraestructura antes del cumplimiento de la vida útil. 2. Adjuntar la Documentación al BIP. | N68: Se encuentra dentro de la ERD en el - Lineamiento: Bienestar Socio Territorial. - Ítem: Salud. - Objetivo: Aumentar Cobertura de atención primaria en salud en la comunas de la región. - Actividad: Convenio de Programación. | O68: Se enlaza con el programa del Gobernador Regional en el - Pilar: 3. Inclusión Social y Mejoramiento de la Calidad de Vida. - Letra: e) Acceso a Servicios de Salud: Ampliar y mejorar la red de servicios de salud, especialmente en zonas rurales, garantizando atención médica de calidad para todos. | P68: 258 | Q68: 230 | R68: =SUM(P68:Q68) -> 488 | T68: SSReloncavi | U68: Municipalidad Chaiten | V68: 302 | W68: 46133 | AA68: 46133 | AB68: =WORKDAY(AA68,15,'Feriados y Comunas'!A$2:A$25) -> 46154 | AH68: 1262 1463 | AI68: 26-05-2026 15-06-2026 | AJ68: 15-05-2026 12-06-2026 | AK68: OBSERVADO | AL68: 433 | AM68: 46171 | AO68: 46171 | AQ68: 1262 1463 | AR68: 26-05-2026 15-06-2026 | AU68: OBSERVADO | AW68: 18
A69: =1+A68 -> 68 | B69: 40073908 | C69: 0 | D69: Construcción Polideportivo de Achao | E69: Quinchao | F69: =+IFERROR(VLOOKUP(E69,'Feriados y Comunas'!$C$1:$D$36,2,FALSE),"") -> CHILOÉ | G69: 46157 | H69: 83922 | I69: Diseño | J69: 2027 | K69: Deporte | L69: Comité 12-06-26. 1. Se mantiene la solicitud de adjuntar compromiso de cofinanciamiento. 2. Adjuntar la Documentación al BIP. | N69: La iniciativa se orienta dentro de la ERD en el: - Lineamiento: Bienestar Socio Territorial. - Ítem: Espacios y Equipamiento Público - Objetivo: Aumentar el Nro. De espacios polideportivos en la región con criterios de genero e inclusividad. - Actividad: No hay. | O69: Se enlaza con el Programa Regional del Gobernador: - Pilar: 3. Inclusión Social y Mejoramiento de la Calidad de Vida. - Letra: c) Programas de Apoyo Social: Desarrollar iniciativas para apoyar a los sectores más vulnerables de nuestra comunidad. | P69: 407 | Q69: 406 | R69: =SUM(P69:Q69) -> 813 | T69: Municipalidad Quinchao | U69: Municipalidad Quinchao | V69: 235 | W69: 46154 | AA69: 46157 | AB69: =WORKDAY(AA69,15,'Feriados y Comunas'!A$2:A$25) -> 46178 | AH69: 1265 1453 | AI69: 26-05-2026 15-06-2026 | AJ69: 15-05-2026 12-06-2026 | AK69: OBSERVADO | AL69: 252 | AM69: 46169 | AO69: 46171 | AQ69: 1265 1453 | AR69: 26-05-2026 15-06-2026 | AU69: OBSERVADO | AV69: OK | AW69: 1
A70: =1+A69 -> 69 | B70: 40031485 | C70: 0 | D70: Mejoramiento y Ampliación Sistema APR y ALC. | E70: Queilén | F70: =+IFERROR(VLOOKUP(E70,'Feriados y Comunas'!$C$1:$D$36,2,FALSE),"") -> CHILOÉ | G70: 46178 | H70: 1400000 | I70: Diseño | J70: 2027 | K70: Recursos Hidricos | L70: Comité 12-06-26. 1. Proyecto está postulado a una etapa incorrecta, ya que el perfil y presupuesto presentan serias inconsistencias frente a las normas y criterios del Sistema Nacional de Inversiones (SNI), se presenta una mezcla entre Pre inversión v/s Diseño. 2. Se sugiere presentar a la etapa de pre factibilidad. 3. Adjuntar información al BIP. | N70: Se encuentra dentro de la ERD en: - Lineamiento: Bienestar Socio territorial. - Ítem: Servicio Básicos. - Obj.: Ampliar la Red de alcantarillado para dar soluciones sustentables. Reducir el numero de vivienda desconectadas de un sistema de suministro de agua en las áreas rurales de la región. - Actividad: Plan de construcción y mejoramiento de infraestructura agua potable y alcantarillado urbano y rural. | O70: Se enlaza con el Programa Regional del Gobernador en el - Pilar: 3. Inclusión Social y Mejoramiento de la Calidad de Vida - Letra: c)Programas de Apoyo Social: Desarrollar iniciativas para apoyar a los sectores más vulnerables de nuestra comunidad. | P70: 1612 | Q70: 1650 | R70: =SUM(P70:Q70) -> 3262 | T70: Municipalidad Queilen | U70: Municipalidad Queilen | V70: 581 | W70: 46176 | AA70: 46178 | AB70: =WORKDAY(AA70,15,'Feriados y Comunas'!A$2:A$25) -> 46199 | AH70: 1465 | AI70: 46188 | AJ70: 46185 | AK70: OBSERVADO | AQ70: 1465 | AR70: 46188 | AU70: OBSERVADO | AV70: OK | AW70: 5
A71: =1+A70 -> 70 | B71: 30419694 | C71: 0 | D71: Reposición Esc. Rural Caleta El Manzano | E71: Hualaihué | F71: =+IFERROR(VLOOKUP(E71,'Feriados y Comunas'!$C$1:$D$36,2,FALSE),"") -> PALENA | G71: 46176 | H71: 2752987 | I71: Ejecución | J71: 2027 | K71: Educación | L71: Comité 12-06-26. 1. Adjuntar compromiso de financiamiento compartido. 2. Anexar Costos Operacionales. 3. Incorporar Plan de Mitigación. 4. Adjuntar Informe situación actual. 5. Anexar Dominio Vigente. 6. Incorporar Hipotecas y gravámenes. 7. Anexar Certificado de Informaciones Previas. (CIP). 8. Adjuntar la Documentación al BIP. | N71: Se encuentra dentro de la ERD en, - Lineamiento: Bienestar Socio Territorial. - Ítem: Educación. - Objetivo: Mejorar el desempeño de los establecimientos educacionales públicos y subvencionados de la Región . - Actividad: No hay. | O71: Se enlaza con el Programa Regional del Gobernador en el lineamiento - Pilar: 3. Inclusión Social y Mejoramiento de la Calidad de Vida. - Letra: i) Infraestructura Educativa: Renovar y construir nuevas instalaciones educativas para garantizar ambientes de aprendizaje adecuados. | P71: 27 | Q71: 27 | R71: =SUM(P71:Q71) -> 54 | T71: Municipalidad Hualaihue | U71: Municipalidad Hualaihue | V71: 523 | W71: 46175 | AA71: 46176 | AB71: =WORKDAY(AA71,15,'Feriados y Comunas'!A$2:A$25) -> 46197 | AH71: 1462 | AI71: 46188 | AJ71: 46185 | AK71: OBSERVADO | AQ71: 1462 | AR71: 46188 | AU71: OBSERVADO | AV71: OK | AW71: 7
A72: =1+A71 -> 71 | B72: 30034826 | C72: 0 | D72: Reposición PSR Isla Maillen | E72: Puerto Montt | F72: =+IFERROR(VLOOKUP(E72,'Feriados y Comunas'!$C$1:$D$36,2,FALSE),"") -> LLANQUIHUE | G72: 46190 | H72: 1451216 | I72: Ejecución | J72: 2026 | K72: Salud | L72: Comité 25-09-26. 1. Adjuntar Oficio de postulación. 2. Crear Ficha 2027. 3. Incorporar Ppto. Equipo y equipamiento firmado con cotizaciones. 4. Adjuntar TTR firmados por la UT. 5. Anexar Participación ciudadana. 6. Incorporar Plan de Mitigación. 7. Adjuntar IMIV, si corresponde. 8. Incorporar Certificado de no objeción del SSReloncavi. 9. Anexar Certificado de Hipotecas y Gravámenes. 10. Incorporar Cronograma. 11. Adjuntar Documentación al BIP. | N72: Se encuentra dentro de la ERD en el - Lineamiento: Bienestar Socio Territorial. - Ítem: Salud. - Objetivo: Aumentar Cobertura de atención primaria en salud en la comunas de la región. - Actividad: Convenio de Programación. | O72: Se enlaza con el programa del Gobernador Regional en el - Pilar: 3. Inclusión Social y Mejoramiento de la Calidad de Vida. - Letra: e) Acceso a Servicios de Salud: Ampliar y mejorar la red de servicios de salud, especialmente en zonas rurales, garantizando atención médica de calidad para todos. | P72: 199 | Q72: 249 | R72: =SUM(P72:Q72) -> 448 | T72: Municipalidad Puerto Montt | U72: Municipalidad Puerto Montt | V72: 494 | W72: 46176 | AA72: 46190 | AB72: =WORKDAY(AA72,15,'Feriados y Comunas'!A$2:A$25) -> 46211 | AH72: 1644 2693 | AI72: 30-06-2026 10-09-2026 | AJ72: 26-06-2026 25-09-2026 | AK72: OBSERVADO | AL72: 1788 | AM72: 46262 | AO72: 46265 | AQ72: 1644 2693 | AR72: 30-06-2026 10-09-2026 | AU72: OBSERVADO | AV72: OK | AW72: 7
A73: =1+A72 -> 72 | B73: 40072730 | C73: 0 | D73: Mejoramiento Gimnasio Esc. Rural San Antonio Pocoihuen Alto | E73: Cochamó | F73: =+IFERROR(VLOOKUP(E73,'Feriados y Comunas'!$C$1:$D$36,2,FALSE),"") -> LLANQUIHUE | G73: 46198 | H73: 440112 | I73: Ejecución | J73: 2027 | K73: Educación | L73: Comité 15-07-26. 1. Adjuntar Informe situación actual. 2. Anexar EETT con firma de la UT. 3. Incorporar Memoria de Cálculo. 4. Adjuntar Revisores Independientes. 5. Anexar IMIV si corresponde. 6. Ajustar Diferencia Programa Arquitectónico v/s IDI. 7. Ajustar Diferencia entre Ppto. v/s IDI. 8. Incorporar programa recintos actual v/s el propuesto. 9. Anexar Financiamiento compartido. 10. Adjuntar la Documentación al BIP. | N73: Se encuentra dentro de la ERD en, - Lineamiento: Bienestar Socio Territorial. - Ítem: Educación. - Objetivo: Mejorar el desempeño de los establecimientos educacionales públicos y subvencionados de la Región . - Actividad: No hay. | O73: Se enlaza con el Programa Regional del Gobernador en el lineamiento - Pilar: 3. Inclusión Social y Mejoramiento de la Calidad de Vida. - Letra: i) Infraestructura Educativa: Renovar y construir nuevas instalaciones educativas para garantizar ambientes de aprendizaje adecuados. | P73: 50 | Q73: 50 | R73: =SUM(P73:Q73) -> 100 | T73: Municipalidad Cochamo | U73: Municipalidad Cochamo | V73: 490 | W73: 46199 | AA73: 46199 | AB73: =WORKDAY(AA73,15,'Feriados y Comunas'!A$2:A$25) -> 46220 | AH73: 1845 | AI73: 46225 | AJ73: 46218 | AK73: OBSERVADO | AQ73: 1845 | AR73: 46225 | AU73: OBSERVADO | AV73: OK | AW73: 13
A74: =1+A73 -> 73 | B74: 40069091 | C74: 0 | D74: Construcción PSR Forrahue | E74: Osorno | F74: =+IFERROR(VLOOKUP(E74,'Feriados y Comunas'!$C$1:$D$36,2,FALSE),"") -> OSORNO | G74: 46205 | H74: 1270025 | I74: Ejecución | J74: 2027 | K74: Salud | L74: Comité 15-07-26. 1. Incorporar iniciativa al Convenio de Salud. 2. Adjuntar Presupuesto Obras Civiles con firma. 3. Anexar EETT Firmada por la UT. 4. Actualizar la Participación Ciudadana. 5. Incorporar Factibilidades. 6. Adjuntar Costos Operacionales Firmado por Consejo Municipal. 7. Anexar Informe Infraestructura Actual. 8. Incorporar Cronograma. 9. Adjuntar Plan de Contingencia. 10. Anexar Certificado Conadi si corresponde. 11. Adjuntar la Documentación al BIP. | N74: Se encuentra dentro de la ERD en el - Lineamiento: Bienestar Socio Territorial. - Ítem: Salud. - Objetivo: Aumentar Cobertura de atención primaria en salud en la comunas de la región. - Actividad: Convenio de Programación. | O74: Se enlaza con el programa del Gobernador Regional en el - Pilar: 3. Inclusión Social y Mejoramiento de la Calidad de Vida. - Letra: e) Acceso a Servicios de Salud: Ampliar y mejorar la red de servicios de salud, especialmente en zonas rurales, garantizando atención médica de calidad para todos. | P74: 468 | Q74: 391 | R74: =SUM(P74:Q74) -> 859 | T74: Municipalidad Osorno | U74: Municipalidad Osorno | V74: 309 | W74: 46199 | AA74: 46205 | AB74: =WORKDAY(AA74,15,'Feriados y Comunas'!A$2:A$25) -> 46226 | AH74: 1849 | AI74: 46225 | AJ74: 46218 | AK74: OBSERVADO | AQ74: 1849 | AR74: 46225 | AU74: OBSERVADO | AV74: OK | AW74: 10
A75: =1+A74 -> 74 | B75: 40072640 | C75: 0 | D75: Construcción Estadio Municipal St Rural de Taiguen, Peninsula de Lacuy | E75: Ancud | F75: =+IFERROR(VLOOKUP(E75,'Feriados y Comunas'!$C$1:$D$36,2,FALSE),"") -> CHILOÉ | G75: 46244 | H75: 115000 | I75: Diseño | J75: 2027 | K75: Deporte | L75: Comité 28-08-26. 1. Adjuntar compromiso de Financiamiento compartido. 2. Incorporar Participación Ciudadana. 3. Anexar Modelo de Gestión. 4. Adjuntar Plan de Mitigación, si corresponde. 5. Incorporar Visación DOM. 6. Anexar Informe situación Actual. 7. Adjuntar certificación de ANFA. 8. Se sugiere replantear diseño a requerimientos para la práctica deportiva. 9. Justificar estándar FIFA de los usuarios. 10. Adjuntar la Información al BIP. | N75: La iniciativa se orienta dentro de la ERD en el: - Lineamiento: Bienestar Socio Territorial. - Ítem: Espacios y Equipamiento Público - Objetivo: Aumentar el Nro. De espacios polideportivos en la región con criterios de genero e inclusividad. - Actividad: No hay. | O75: Se enlaza con el Programa Regional del Gobernador: - Pilar: 3. Inclusión Social y Mejoramiento de la Calidad de Vida. - Letra: c) Programas de Apoyo Social: Desarrollar iniciativas para apoyar a los sectores más vulnerables de nuestra comunidad. | P75: 448 | Q75: 64 | R75: =SUM(P75:Q75) -> 512 | T75: Municipalidad Ancud | U75: Municipalidad Ancud | V75: 750 | W75: 46240 | AA75: 46244 | AB75: =WORKDAY(AA75,15,'Feriados y Comunas'!A$2:A$25) -> 46265 | AH75: 2642 | AI75: 46268 | AJ75: 46262 | AK75: OBSERVADO | AQ75: 2642 | AR75: 46268 | AU75: OBSERVADO | AV75: OK | AW75: 14
A76: =1+A75 -> 75 | B76: 40077016 | C76: 0 | D76: Construcción Centro de Investigación Frutícola de la Region de Los Lagos | E76: Osorno | F76: =+IFERROR(VLOOKUP(E76,'Feriados y Comunas'!$C$1:$D$36,2,FALSE),"") -> OSORNO | G76: 46258 | H76: 112664 | I76: Diseño | J76: 2027 | K76: Educación | L76: Comité 28-08-26.1. Financiamiento de Ejecución: Identificar e ingresar formalmente la institución financiera y la fuente de recursos que asumirán el financiamiento de la etapa de ejecución. 2. Diagnóstico de Demanda Integral: Desarrollar la estimación de la demanda actual y proyectada en el área de influencia dentro del diagnóstico, incorporando los requerimientos de toda la oferta como por ejemplo del Instituto Profesional Agrícola Adolfo Matthei. 3. Balance Oferta-Demanda y Brecha: Profundizar el análisis de la oferta optimizada y la demanda proyectada durante el horizonte de evaluación, determinando con precisión la brecha o déficit (cuantitativo y/o cualitativo) a resolver. 4. Revisión del Árbol de Problemas: Reestructurar la lógica de causas y efectos en el árbol de problemas, asegurando que el problema central se defina como una necesidad insatisfecha o condición de riesgo y no como la ausencia de una solución obra específica. 5. Ventajas Competitivas: Definir y fundamentar las ventajas competitivas de la alternativa seleccionada en términos de localización, tecnología, tamaño y modelo de gestión. 6. Factibilidad Eléctrica: Adjuntar el certificado de factibilidad técnica de suministro y empalme eléctrico emitido por la empresa distribuidora correspondiente. 7. Visación de la Unidad Técnica (UT): Acreditar la visación y validación técnica formal de los antecedentes (presupuesto, términos técnicos de referencia) firmada por Unidad Técnica. 8. Informe de Situación Actual: Cargar en la carpeta digital el informe técnico que diagnostique el estado físico, operativo, legal y territorial actual de la infraestructura o terreno. 9. Plan de Mitigación: Presentar el Plan correspondiente para abordar los impactos ambientales, de tránsito/viales o los planes de contingencia durante el desarrollo del proyecto. 10. Incorporar listado valorizado de equipo y equipamiento con sus respectivas fichas técnicas. 11. Adjuntar la Información al BIP | P76: 420 | Q76: 404 | R76: =SUM(P76:Q76) -> 824 | T76: Universidad de Los Lagos | U76: Universidad de Los Lagos | V76: 132 | W76: 46251 | AA76: 46258 | AB76: =WORKDAY(AA76,15,'Feriados y Comunas'!A$2:A$25) -> 46279 | AH76: 2651 | AI76: 46269 | AJ76: 46262 | AK76: OBSERVADO | AU76: OBSERVADO | AV76: OK | AW76: 4
A77: =1+A76 -> 76 | B77: 40073295 | C77: 0 | D77: Mejoramiento Multicancha Cubierta Esc. Juan Soler Manferdini | E77: Cochamó | F77: =+IFERROR(VLOOKUP(E77,'Feriados y Comunas'!$C$1:$D$36,2,FALSE),"") -> LLANQUIHUE | G77: 46275 | H77: 556258 | I77: Ejecución | J77: 2027 | K77: Deporte | L77: Comité 25-09-26. 1. Adjuntar TTR firmados por la UT. 2. Anexar PPto. OC. Firmadas. 3. Incorporar Ppto. AITO si corresponde. 4. Adjuntar Participación ciudadana. 5. Adjuntar Permiso. 6. Incorporar Mecánica de Suelos. 7. Adjuntar Revisores Independientes. 8. Anexar Plan de Mitigación. 9. Incorporar Informe Técnico Situación Actual. 10. Adjuntar IMIV, si corresponde. 11. Anexar Certificado Hipotecas y Gravámenes. 12. Incorporar Planos Firmados. 13. Anexar Cotizaciones de equipamiento. 14. Adjuntar Documentación al BIP. | N77: Se encuentra dentro de la ERD en, - Lineamiento: Bienestar Socio Territorial. - Ítem: Educación. - Objetivo: Mejorar el desempeño de los establecimientos educacionales públicos y subvencionados de la Región . - Actividad: No hay. | O77: Se enlaza con el Programa Regional del Gobernador en el lineamiento - Pilar: 3. Inclusión Social y Mejoramiento de la Calidad de Vida. - Letra: i) Infraestructura Educativa: Renovar y construir nuevas instalaciones educativas para garantizar ambientes de aprendizaje adecuados. | P77: 96 | Q77: 96 | R77: =SUM(P77:Q77) -> 192 | T77: Municipalidad Cochamo | U77: Municipalidad Cochamo | V77: 702-26 | W77: 46275 | AA77: 46279 | AB77: =WORKDAY(AA77,15,'Feriados y Comunas'!A$2:A$25) -> 46300 | AH77: 2881 | AI77: 46288 | AJ77: 46290 | AK77: OBSERVADO | AQ77: 2881 | AR77: 46288 | AU77: OBSERVADO | AV77: OK | AW77: 9
A78: =1+A77 -> 77 | B78: 40063290 | C78: 0 | D78: Mejoramiento Veredas Barrio Lagos de Chile, Rio Negro | E78: Río Negro | F78: =+IFERROR(VLOOKUP(E78,'Feriados y Comunas'!$C$1:$D$36,2,FALSE),"") -> OSORNO | G78: 46274 | H78: 434641 | I78: Ejecución | J78: 2027 | K78: Transporte | L78: Comité 25-09-26. 1. Adjuntar Oficio de postulación. 2. Anexar Ppto. AITO. 3. Incorporar Factibilidad Eléctrica. 4. Adjuntar Costos Operacionales. 5. Anexar Memoria Calculo. 6. Incorporar mecánica. 7. Adjuntar proyecto de ingeniería. 8. Incorporar Certificado SERVIU. 9. Anexar Participación Ciudadana. 10. Incorporar Informe Técnico Situación Actual. 11. Adjuntar Documentación al BIP. | N78: Se encuentra dentro de los de la ERD en - lineamientos: Conectividad y Movilidad Regional Sustentable. - Ítem Conectividad insular y de lugares aislados. - Obj.: Disminuir el déficit de infraestructura de conectividad para territorios insulares y aislados de la región. | O78: Se enlaza con el Programa Regional del Gobernador en el - Pilar: 2. Desarrollo Económico Sostenible: una Alianza Público-Privada. - Letra: c) Inversiones en Infraestructura: Mejorar la conectividad y la infraestructura regional para atraer inversiones y generar empleo. | P78: 503 | Q78: 489 | R78: =SUM(P78:Q78) -> 992 | T78: Municipalidad Rio Negro | U78: Municipalidad Rio Negro | V78: 948 | W78: 46274 | AA78: 46274 | AB78: =WORKDAY(AA78,15,'Feriados y Comunas'!A$2:A$25) -> 46295 | AH78: 2880 | AI78: 46288 | AJ78: 46290 | AK78: OBSERVADO | AQ78: 2880 | AR78: 46288 | AU78: OBSERVADO | AV78: OK | AW78: 12
A79: =1+A78 -> 78 | B79: 30092370 | C79: 0 | D79: Reposición PSR Salto Grande | E79: Puerto Montt | F79: =+IFERROR(VLOOKUP(E79,'Feriados y Comunas'!$C$1:$D$36,2,FALSE),"") -> LLANQUIHUE | G79: 46266 | H79: 1313306 | I79: Ejecución | J79: 2027 | K79: Salud | L79: Comité 25-09-26 1. Incorporar Ppto. Equipo y equipamiento firmado con cotizaciones. 2. Adjuntar TTR firmados por la UT. 3. Anexar Participación ciudadana. 4. Incorporar Plan de Mitigación. 5. Adjuntar IMIV, si corresponde 6. Incorporar Bases Técnicas firmadas por quien fiscalizara. 7. Adjuntar Documentación al BIP. | N79: Se encuentra dentro de la ERD en el - Lineamiento: Bienestar Socio Territorial. - Ítem: Salud. - Objetivo: Aumentar Cobertura de atención primaria en salud en la comunas de la región. - Actividad: Convenio de Programación. | O79: Se enlaza con el programa del Gobernador Regional en el - Pilar: 3. Inclusión Social y Mejoramiento de la Calidad de Vida. - Letra: e) Acceso a Servicios de Salud: Ampliar y mejorar la red de servicios de salud, especialmente en zonas rurales, garantizando atención médica de calidad para todos. | P79: 150 | Q79: 250 | R79: =SUM(P79:Q79) -> 400 | T79: Municipalidad Puerto Montt | U79: Municipalidad Puerto Montt | V79: 710 | W79: 46266 | AA79: 46267 | AB79: =WORKDAY(AA79,15,'Feriados y Comunas'!A$2:A$25) -> 46288 | AH79: 2695 | AI79: 46275 | AJ79: 46290 | AK79: OBSERVADO | AQ79: 2695 | AR79: 46275 | AU79: OBSERVADO | AV79: OK | AW79: 6
A80: =1+A79 -> 79 | B80: 40080268 | C80: 0 | D80: Mejoramiento Calle Los Alpes | E80: Puerto Varas | F80: =+IFERROR(VLOOKUP(E80,'Feriados y Comunas'!$C$1:$D$36,2,FALSE),"") -> LLANQUIHUE | G80: 46260 | H80: 417249 | I80: Ejecución | J80: 2027 | K80: Transporte | L80: Comité 25-09-26. 1. Adjuntar Oficio de postulación. 2. Anexar Ppto. AITO. 3. Incorporar Factibilidad Eléctrica. 4. Adjuntar Costos Operacionales. 5. Anexar Memoria Calculo. 6. Incorporar mecánica. 7. Adjuntar proyecto de ingeniería. 8. Incorporar Certificado SERVIU. 9. Anexar Participación Ciudadana. 10. Incorporar Informe Técnico Situación Actual. 11. Adjuntar Documentación al BIP. | N80: Se encuentra dentro de los de la ERD en - lineamientos: Conectividad y Movilidad Regional Sustentable. - Ítem Conectividad insular y de lugares aislados. - Obj.: Disminuir el déficit de infraestructura de conectividad para territorios insulares y aislados de la región. | O80: Se enlaza con el Programa Regional del Gobernador en el - Pilar: 2. Desarrollo Económico Sostenible: una Alianza Público-Privada. - Letra: c) Inversiones en Infraestructura: Mejorar la conectividad y la infraestructura regional para atraer inversiones y generar empleo. | P80: 349 | Q80: 348 | R80: =SUM(P80:Q80) -> 697 | T80: Municipalidad Puerto Varas | U80: Municipalidad Puerto Varas | V80: 908 | W80: 46260 | AA80: 46262 | AB80: =WORKDAY(AA80,15,'Feriados y Comunas'!A$2:A$25) -> 46283 | AH80: 2694 | AI80: 46275 | AJ80: 46290 | AK80: OBSERVADO | AQ80: 2694 | AR80: 46275 | AU80: OBSERVADO | AV80: OK | AW80: 9
A81: =1+A80 -> 80 | B81: 40024992 | C81: 0 | D81: Construcción Gimnasio Polivalente | E81: Queilén | F81: =+IFERROR(VLOOKUP(E81,'Feriados y Comunas'!$C$1:$D$36,2,FALSE),"") -> CHILOÉ | G81: 46282 | H81: 2096619 | I81: Ejecución | J81: 2027 | K81: Deporte | L81: Comité 25-09-26. 1. Adjuntar Financiamiento compartido. 2. Adjuntar Documentación al BIP. | N81: Se encuentra dentro de la ERD en, - Lineamiento: Bienestar Socio Territorial. - Ítem: Educación. - Objetivo: Mejorar el desempeño de los establecimientos educacionales públicos y subvencionados de la Región . - Actividad: No hay. | O81: Se enlaza con el Programa Regional del Gobernador en el lineamiento - Pilar: 3. Inclusión Social y Mejoramiento de la Calidad de Vida. - Letra: i) Infraestructura Educativa: Renovar y construir nuevas instalaciones educativas para garantizar ambientes de aprendizaje adecuados. | P81: 96 | Q81: 92 | R81: =SUM(P81:Q81) -> 188 | T81: Municipalidad Queilen | U81: Municipalidad Queilen | V81: 846 | W81: 46281 | AA81: 46282 | AB81: =WORKDAY(AA81,15,'Feriados y Comunas'!A$2:A$25) -> 46303 | AH81: 2935 | AI81: 46294 | AJ81: 46290 | AK81: OBSERVADO | AQ81: 2935 | AR81: 46294 | AU81: OBSERVADO | AV81: OK | AW81: 6
A82: =1+A81 -> 81 | F82: =+IFERROR(VLOOKUP(E82,'Feriados y Comunas'!$C$1:$D$36,2,FALSE),"")
A83: =1+A82 -> 82 | F83: =+IFERROR(VLOOKUP(E83,'Feriados y Comunas'!$C$1:$D$36,2,FALSE),"")
A84: =1+A83 -> 83 | F84: =+IFERROR(VLOOKUP(E84,'Feriados y Comunas'!$C$1:$D$36,2,FALSE),"")
A85: =1+A84 -> 84 | F85: =+IFERROR(VLOOKUP(E85,'Feriados y Comunas'!$C$1:$D$36,2,FALSE),"")
A86: =1+A85 -> 85 | F86: =+IFERROR(VLOOKUP(E86,'Feriados y Comunas'!$C$1:$D$36,2,FALSE),"")
A87: =1+A86 -> 86 | F87: =+IFERROR(VLOOKUP(E87,'Feriados y Comunas'!$C$1:$D$36,2,FALSE),"")
A88: =1+A87 -> 87 | F88: =+IFERROR(VLOOKUP(E88,'Feriados y Comunas'!$C$1:$D$36,2,FALSE),"")
A89: =1+A88 -> 88 | F89: =+IFERROR(VLOOKUP(E89,'Feriados y Comunas'!$C$1:$D$36,2,FALSE),"")
A90: =1+A89 -> 89 | F90: =+IFERROR(VLOOKUP(E90,'Feriados y Comunas'!$C$1:$D$36,2,FALSE),"")
A91: =1+A90 -> 90 | F91: =+IFERROR(VLOOKUP(E91,'Feriados y Comunas'!$C$1:$D$36,2,FALSE),"")
A92: =1+A91 -> 91 | F92: =+IFERROR(VLOOKUP(E92,'Feriados y Comunas'!$C$1:$D$36,2,FALSE),"")
A93: =1+A92 -> 92 | F93: =+IFERROR(VLOOKUP(E93,'Feriados y Comunas'!$C$1:$D$36,2,FALSE),"")
... A115: =1+A114 -> 114 | F115: =+IFERROR(VLOOKUP(E115,'Feriados y Comunas'!$C$1:$D$36,2,FALSE),"")
M164: =SUM(M5:M163) -> 0

Sheet Feriados y Comunas
A1: Feriados | C1: Comuna | D1: PROVINCIA
A2: 45292 | C2: Puerto Montt | D2: LLANQUIHUE
A3: 45380 | C3: Puerto Varas | D3: LLANQUIHUE
A4: 45413 | C4: Cochamó | D4: LLANQUIHUE
A5: 45433 | C5: Calbuco | D5: LLANQUIHUE
A6: 45463 | C6: Maullín | D6: LLANQUIHUE
A7: 45489 | C7: Los Muermos | D7: LLANQUIHUE
A8: 45519 | C8: Fresia | D8: LLANQUIHUE
A9: 45553 | C9: Llanquihue | D9: LLANQUIHUE
A10: 45554 | C10: Frutillar | D10: LLANQUIHUE
A11: 45579 | C11: Prov. Llanquihue | D11: LLANQUIHUE
A12: 45596 | C12: Ancud | D12: CHILOÉ
A13: 45597 | C13: Castro | D13: CHILOÉ
... A35: 46381 | C35: Prov. Palena | D35: PALENA
C36: Regional | D36: REGIONAL
